Workbook

Sheet 00_Control
A1: Grayson Swim Site - master control
A2: Private master workbook. Do not publish this workbook to the public GitHub repository.
A4: Setting | B4: Value | C4: Purpose
A5: Workbook version | B5: 3.0 | C5: All-event Grayson consistency build; canonical swimmer IDs reconciled
A6: Build date | B6: 46305 | C6: Current build date
A7: Consistency analysis start | B7: 45292 | C7: Fixed start date requested by user
A8: Progression maximum age | B8: Through age 20 (<21.0 exact age) | C8: Do not plot comparison performances after age 20
A9: Progression population | B9: Male only | C9: Comparison page scope
A10: Exact age denominator | B10: 365.2425 | C10: Days per tropical year approximation
A11: Margin formula | B11: (next-fastest - record) / next-fastest | C11: Percent faster than next-fastest different swimmer
A12: Next-fastest rule | B12: Different swimmer | C12: Own previous record is not an eligible comparator
A13: Joint record rule | B13: 0% vs joint holder | C13: Another joint record holder is the next-fastest different swimmer
A14: Public DOB policy | B14: Do not export DOBs | C14: DOB retained only in private master workbook
A15: Trend selection | B15: Cross-validated parsimonious best fit | C15: Leave-one-meet-out where meet identifiers are available
A16: All-event consistency scope | B16: All Grayson SCM/LCM event-course combinations with a swim since 1 Jan 2024 | C16: Dynamic from SwimCloud all-event history plus audited supplements
A18: Trend model candidates
A19: Model | B19: Horizontal asymptote? | C19: Role
A20: Linear | B20: No | C20: Transparent baseline
A21: Quadratic | B21: No | C21: Captures curvature but can turn unrealistically
A22: Logarithmic | B22: No | C22: Diminishing improvement; no true floor
A23: Asymptotic exponential | B23: Yes | C23: Biologically plausible flattening curve
A24: Stretched exponential | B24: Yes | C24: Flexible asymptotic curve
A25: Smoothing spline | B25: No explicit | C25: Descriptive benchmark; avoid using for extrapolation
A28: Acquisition status
A29: Item | B29: Value | C29: Status
A30: SwimCloud API v6 | B30: 19 profiles / 152 target event calls / 126 non-empty event histories / 2,834 raw swims | C30: Complete
A31: NZSC 2026 all-event supplement source | B31: https://swimdadnz.github.io/NZSC_2026/ | C31: Used only for Grayson meet swims not yet present in SwimCloud at acquisition time.
A32: Grayson canonical selected-event swims | B32: 101 | C32: Complete for eight requested events
A33: Grayson all-event consistency | B33: See included v7 Grayson-only acquisition | C33: Pending additional acquisition

Sheet 01_Swimmers
A1: Swimmers
A2: Canonical swimmer table. Exact DOB is private and is not exported to the website.
A4: SwimmerID | B4: Display Name | C4: Full Name | D4: Sex | E4: DOB | F4: Group | G4: Nation | H4: Club | I4: Public Flag
A5: SW001 | B5: Grayson Coulter | C5: Grayson Coulter | D5: M | E5: 40925 | F5: Grayson | I5: YES
A6: SW002 | B6: Miron Bunakov | C6: Miron Bunakov | D6: M | E6: 40800 | F6: Current age group star | I6: YES
A7: SW003 | B7: Luka Mijatovic | C7: Luka Mijatovic | D7: M | E7: 39925 | F7: Current age group star | I7: YES
A8: SW004 | B8: Lubo Liu-Tchorbadjiyski | C8: Lubo Liu-Tchorbadjiyski | D8: M | E8: 40836 | F8: Current age group star | I8: YES
A9: SW005 | B9: Thomas Heilman | C9: Thomas Heilman | D9: M | E9: 39120 | F9: Current age group star | I9: YES
A10: SW006 | B10: Tajus Juska | C10: Tajus Juska | D10: M | E10: 39830 | F10: Current age group star | I10: YES
A11: SW007 | B11: Laon Kim | C11: Laon Kim | D11: M | E11: 39591 | F11: Current age group star | I11: YES
A12: SW008 | B12: Jacob Whittle | C12: Jacob Whittle | D12: M | E12: 38255 | F12: Historical champion | I12: YES
A13: SW009 | B13: David Popovici | C13: David Popovici | D13: M | E13: 38245 | F13: Historical champion | I13: YES
A14: SW010 | B14: Caeleb Dressel | C14: Caeleb Dressel | D14: M | E14: 35293 | F14: Historical champion | I14: YES
A15: SW011 | B15: Kyle Chalmers | C15: Kyle Chalmers | D15: M | E15: 35971 | F15: Historical champion | I15: YES
A16: SW012 | B16: Flynn Southam | C16: Flynn Southam | D16: M | E16: 38508 | F16: Historical champion | I16: YES
... A22: SW018 | B22: Kristof Milak | C22: Kristof Milak | D22: M | E22: 36576 | F22: Historical champion | I22: YES

Sheet 02_Swimmer_Sources
A1: Swimmer sources
A2: One swimmer can have multiple source profiles. Grayson's two SwimCloud profiles map to one canonical swimmer.
A4: SwimmerID | B4: Display Name | C4: Source | D4: External ID | E4: URL | F4: Active | G4: Notes
A5: SW001 | B5: Grayson Coulter | C5: SwimCloud | D5: 3637780 | E5: https://www.swimcloud.com/swimmer/3637780/ | F5: YES
A6: SW001 | B6: Grayson Coulter | C6: SwimCloud | D6: 3651023 | E6: https://www.swimcloud.com/swimmer/3651023/ | F6: YES
A7: SW002 | B7: Miron Bunakov | C7: SwimCloud | D7: 3360584 | E7: https://www.swimcloud.com/swimmer/3360584/ | F7: YES
A8: SW003 | B8: Luka Mijatovic | C8: SwimCloud | D8: 2415996 | E8: https://www.swimcloud.com/swimmer/2415996/ | F8: YES
A9: SW004 | B9: Lubo Liu-Tchorbadjiyski | C9: SwimCloud | D9: 3102544 | E9: https://www.swimcloud.com/swimmer/3102544/ | F9: YES
A10: SW005 | B10: Thomas Heilman | C10: SwimCloud | D10: 1336401 | E10: https://www.swimcloud.com/swimmer/1336401/ | F10: YES
A11: SW006 | B11: Tajus Juska | C11: SwimCloud | D11: 2116196 | E11: https://www.swimcloud.com/swimmer/2116196/ | F11: YES
A12: SW007 | B12: Laon Kim | C12: SwimCloud | D12: 2829279 | E12: https://www.swimcloud.com/swimmer/2829279/ | F12: YES
A13: SW008 | B13: Jacob Whittle | C13: SwimCloud | D13: 1133535 | E13: https://www.swimcloud.com/swimmer/1133535/ | F13: YES
A14: SW009 | B14: David Popovici | C14: SwimCloud | D14: 1405298 | E14: https://www.swimcloud.com/swimmer/1405298/ | F14: YES
A15: SW010 | B15: Caeleb Dressel | C15: SwimCloud | D15: 2361642 | E15: https://www.swimcloud.com/swimmer/2361642/ | F15: YES
A16: SW011 | B16: Kyle Chalmers | C16: SwimCloud | D16: 419989 | E16: https://www.swimcloud.com/swimmer/419989/ | F16: YES
... A23: SW018 | B23: Kristof Milak | C23: SwimCloud | D23: 508643 | E23: https://www.swimcloud.com/swimmer/508643/ | F23: YES

Sheet 03_Events
A1: Events
A2: Standard LCM/SCM event dimension. Progression Flag identifies the eight requested comparison charts.
A4: EventID | B4: Course | C4: Distance | D4: Stroke | E4: Event | F4: Display Name | G4: Progression Flag | H4: Consistency Flag
A5: LCM_50_BACK | B5: LCM | C5: 50 | D5: Back | E5: 50 Back | F5: 50 Back LCM | G5: NO | H5: YES
A6: LCM_50_BREAST | B6: LCM | C6: 50 | D6: Breast | E6: 50 Breast | F6: 50 Breast LCM | G6: NO | H6: YES
A7: LCM_50_FLY | B7: LCM | C7: 50 | D7: Fly | E7: 50 Fly | F7: 50 Fly LCM | G7: NO | H7: YES
A8: LCM_50_FREE | B8: LCM | C8: 50 | D8: Free | E8: 50 Free | F8: 50 Free LCM | G8: NO | H8: YES
A9: LCM_100_BACK | B9: LCM | C9: 100 | D9: Back | E9: 100 Back | F9: 100 Back LCM | G9: NO | H9: YES
A10: LCM_100_BREAST | B10: LCM | C10: 100 | D10: Breast | E10: 100 Breast | F10: 100 Breast LCM | G10: NO | H10: YES
A11: LCM_100_FLY | B11: LCM | C11: 100 | D11: Fly | E11: 100 Fly | F11: 100 Fly LCM | G11: YES | H11: YES
A12: LCM_100_FREE | B12: LCM | C12: 100 | D12: Free | E12: 100 Free | F12: 100 Free LCM | G12: YES | H12: YES
A13: LCM_100_IM | B13: LCM | C13: 100 | D13: IM | E13: 100 IM | F13: 100 IM LCM | G13: NO | H13: YES
A14: LCM_200_BACK | B14: LCM | C14: 200 | D14: Back | E14: 200 Back | F14: 200 Back LCM | G14: NO | H14: YES
A15: LCM_200_BREAST | B15: LCM | C15: 200 | D15: Breast | E15: 200 Breast | F15: 200 Breast LCM | G15: NO | H15: YES
A16: LCM_200_FLY | B16: LCM | C16: 200 | D16: Fly | E16: 200 Fly | F16: 200 Fly LCM | G16: NO | H16: YES
... A40: SCM_1500_FREE | B40: SCM | C40: 1500 | D40: Free | E40: 1500 Free | F40: 1500 Free SCM | G40: NO | H40: YES

Sheet 04_Swims
A1: Swims
A2: Normalized performance database. One row per legal performance; Grayson's two SwimCloud profiles are merged to one canonical swimmer. Formula helper columns support the consistency analysis.
A4: SwimID | B4: SwimmerID | C4: Display Name | D4: Source | E4: Source Profile ID | F4: Source Race ID | G4: Swim Date | H4: Meet | I4: Meet ID | J4: Session | K4: Round | L4: Round Order | M4: Course | N4: Distance | O4: Stroke | P4: Event | Q4: EventID | R4: Time Seconds | S4: Time Display | T4: Exact Age | U4: Age Year | V4: Relay Lead-off | W4: Legal | X4: Exhibition | Y4: Heat | Z4: Lane | AA4: Place | AB4: Source URL | AC4: Acquisition Batch | AD4: Duplicate Key | AE4: Race Order | AF4: Prior Faster Count | AG4: Top 5 At Time | AH4: Top 10 At Time | AI4: In Consistency Window | AJ4: QC Status
A5: SM000001 | B5: SW010 | C5: Caeleb Dressel | D5: SwimCloud | E5: 2361642 | F5: 88639280 | G5: 37757 | H5: 2003 Bolles School Sharks LC Invite | I5: 251562 | K5: TIM | L5: =IF(K5="FIN",3,IF(OR(K5="SEM",K5="SEMI"),2,IF(OR(K5="PRE",K5="HEAT"),1,IF(V5="YES",4,2)))) | M5: LCM | N5: 100 | O5: Free | P5: 100 Free | Q5: LCM_100_FREE | R5: 104.58 | S5: =IF(R5="","",IF(R5>=60,INT(R5/60)&":"&TEXT(MOD(R5,60),"00.00"),TEXT(R5,"0.00"))) | T5: =IFERROR((G5-INDEX('01_Swimmers'!$E$5:$E$22,MATCH(B5,'01_Swimmers'!$A$5:$A$22,0)))/'00_Control'!$B$10,"") | U5: =IF(T5="","",INT(T5)) | V5: NO | W5: YES | X5: NO | Y5: 1 | Z5: 7 | AA5: 3 | AB5: https://www.swimcloud.com/results/251562/event/50/?id=88639280#time88639280 | AC5: SwimCloud API v6 2026-10-08 | AD5: Caeleb Dressel|2003-05-16|LCM|100|Free|104.58|2003 Bolles School Sharks LC Invite|TIM|False | AE5: =G5+L5/1000+ROW()/1000000000 | AF5: =IF(C5<>"Grayson Coulter","",COUNTIFS($C$5:$C$2991,"Grayson Coulter",$Q$5:$Q$2991,Q5,$AE$5:$AE$2991,"<="&AE5,$R$5:$R$2991,"<"&R5)) | AG5: =IF(OR(C5<>"Grayson Coulter",G5<'00_Control'!$B$7),"",--(AF5<5)) | AH5: =IF(OR(C5<>"Grayson Coulter",G5<'00_Control'!$B$7),"",--(AF5<10)) | AI5: =IF(AND(C5="Grayson Coulter",G5>='00_Control'!$B$7),"YES","NO") | AJ5: OK
A6: SM000002 | B6: SW010 | C6: Caeleb Dressel | D6: SwimCloud | E6: 2361642 | F6: 86946527 | G6: 38492 | H6: 2005 MARLIN MAY MEET | I6: 250113 | K6: TIM | L6: =IF(K6="FIN",3,IF(OR(K6="SEM",K6="SEMI"),2,IF(OR(K6="PRE",K6="HEAT"),1,IF(V6="YES",4,2)))) | M6: LCM | N6: 100 | O6: Free | P6: 100 Free | Q6: LCM_100_FREE | R6: 78.49 | S6: =IF(R6="","",IF(R6>=60,INT(R6/60)&":"&TEXT(MOD(R6,60),"00.00"),TEXT(R6,"0.00"))) | T6: =IFERROR((G6-INDEX('01_Swimmers'!$E$5:$E$22,MATCH(B6,'01_Swimmers'!$A$5:$A$22,0)))/'00_Control'!$B$10,"") | U6: =IF(T6="","",INT(T6)) | V6: NO | W6: YES | X6: NO | Y6: 2 | Z6: 8 | AA6: 1 | AB6: https://www.swimcloud.com/results/250113/event/6/?id=86946527#time86946527 | AC6: SwimCloud API v6 2026-10-08 | AD6: Caeleb Dressel|2005-05-20|LCM|100|Free|78.49|2005 MARLIN MAY MEET|TIM|False | AE6: =G6+L6/1000+ROW()/1000000000 | AF6: =IF(C6<>"Grayson Coulter","",COUNTIFS($C$5:$C$2991,"Grayson Coulter",$Q$5:$Q$2991,Q6,$AE$5:$AE$2991,"<="&AE6,$R$5:$R$2991,"<"&R6)) | AG6: =IF(OR(C6<>"Grayson Coulter",G6<'00_Control'!$B$7),"",--(AF6<5)) | AH6: =IF(OR(C6<>"Grayson Coulter",G6<'00_Control'!$B$7),"",--(AF6<10)) | AI6: =IF(AND(C6="Grayson Coulter",G6>='00_Control'!$B$7),"YES","NO") | AJ6: OK
A7: SM000003 | B7: SW010 | C7: Caeleb Dressel | D7: SwimCloud | E7: 2361642 | F7: 86926540 | G7: 38512 | H7: Daytona Beach Swimming 2005 Su | I7: 250102 | K7: TIM | L7: =IF(K7="FIN",3,IF(OR(K7="SEM",K7="SEMI"),2,IF(OR(K7="PRE",K7="HEAT"),1,IF(V7="YES",4,2)))) | M7: LCM | N7: 100 | O7: Free | P7: 100 Free | Q7: LCM_100_FREE | R7: 81.26 | S7: =IF(R7="","",IF(R7>=60,INT(R7/60)&":"&TEXT(MOD(R7,60),"00.00"),TEXT(R7,"0.00"))) | T7: =IFERROR((G7-INDEX('01_Swimmers'!$E$5:$E$22,MATCH(B7,'01_Swimmers'!$A$5:$A$22,0)))/'00_Control'!$B$10,"") | U7: =IF(T7="","",INT(T7)) | V7: NO | W7: YES | X7: NO | Y7: 1 | Z7: 2 | AA7: 8 | AB7: https://www.swimcloud.com/results/250102/event/112/?id=86926540#time86926540 | AC7: SwimCloud API v6 2026-10-08 | AD7: Caeleb Dressel|2005-06-09|LCM|100|Free|81.26|Daytona Beach Swimming 2005 Su|TIM|False | AE7: =G7+L7/1000+ROW()/1000000000 | AF7: =IF(C7<>"Grayson Coulter","",COUNTIFS($C$5:$C$2991,"Grayson Coulter",$Q$5:$Q$2991,Q7,$AE$5:$AE$2991,"<="&AE7,$R$5:$R$2991,"<"&R7)) | AG7: =IF(OR(C7<>"Grayson Coulter",G7<'00_Control'!$B$7),"",--(AF7<5)) | AH7: =IF(OR(C7<>"Grayson Coulter",G7<'00_Control'!$B$7),"",--(AF7<10)) | AI7: =IF(AND(C7="Grayson Coulter",G7>='00_Control'!$B$7),"YES","NO") | AJ7: OK
A8: SM000004 | B8: SW010 | C8: Caeleb Dressel | D8: SwimCloud | E8: 2361642 | F8: 85685937 | G8: 38836 | H8: Highlander Long Course Invitat | I8: 248680 | K8: TIM | L8: =IF(K8="FIN",3,IF(OR(K8="SEM",K8="SEMI"),2,IF(OR(K8="PRE",K8="HEAT"),1,IF(V8="YES",4,2)))) | M8: LCM | N8: 100 | O8: Free | P8: 100 Free | Q8: LCM_100_FREE | R8: 70.27 | S8: =IF(R8="","",IF(R8>=60,INT(R8/60)&":"&TEXT(MOD(R8,60),"00.00"),TEXT(R8,"0.00"))) | T8: =IFERROR((G8-INDEX('01_Swimmers'!$E$5:$E$22,MATCH(B8,'01_Swimmers'!$A$5:$A$22,0)))/'00_Control'!$B$10,"") | U8: =IF(T8="","",INT(T8)) | V8: NO | W8: YES | X8: NO | Y8: 5 | Z8: 4 | AA8: 2 | AB8: https://www.swimcloud.com/results/248680/event/38/?id=85685937#time85685937 | AC8: SwimCloud API v6 2026-10-08 | AD8: Caeleb Dressel|2006-04-29|LCM|100|Free|70.27|Highlander Long Course Invitat|TIM|False | AE8: =G8+L8/1000+ROW()/1000000000 | AF8: =IF(C8<>"Grayson Coulter","",COUNTIFS($C$5:$C$2991,"Grayson Coulter",$Q$5:$Q$2991,Q8,$AE$5:$AE$2991,"<="&AE8,$R$5:$R$2991,"<"&R8)) | AG8: =IF(OR(C8<>"Grayson Coulter",G8<'00_Control'!$B$7),"",--(AF8<5)) | AH8: =IF(OR(C8<>"Grayson Coulter",G8<'00_Control'!$B$7),"",--(AF8<10)) | AI8: =IF(AND(C8="Grayson Coulter",G8>='00_Control'!$B$7),"YES","NO") | AJ8: OK
A9: SM000005 | B9: SW010 | C9: Caeleb Dressel | D9: SwimCloud | E9: 2361642 | F9: 85654045 | G9: 38857 | H9: 2006 FL Marlin May Meet | I9: 248665 | K9: TIM | L9: =IF(K9="FIN",3,IF(OR(K9="SEM",K9="SEMI"),2,IF(OR(K9="PRE",K9="HEAT"),1,IF(V9="YES",4,2)))) | M9: LCM | N9: 100 | O9: Free | P9: 100 Free | Q9: LCM_100_FREE | R9: 70.59 | S9: =IF(R9="","",IF(R9>=60,INT(R9/60)&":"&TEXT(MOD(R9,60),"00.00"),TEXT(R9,"0.00"))) | T9: =IFERROR((G9-INDEX('01_Swimmers'!$E$5:$E$22,MATCH(B9,'01_Swimmers'!$A$5:$A$22,0)))/'00_Control'!$B$10,"") | U9: =IF(T9="","",INT(T9)) | V9: NO | W9: YES | X9: NO | Y9: 4 | Z9: 4 | AA9: 1 | AB9: https://www.swimcloud.com/results/248665/event/6/?id=85654045#time85654045 | AC9: SwimCloud API v6 2026-10-08 | AD9: Caeleb Dressel|2006-05-20|LCM|100|Free|70.59|2006 FL Marlin May Meet|TIM|False | AE9: =G9+L9/1000+ROW()/1000000000 | AF9: =IF(C9<>"Grayson Coulter","",COUNTIFS($C$5:$C$2991,"Grayson Coulter",$Q$5:$Q$2991,Q9,$AE$5:$AE$2991,"<="&AE9,$R$5:$R$2991,"<"&R9)) | AG9: =IF(OR(C9<>"Grayson Coulter",G9<'00_Control'!$B$7),"",--(AF9<5)) | AH9: =IF(OR(C9<>"Grayson Coulter",G9<'00_Control'!$B$7),"",--(AF9<10)) | AI9: =IF(AND(C9="Grayson Coulter",G9>='00_Control'!$B$7),"YES","NO") | AJ9: OK
A10: SM000006 | B10: SW010 | C10: Caeleb Dressel | D10: SwimCloud | E10: 2361642 | F10: 85608130 | G10: 38878 | H10: 2006 Stonewood Invitational | I10: 248614 | K10: TIM | L10: =IF(K10="FIN",3,IF(OR(K10="SEM",K10="SEMI"),2,IF(OR(K10="PRE",K10="HEAT"),1,IF(V10="YES",4,2)))) | M10: LCM | N10: 100 | O10: Fly | P10: 100 Fly | Q10: LCM_100_FLY | R10: 79.55 | S10: =IF(R10="","",IF(R10>=60,INT(R10/60)&":"&TEXT(MOD(R10,60),"00.00"),TEXT(R10,"0.00"))) | T10: =IFERROR((G10-INDEX('01_Swimmers'!$E$5:$E$22,MATCH(B10,'01_Swimmers'!$A$5:$A$22,0)))/'00_Control'!$B$10,"") | U10: =IF(T10="","",INT(T10)) | V10: NO | W10: YES | X10: NO | Y10: 3 | Z10: 4 | AA10: 1 | AB10: https://www.swimcloud.com/results/248614/event/78/?id=85608130#time85608130 | AC10: SwimCloud API v6 2026-10-08 | AD10: Caeleb Dressel|2006-06-10|LCM|100|Fly|79.55|2006 Stonewood Invitational|TIM|False | AE10: =G10+L10/1000+ROW()/1000000000 | AF10: =IF(C10<>"Grayson Coulter","",COUNTIFS($C$5:$C$2991,"Grayson Coulter",$Q$5:$Q$2991,Q10,$AE$5:$AE$2991,"<="&AE10,$R$5:$R$2991,"<"&R10)) | AG10: =IF(OR(C10<>"Grayson Coulter",G10<'00_Control'!$B$7),"",--(AF10<5)) | AH10: =IF(OR(C10<>"Grayson Coulter",G10<'00_Control'!$B$7),"",--(AF10<10)) | AI10: =IF(AND(C10="Grayson Coulter",G10>='00_Control'!$B$7),"YES","NO") | AJ10: OK
A11: SM000007 | B11: SW010 | C11: Caeleb Dressel | D11: SwimCloud | E11: 2361642 | F11: 85607143 | G11: 38878 | H11: 2006 Stonewood Invitational | I11: 248614 | K11: TIM | L11: =IF(K11="FIN",3,IF(OR(K11="SEM",K11="SEMI"),2,IF(OR(K11="PRE",K11="HEAT"),1,IF(V11="YES",4,2)))) | M11: LCM | N11: 100 | O11: Free | P11: 100 Free | Q11: LCM_100_FREE | R11: 67.97 | S11: =IF(R11="","",IF(R11>=60,INT(R11/60)&":"&TEXT(MOD(R11,60),"00.00"),TEXT(R11,"0.00"))) | T11: =IFERROR((G11-INDEX('01_Swimmers'!$E$5:$E$22,MATCH(B11,'01_Swimmers'!$A$5:$A$22,0)))/'00_Control'!$B$10,"") | U11: =IF(T11="","",INT(T11)) | V11: NO | W11: YES | X11: NO | Y11: 6 | Z11: 4 | AA11: 1 | AB11: https://www.swimcloud.com/results/248614/event/82/?id=85607143#time85607143 | AC11: SwimCloud API v6 2026-10-08 | AD11: Caeleb Dressel|2006-06-10|LCM|100|Free|67.97|2006 Stonewood Invitational|TIM|False | AE11: =G11+L11/1000+ROW()/1000000000 | AF11: =IF(C11<>"Grayson Coulter","",COUNTIFS($C$5:$C$2991,"Grayson Coulter",$Q$5:$Q$2991,Q11,$AE$5:$AE$2991,"<="&AE11,$R$5:$R$2991,"<"&R11)) | AG11: =IF(OR(C11<>"Grayson Coulter",G11<'00_Control'!$B$7),"",--(AF11<5)) | AH11: =IF(OR(C11<>"Grayson Coulter",G11<'00_Control'!$B$7),"",--(AF11<10)) | AI11: =IF(AND(C11="Grayson Coulter",G11>='00_Control'!$B$7),"YES","NO") | AJ11: OK
A12: SM000008 | B12: SW010 | C12: Caeleb Dressel | D12: SwimCloud | E12: 2361642 | F12: 85544054 | G12: 38897 | H12: Speedo Summer Classic LC Invit | I12: 248588 | K12: TIM | L12: =IF(K12="FIN",3,IF(OR(K12="SEM",K12="SEMI"),2,IF(OR(K12="PRE",K12="HEAT"),1,IF(V12="YES",4,2)))) | M12: LCM | N12: 400 | O12: Free | P12: 400 Free | Q12: LCM_400_FREE | R12: 318.65 | S12: =IF(R12="","",IF(R12>=60,INT(R12/60)&":"&TEXT(MOD(R12,60),"00.00"),TEXT(R12,"0.00"))) | T12: =IFERROR((G12-INDEX('01_Swimmers'!$E$5:$E$22,MATCH(B12,'01_Swimmers'!$A$5:$A$22,0)))/'00_Control'!$B$10,"") | U12: =IF(T12="","",INT(T12)) | V12: NO | W12: YES | X12: NO | Y12: 1 | Z12: 6 | AA12: 1 | AB12: https://www.swimcloud.com/results/248588/event/2/?id=85544054#time85544054 | AC12: SwimCloud API v6 2026-10-08 | AD12: Caeleb Dressel|2006-06-29|LCM|400|Free|318.65|Speedo Summer Classic LC Invit|TIM|False | AE12: =G12+L12/1000+ROW()/1000000000 | AF12: =IF(C12<>"Grayson Coulter","",COUNTIFS($C$5:$C$2991,"Grayson Coulter",$Q$5:$Q$2991,Q12,$AE$5:$AE$2991,"<="&AE12,$R$5:$R$2991,"<"&R12)) | AG12: =IF(OR(C12<>"Grayson Coulter",G12<'00_Control'!$B$7),"",--(AF12<5)) | AH12: =IF(OR(C12<>"Grayson Coulter",G12<'00_Control'!$B$7),"",--(AF12<10)) | AI12: =IF(AND(C12="Grayson Coulter",G12>='00_Control'!$B$7),"YES","NO") | AJ12: OK
A13: SM000009 | B13: SW010 | C13: Caeleb Dressel | D13: SwimCloud | E13: 2361642 | F13: 85543634 | G13: 38898 | H13: Speedo Summer Classic LC Invit | I13: 248588 | K13: TIM | L13: =IF(K13="FIN",3,IF(OR(K13="SEM",K13="SEMI"),2,IF(OR(K13="PRE",K13="HEAT"),1,IF(V13="YES",4,2)))) | M13: LCM | N13: 200 | O13: Free | P13: 200 Free | Q13: LCM_200_FREE | R13: 150.46 | S13: =IF(R13="","",IF(R13>=60,INT(R13/60)&":"&TEXT(MOD(R13,60),"00.00"),TEXT(R13,"0.00"))) | T13: =IFERROR((G13-INDEX('01_Swimmers'!$E$5:$E$22,MATCH(B13,'01_Swimmers'!$A$5:$A$22,0)))/'00_Control'!$B$10,"") | U13: =IF(T13="","",INT(T13)) | V13: NO | W13: YES | X13: NO | Y13: 2 | Z13: 4 | AA13: 1 | AB13: https://www.swimcloud.com/results/248588/event/34/?id=85543634#time85543634 | AC13: SwimCloud API v6 2026-10-08 | AD13: Caeleb Dressel|2006-06-30|LCM|200|Free|150.46|Speedo Summer Classic LC Invit|TIM|False | AE13: =G13+L13/1000+ROW()/1000000000 | AF13: =IF(C13<>"Grayson Coulter","",COUNTIFS($C$5:$C$2991,"Grayson Coulter",$Q$5:$Q$2991,Q13,$AE$5:$AE$2991,"<="&AE13,$R$5:$R$2991,"<"&R13)) | AG13: =IF(OR(C13<>"Grayson Coulter",G13<'00_Control'!$B$7),"",--(AF13<5)) | AH13: =IF(OR(C13<>"Grayson Coulter",G13<'00_Control'!$B$7),"",--(AF13<10)) | AI13: =IF(AND(C13="Grayson Coulter",G13>='00_Control'!$B$7),"YES","NO") | AJ13: OK
A14: SM000010 | B14: SW010 | C14: Caeleb Dressel | D14: SwimCloud | E14: 2361642 | F14: 85435502 | G14: 38918 | H14: 2006 LC JO Championships | I14: 248449 | K14: TIM | L14: =IF(K14="FIN",3,IF(OR(K14="SEM",K14="SEMI"),2,IF(OR(K14="PRE",K14="HEAT"),1,IF(V14="YES",4,2)))) | M14: LCM | N14: 400 | O14: Free | P14: 400 Free | Q14: LCM_400_FREE | R14: 316.79 | S14: =IF(R14="","",IF(R14>=60,INT(R14/60)&":"&TEXT(MOD(R14,60),"00.00"),TEXT(R14,"0.00"))) | T14: =IFERROR((G14-INDEX('01_Swimmers'!$E$5:$E$22,MATCH(B14,'01_Swimmers'!$A$5:$A$22,0)))/'00_Control'!$B$10,"") | U14: =IF(T14="","",INT(T14)) | V14: NO | W14: YES | X14: NO | Y14: 1 | Z14: 2 | AA14: 8 | AB14: https://www.swimcloud.com/results/248449/event/2/?id=85435502#time85435502 | AC14: SwimCloud API v6 2026-10-08 | AD14: Caeleb Dressel|2006-07-20|LCM|400|Free|316.79|2006 LC JO Championships|TIM|False | AE14: =G14+L14/1000+ROW()/1000000000 | AF14: =IF(C14<>"Grayson Coulter","",COUNTIFS($C$5:$C$2991,"Grayson Coulter",$Q$5:$Q$2991,Q14,$AE$5:$AE$2991,"<="&AE14,$R$5:$R$2991,"<"&R14)) | AG14: =IF(OR(C14<>"Grayson Coulter",G14<'00_Control'!$B$7),"",--(AF14<5)) | AH14: =IF(OR(C14<>"Grayson Coulter",G14<'00_Control'!$B$7),"",--(AF14<10)) | AI14: =IF(AND(C14="Grayson Coulter",G14>='00_Control'!$B$7),"YES","NO") | AJ14: OK
A15: SM000011 | B15: SW010 | C15: Caeleb Dressel | D15: SwimCloud | E15: 2361642 | F15: 85435532 | G15: 38919 | H15: 2006 LC JO Championships | I15: 248449 | K15: TIM | L15: =IF(K15="FIN",3,IF(OR(K15="SEM",K15="SEMI"),2,IF(OR(K15="PRE",K15="HEAT"),1,IF(V15="YES",4,2)))) | M15: LCM | N15: 200 | O15: Free | P15: 200 Free | Q15: LCM_200_FREE | R15: 147.05 | S15: =IF(R15="","",IF(R15>=60,INT(R15/60)&":"&TEXT(MOD(R15,60),"00.00"),TEXT(R15,"0.00"))) | T15: =IFERROR((G15-INDEX('01_Swimmers'!$E$5:$E$22,MATCH(B15,'01_Swimmers'!$A$5:$A$22,0)))/'00_Control'!$B$10,"") | U15: =IF(T15="","",INT(T15)) | V15: NO | W15: YES | X15: NO | Y15: 5 | Z15: 2 | AA15: 5 | AB15: https://www.swimcloud.com/results/248449/event/18/?id=85435532#time85435532 | AC15: SwimCloud API v6 2026-10-08 | AD15: Caeleb Dressel|2006-07-21|LCM|200|Free|147.05|2006 LC JO Championships|TIM|False | AE15: =G15+L15/1000+ROW()/1000000000 | AF15: =IF(C15<>"Grayson Coulter","",COUNTIFS($C$5:$C$2991,"Grayson Coulter",$Q$5:$Q$2991,Q15,$AE$5:$AE$2991,"<="&AE15,$R$5:$R$2991,"<"&R15)) | AG15: =IF(OR(C15<>"Grayson Coulter",G15<'00_Control'!$B$7),"",--(AF15<5)) | AH15: =IF(OR(C15<>"Grayson Coulter",G15<'00_Control'!$B$7),"",--(AF15<10)) | AI15: =IF(AND(C15="Grayson Coulter",G15>='00_Control'!$B$7),"YES","NO") | AJ15: OK
A16: SM000012 | B16: SW010 | C16: Caeleb Dressel | D16: SwimCloud | E16: 2361642 | F16: 85435649 | G16: 38921 | H16: 2006 LC JO Championships | I16: 248449 | K16: TIM | L16: =IF(K16="FIN",3,IF(OR(K16="SEM",K16="SEMI"),2,IF(OR(K16="PRE",K16="HEAT"),1,IF(V16="YES",4,2)))) | M16: LCM | N16: 100 | O16: Free | P16: 100 Free | Q16: LCM_100_FREE | R16: 66.82 | S16: =IF(R16="","",IF(R16>=60,INT(R16/60)&":"&TEXT(MOD(R16,60),"00.00"),TEXT(R16,"0.00"))) | T16: =IFERROR((G16-INDEX('01_Swimmers'!$E$5:$E$22,MATCH(B16,'01_Swimmers'!$A$5:$A$22,0)))/'00_Control'!$B$10,"") | U16: =IF(T16="","",INT(T16)) | V16: NO | W16: YES | X16: NO | Y16: 5 | Z16: 3 | AA16: 3 | AB16: https://www.swimcloud.com/results/248449/event/84/?id=85435649#time85435649 | AC16: SwimCloud API v6 2026-10-08 | AD16: Caeleb Dressel|2006-07-23|LCM|100|Free|66.82|2006 LC JO Championships|TIM|False | AE16: =G16+L16/1000+ROW()/1000000000 | AF16: =IF(C16<>"Grayson Coulter","",COUNTIFS($C$5:$C$2991,"Grayson Coulter",$Q$5:$Q$2991,Q16,$AE$5:$AE$2991,"<="&AE16,$R$5:$R$2991,"<"&R16)) | AG16: =IF(OR(C16<>"Grayson Coulter",G16<'00_Control'!$B$7),"",--(AF16<5)) | AH16: =IF(OR(C16<>"Grayson Coulter",G16<'00_Control'!$B$7),"",--(AF16<10)) | AI16: =IF(AND(C16="Grayson Coulter",G16>='00_Control'!$B$7),"YES","NO") | AJ16: OK
... A67: SM000063 | B67: SW010 | C67: Caeleb Dressel | D67: SwimCloud | E67: 2361642 | F67: 2503929 | G67: 40949 | H67: USA Swimming Grand Prix - Missouri (18 & Under Times) | I67: 18544 | K67: PRE | L67: =IF(K67="FIN",3,IF(OR(K67="SEM",K67="SEMI"),2,IF(OR(K67="PRE",K67="HEAT"),1,IF(V67="YES",4,2)))) | M67: LCM | N67: 200 | O67: Free | P67: 200 Free | Q67: LCM_200_FREE | R67: 120.5 | S67: =IF(R67="","",IF(R67>=60,INT(R67/60)&":"&TEXT(MOD(R67,60),"00.00"),TEXT(R67,"0.00"))) | T67: =IFERROR((G67-INDEX('01_Swimmers'!$E$5:$E$22,MATCH(B67,'01_Swimmers'!$A$5:$A$22,0)))/'00_Control'!$B$10,"") | U67: =IF(T67="","",INT(T67)) | V67: NO | W67: YES | X67: NO | Y67: 2 | Z67: 1 | AA67: 79 | AB67: https://www.swimcloud.com/results/18544/event/2/?id=2503929#time2503929 | AC67: SwimCloud API v6 2026-10-08 | AD67: Caeleb Dressel|2012-02-10|LCM|200|Free|120.5|USA Swimming Grand Prix - Missouri (18 & Under Times)|PRE|False | AE67: =G67+L67/1000+ROW()/1000000000 | AF67: =IF(C67<>"Grayson Coulter","",COUNTIFS($C$5:$C$2991,"Grayson Coulter",$Q$5:$Q$2991,Q67,$AE$5:$AE$2991,"<="&AE67,$R$5:$R$2991,"<"&R67)) | AG67: =IF(OR(C67<>"Grayson Coulter",G67<'00_Control'!$B$7),"",--(AF67<5)) | AH67: =IF(OR(C67<>"Grayson Coulter",G67<'00_Control'!$B$7),"",--(AF67<10)) | AI67: =IF(AND(C67="Grayson Coulter",G67>='00_Control'!$B$7),"YES","NO") | AJ67: OK
A68: SM000064 | B68: SW010 | C68: Caeleb Dressel | D68: SwimCloud | E68: 2361642 | F68: 2504706 | G68: 40950 | H68: USA Swimming Grand Prix - Missouri (18 & Under Times) | I68: 18544 | K68: TIM | L68: =IF(K68="FIN",3,IF(OR(K68="SEM",K68="SEMI"),2,IF(OR(K68="PRE",K68="HEAT"),1,IF(V68="YES",4,2)))) | M68: LCM | N68: 200 | O68: Free | P68: 200 Free | Q68: LCM_200_FREE | R68: 118.7 | S68: =IF(R68="","",IF(R68>=60,INT(R68/60)&":"&TEXT(MOD(R68,60),"00.00"),TEXT(R68,"0.00"))) | T68: =IFERROR((G68-INDEX('01_Swimmers'!$E$5:$E$22,MATCH(B68,'01_Swimmers'!$A$5:$A$22,0)))/'00_Control'!$B$10,"") | U68: =IF(T68="","",INT(T68)) | V68: YES | W68: YES | X68: NO | Y68: 2 | Z68: 6 | AB68: https://www.swimcloud.com/results/18544/event/22/?id=2504412#time2504412 | AC68: SwimCloud API v6 2026-10-08 | AD68: Caeleb Dressel|2012-02-11|LCM|200|Free|118.7|USA Swimming Grand Prix - Missouri (18 & Under Times)|TIM|True | AE68: =G68+L68/1000+ROW()/1000000000 | AF68: =IF(C68<>"Grayson Coulter","",COUNTIFS($C$5:$C$2991,"Grayson Coulter",$Q$5:$Q$2991,Q68,$AE$5:$AE$2991,"<="&AE68,$R$5:$R$2991,"<"&R68)) | AG68: =IF(OR(C68<>"Grayson Coulter",G68<'00_Control'!$B$7),"",--(AF68<5)) | AH68: =IF(OR(C68<>"Grayson Coulter",G68<'00_Control'!$B$7),"",--(AF68<10)) | AI68: =IF(AND(C68="Grayson Coulter",G68>='00_Control'!$B$7),"YES","NO") | AJ68: OK
A69: SM000065 | B69: SW010 | C69: Caeleb Dressel | D69: SwimCloud | E69: 2361642 | F69: 2502723 | G69: 40951 | H69: USA Swimming Grand Prix - Missouri (18 & Under Times) | I69: 18544 | K69: PRE | L69: =IF(K69="FIN",3,IF(OR(K69="SEM",K69="SEMI"),2,IF(OR(K69="PRE",K69="HEAT"),1,IF(V69="YES",4,2)))) | M69: LCM | N69: 100 | O69: Free | P69: 100 Free | Q69: LCM_100_FREE | R69: 52.54 | S69: =IF(R69="","",IF(R69>=60,INT(R69/60)&":"&TEXT(MOD(R69,60),"00.00"),TEXT(R69,"0.00"))) | T69: =IFERROR((G69-INDEX('01_Swimmers'!$E$5:$E$22,MATCH(B69,'01_Swimmers'!$A$5:$A$22,0)))/'00_Control'!$B$10,"") | U69: =IF(T69="","",INT(T69)) | V69: NO | W69: YES | X69: NO | Y69: 10 | Z69: 6 | AA69: 28 | AB69: https://www.swimcloud.com/results/18544/event/30/?id=2502723#time2502723 | AC69: SwimCloud API v6 2026-10-08 | AD69: Caeleb Dressel|2012-02-12|LCM|100|Free|52.54|USA Swimming Grand Prix - Missouri (18 & Under Times)|PRE|False | AE69: =G69+L69/1000+ROW()/1000000000 | AF69: =IF(C69<>"Grayson Coulter","",COUNTIFS($C$5:$C$2991,"Grayson Coulter",$Q$5:$Q$2991,Q69,$AE$5:$AE$2991,"<="&AE69,$R$5:$R$2991,"<"&R69)) | AG69: =IF(OR(C69<>"Grayson Coulter",G69<'00_Control'!$B$7),"",--(AF69<5)) | AH69: =IF(OR(C69<>"Grayson Coulter",G69<'00_Control'!$B$7),"",--(AF69<10)) | AI69: =IF(AND(C69="Grayson Coulter",G69>='00_Control'!$B$7),"YES","NO") | AJ69: OK
A70: SM000066 | B70: SW010 | C70: Caeleb Dressel | D70: SwimCloud | E70: 2361642 | F70: 2502766 | G70: 40951 | H70: USA Swimming Grand Prix - Missouri (18 & Under Times) | I70: 18544 | K70: FIN | L70: =IF(K70="FIN",3,IF(OR(K70="SEM",K70="SEMI"),2,IF(OR(K70="PRE",K70="HEAT"),1,IF(V70="YES",4,2)))) | M70: LCM | N70: 100 | O70: Free | P70: 100 Free | Q70: LCM_100_FREE | R70: 52.48 | S70: =IF(R70="","",IF(R70>=60,INT(R70/60)&":"&TEXT(MOD(R70,60),"00.00"),TEXT(R70,"0.00"))) | T70: =IFERROR((G70-INDEX('01_Swimmers'!$E$5:$E$22,MATCH(B70,'01_Swimmers'!$A$5:$A$22,0)))/'00_Control'!$B$10,"") | U70: =IF(T70="","",INT(T70)) | V70: NO | W70: YES | X70: NO | Y70: 1 | Z70: 8 | AA70: 22 | AB70: https://www.swimcloud.com/results/18544/event/30/?id=2502766#time2502766 | AC70: SwimCloud API v6 2026-10-08 | AD70: Caeleb Dressel|2012-02-12|LCM|100|Free|52.48|USA Swimming Grand Prix - Missouri (18 & Under Times)|FIN|False | AE70: =G70+L70/1000+ROW()/1000000000 | AF70: =IF(C70<>"Grayson Coulter","",COUNTIFS($C$5:$C$2991,"Grayson Coulter",$Q$5:$Q$2991,Q70,$AE$5:$AE$2991,"<="&AE70,$R$5:$R$2991,"<"&R70)) | AG70: =IF(OR(C70<>"Grayson Coulter",G70<'00_Control'!$B$7),"",--(AF70<5)) | AH70: =IF(OR(C70<>"Grayson Coulter",G70<'00_Control'!$B$7),"",--(AF70<10)) | AI70: =IF(AND(C70="Grayson Coulter",G70>='00_Control'!$B$7),"YES","NO") | AJ70: OK
A71: SM000067 | B71: SW010 | C71: Caeleb Dressel | D71: SwimCloud | E71: 2361642 | F71: 2757659 | G71: 40984 | H71: Speedo Champions Series - Orlando, FL (18 & Under) | I71: 18896 | K71: PRE | L71: =IF(K71="FIN",3,IF(OR(K71="SEM",K71="SEMI"),2,IF(OR(K71="PRE",K71="HEAT"),1,IF(V71="YES",4,2)))) | M71: LCM | N71: 100 | O71: Fly | P71: 100 Fly | Q71: LCM_100_FLY | R71: 59.72 | S71: =IF(R71="","",IF(R71>=60,INT(R71/60)&":"&TEXT(MOD(R71,60),"00.00"),TEXT(R71,"0.00"))) | T71: =IFERROR((G71-INDEX('01_Swimmers'!$E$5:$E$22,MATCH(B71,'01_Swimmers'!$A$5:$A$22,0)))/'00_Control'!$B$10,"") | U71: =IF(T71="","",INT(T71)) | V71: NO | W71: YES | X71: NO | Y71: 20 | Z71: 8 | AA71: 55 | AB71: https://www.swimcloud.com/results/18896/event/12/?id=2757659#time2757659 | AC71: SwimCloud API v6 2026-10-08 | AD71: Caeleb Dressel|2012-03-16|LCM|100|Fly|59.72|Speedo Champions Series - Orlando, FL (18 & Under)|PRE|False | AE71: =G71+L71/1000+ROW()/1000000000 | AF71: =IF(C71<>"Grayson Coulter","",COUNTIFS($C$5:$C$2991,"Grayson Coulter",$Q$5:$Q$2991,Q71,$AE$5:$AE$2991,"<="&AE71,$R$5:$R$2991,"<"&R71)) | AG71: =IF(OR(C71<>"Grayson Coulter",G71<'00_Control'!$B$7),"",--(AF71<5)) | AH71: =IF(OR(C71<>"Grayson Coulter",G71<'00_Control'!$B$7),"",--(AF71<10)) | AI71: =IF(AND(C71="Grayson Coulter",G71>='00_Control'!$B$7),"YES","NO") | AJ71: OK
A72: SM000068 | B72: SW010 | C72: Caeleb Dressel | D72: SwimCloud | E72: 2361642 | F72: 2758506 | G72: 40984 | H72: Speedo Champions Series - Orlando, FL (18 & Under) | I72: 18896 | K72: PRE | L72: =IF(K72="FIN",3,IF(OR(K72="SEM",K72="SEMI"),2,IF(OR(K72="PRE",K72="HEAT"),1,IF(V72="YES",4,2)))) | M72: LCM | N72: 200 | O72: Free | P72: 200 Free | Q72: LCM_200_FREE | R72: 116.65 | S72: =IF(R72="","",IF(R72>=60,INT(R72/60)&":"&TEXT(MOD(R72,60),"00.00"),TEXT(R72,"0.00"))) | T72: =IFERROR((G72-INDEX('01_Swimmers'!$E$5:$E$22,MATCH(B72,'01_Swimmers'!$A$5:$A$22,0)))/'00_Control'!$B$10,"") | U72: =IF(T72="","",INT(T72)) | V72: NO | W72: YES | X72: NO | Y72: 5 | Z72: 5 | AA72: 29 | AB72: https://www.swimcloud.com/results/18896/event/8/?id=2758506#time2758506 | AC72: SwimCloud API v6 2026-10-08 | AD72: Caeleb Dressel|2012-03-16|LCM|200|Free|116.65|Speedo Champions Series - Orlando, FL (18 & Under)|PRE|False | AE72: =G72+L72/1000+ROW()/1000000000 | AF72: =IF(C72<>"Grayson Coulter","",COUNTIFS($C$5:$C$2991,"Grayson Coulter",$Q$5:$Q$2991,Q72,$AE$5:$AE$2991,"<="&AE72,$R$5:$R$2991,"<"&R72)) | AG72: =IF(OR(C72<>"Grayson Coulter",G72<'00_Control'!$B$7),"",--(AF72<5)) | AH72: =IF(OR(C72<>"Grayson Coulter",G72<'00_Control'!$B$7),"",--(AF72<10)) | AI72: =IF(AND(C72="Grayson Coulter",G72>='00_Control'!$B$7),"YES","NO") | AJ72: OK
A73: SM000069 | B73: SW010 | C73: Caeleb Dressel | D73: SwimCloud | E73: 2361642 | F73: 2758582 | G73: 40984 | H73: Speedo Champions Series - Orlando, FL (18 & Under) | I73: 18896 | K73: FIN | L73: =IF(K73="FIN",3,IF(OR(K73="SEM",K73="SEMI"),2,IF(OR(K73="PRE",K73="HEAT"),1,IF(V73="YES",4,2)))) | M73: LCM | N73: 200 | O73: Free | P73: 200 Free | Q73: LCM_200_FREE | R73: 114.88 | S73: =IF(R73="","",IF(R73>=60,INT(R73/60)&":"&TEXT(MOD(R73,60),"00.00"),TEXT(R73,"0.00"))) | T73: =IFERROR((G73-INDEX('01_Swimmers'!$E$5:$E$22,MATCH(B73,'01_Swimmers'!$A$5:$A$22,0)))/'00_Control'!$B$10,"") | U73: =IF(T73="","",INT(T73)) | V73: NO | W73: YES | X73: NO | Y73: 3 | Z73: 2 | AA73: 18 | AB73: https://www.swimcloud.com/results/18896/event/8/?id=2758582#time2758582 | AC73: SwimCloud API v6 2026-10-08 | AD73: Caeleb Dressel|2012-03-16|LCM|200|Free|114.88|Speedo Champions Series - Orlando, FL (18 & Under)|FIN|False | AE73: =G73+L73/1000+ROW()/1000000000 | AF73: =IF(C73<>"Grayson Coulter","",COUNTIFS($C$5:$C$2991,"Grayson Coulter",$Q$5:$Q$2991,Q73,$AE$5:$AE$2991,"<="&AE73,$R$5:$R$2991,"<"&R73)) | AG73: =IF(OR(C73<>"Grayson Coulter",G73<'00_Control'!$B$7),"",--(AF73<5)) | AH73: =IF(OR(C73<>"Grayson Coulter",G73<'00_Control'!$B$7),"",--(AF73<10)) | AI73: =IF(AND(C73="Grayson Coulter",G73>='00_Control'!$B$7),"YES","NO") | AJ73: OK
A74: SM000070 | B74: SW010 | C74: Caeleb Dressel | D74: SwimCloud | E74: 2361642 | F74: 2757894 | G74: 40986 | H74: Speedo Champions Series - Orlando, FL (18 & Under) | I74: 18896 | K74: PRE | L74: =IF(K74="FIN",3,IF(OR(K74="SEM",K74="SEMI"),2,IF(OR(K74="PRE",K74="HEAT"),1,IF(V74="YES",4,2)))) | M74: LCM | N74: 100 | O74: Free | P74: 100 Free | Q74: LCM_100_FREE | R74: 52.65 | S74: =IF(R74="","",IF(R74>=60,INT(R74/60)&":"&TEXT(MOD(R74,60),"00.00"),TEXT(R74,"0.00"))) | T74: =IFERROR((G74-INDEX('01_Swimmers'!$E$5:$E$22,MATCH(B74,'01_Swimmers'!$A$5:$A$22,0)))/'00_Control'!$B$10,"") | U74: =IF(T74="","",INT(T74)) | V74: NO | W74: YES | X74: NO | Y74: 22 | Z74: 5 | AA74: 20 | AB74: https://www.swimcloud.com/results/18896/event/30/?id=2757894#time2757894 | AC74: SwimCloud API v6 2026-10-08 | AD74: Caeleb Dressel|2012-03-18|LCM|100|Free|52.65|Speedo Champions Series - Orlando, FL (18 & Under)|PRE|False | AE74: =G74+L74/1000+ROW()/1000000000 | AF74: =IF(C74<>"Grayson Coulter","",COUNTIFS($C$5:$C$2991,"Grayson Coulter",$Q$5:$Q$2991,Q74,$AE$5:$AE$2991,"<="&AE74,$R$5:$R$2991,"<"&R74)) | AG74: =IF(OR(C74<>"Grayson Coulter",G74<'00_Control'!$B$7),"",--(AF74<5)) | AH74: =IF(OR(C74<>"Grayson Coulter",G74<'00_Control'!$B$7),"",--(AF74<10)) | AI74: =IF(AND(C74="Grayson Coulter",G74>='00_Control'!$B$7),"YES","NO") | AJ74: OK
A75: SM000071 | B75: SW010 | C75: Caeleb Dressel | D75: SwimCloud | E75: 2361642 | F75: 2757959 | G75: 40986 | H75: Speedo Champions Series - Orlando, FL (18 & Under) | I75: 18896 | K75: FIN | L75: =IF(K75="FIN",3,IF(OR(K75="SEM",K75="SEMI"),2,IF(OR(K75="PRE",K75="HEAT"),1,IF(V75="YES",4,2)))) | M75: LCM | N75: 100 | O75: Free | P75: 100 Free | Q75: LCM_100_FREE | R75: 52.1 | S75: =IF(R75="","",IF(R75>=60,INT(R75/60)&":"&TEXT(MOD(R75,60),"00.00"),TEXT(R75,"0.00"))) | T75: =IFERROR((G75-INDEX('01_Swimmers'!$E$5:$E$22,MATCH(B75,'01_Swimmers'!$A$5:$A$22,0)))/'00_Control'!$B$10,"") | U75: =IF(T75="","",INT(T75)) | V75: NO | W75: YES | X75: NO | Y75: 3 | Z75: 5 | AA75: 18 | AB75: https://www.swimcloud.com/results/18896/event/30/?id=2757959#time2757959 | AC75: SwimCloud API v6 2026-10-08 | AD75: Caeleb Dressel|2012-03-18|LCM|100|Free|52.1|Speedo Champions Series - Orlando, FL (18 & Under)|FIN|False | AE75: =G75+L75/1000+ROW()/1000000000 | AF75: =IF(C75<>"Grayson Coulter","",COUNTIFS($C$5:$C$2991,"Grayson Coulter",$Q$5:$Q$2991,Q75,$AE$5:$AE$2991,"<="&AE75,$R$5:$R$2991,"<"&R75)) | AG75: =IF(OR(C75<>"Grayson Coulter",G75<'00_Control'!$B$7),"",--(AF75<5)) | AH75: =IF(OR(C75<>"Grayson Coulter",G75<'00_Control'!$B$7),"",--(AF75<10)) | AI75: =IF(AND(C75="Grayson Coulter",G75>='00_Control'!$B$7),"YES","NO") | AJ75: OK
A76: SM000072 | B76: SW010 | C76: Caeleb Dressel | D76: SwimCloud | E76: 2361642 | F76: 28175934 | G76: 41086 | H76: USA Olympic Team Trials | I76: 149710 | K76: PRE | L76: =IF(K76="FIN",3,IF(OR(K76="SEM",K76="SEMI"),2,IF(OR(K76="PRE",K76="HEAT"),1,IF(V76="YES",4,2)))) | M76: LCM | N76: 200 | O76: Free | P76: 200 Free | Q76: LCM_200_FREE | R76: 115.17 | S76: =IF(R76="","",IF(R76>=60,INT(R76/60)&":"&TEXT(MOD(R76,60),"00.00"),TEXT(R76,"0.00"))) | T76: =IFERROR((G76-INDEX('01_Swimmers'!$E$5:$E$22,MATCH(B76,'01_Swimmers'!$A$5:$A$22,0)))/'00_Control'!$B$10,"") | U76: =IF(T76="","",INT(T76)) | V76: NO | W76: YES | X76: NO | Y76: 6 | Z76: 1 | AA76: 121 | AB76: https://www.swimcloud.com/results/149710/event/7/?id=28175934#time28175934 | AC76: SwimCloud API v6 2026-10-08 | AD76: Caeleb Dressel|2012-06-26|LCM|200|Free|115.17|USA Olympic Team Trials|PRE|False | AE76: =G76+L76/1000+ROW()/1000000000 | AF76: =IF(C76<>"Grayson Coulter","",COUNTIFS($C$5:$C$2991,"Grayson Coulter",$Q$5:$Q$2991,Q76,$AE$5:$AE$2991,"<="&AE76,$R$5:$R$2991,"<"&R76)) | AG76: =IF(OR(C76<>"Grayson Coulter",G76<'00_Control'!$B$7),"",--(AF76<5)) | AH76: =IF(OR(C76<>"Grayson Coulter",G76<'00_Control'!$B$7),"",--(AF76<10)) | AI76: =IF(AND(C76="Grayson Coulter",G76>='00_Control'!$B$7),"YES","NO") | AJ76: OK
A77: SM000073 | B77: SW010 | C77: Caeleb Dressel | D77: SwimCloud | E77: 2361642 | F77: 28175935 | G77: 41088 | H77: USA Olympic Team Trials | I77: 149710 | K77: PRE | L77: =IF(K77="FIN",3,IF(OR(K77="SEM",K77="SEMI"),2,IF(OR(K77="PRE",K77="HEAT"),1,IF(V77="YES",4,2)))) | M77: LCM | N77: 100 | O77: Free | P77: 100 Free | Q77: LCM_100_FREE | R77: 52.21 | S77: =IF(R77="","",IF(R77>=60,INT(R77/60)&":"&TEXT(MOD(R77,60),"00.00"),TEXT(R77,"0.00"))) | T77: =IFERROR((G77-INDEX('01_Swimmers'!$E$5:$E$22,MATCH(B77,'01_Swimmers'!$A$5:$A$22,0)))/'00_Control'!$B$10,"") | U77: =IF(T77="","",INT(T77)) | V77: NO | W77: YES | X77: NO | Y77: 3 | Z77: 4 | AA77: 152 | AB77: https://www.swimcloud.com/results/149710/event/14/?id=28175935#time28175935 | AC77: SwimCloud API v6 2026-10-08 | AD77: Caeleb Dressel|2012-06-28|LCM|100|Free|52.21|USA Olympic Team Trials|PRE|False | AE77: =G77+L77/1000+ROW()/1000000000 | AF77: =IF(C77<>"Grayson Coulter","",COUNTIFS($C$5:$C$2991,"Grayson Coulter",$Q$5:$Q$2991,Q77,$AE$5:$AE$2991,"<="&AE77,$R$5:$R$2991,"<"&R77)) | AG77: =IF(OR(C77<>"Grayson Coulter",G77<'00_Control'!$B$7),"",--(AF77<5)) | AH77: =IF(OR(C77<>"Grayson Coulter",G77<'00_Control'!$B$7),"",--(AF77<10)) | AI77: =IF(AND(C77="Grayson Coulter",G77>='00_Control'!$B$7),"YES","NO") | AJ77: OK
A78: SM000074 | B78: SW010 | C78: Caeleb Dressel | D78: SwimCloud | E78: 2361642 | F78: 28175938 | G78: 41090 | H78: USA Olympic Team Trials | I78: 149710 | K78: PRE | L78: =IF(K78="FIN",3,IF(OR(K78="SEM",K78="SEMI"),2,IF(OR(K78="PRE",K78="HEAT"),1,IF(V78="YES",4,2)))) | M78: LCM | N78: 100 | O78: Fly | P78: 100 Fly | Q78: LCM_100_FLY | R78: 57.21 | S78: =IF(R78="","",IF(R78>=60,INT(R78/60)&":"&TEXT(MOD(R78,60),"00.00"),TEXT(R78,"0.00"))) | T78: =IFERROR((G78-INDEX('01_Swimmers'!$E$5:$E$22,MATCH(B78,'01_Swimmers'!$A$5:$A$22,0)))/'00_Control'!$B$10,"") | U78: =IF(T78="","",INT(T78)) | V78: NO | W78: YES | X78: NO | Y78: 2 | Z78: 8 | AA78: 121 | AB78: https://www.swimcloud.com/results/149710/event/23/?id=28175938#time28175938 | AC78: SwimCloud API v6 2026-10-08 | AD78: Caeleb Dressel|2012-06-30|LCM|100|Fly|57.21|USA Olympic Team Trials|PRE|False | AE78: =G78+L78/1000+ROW()/1000000000 | AF78: =IF(C78<>"Grayson Coulter","",COUNTIFS($C$5:$C$2991,"Grayson Coulter",$Q$5:$Q$2991,Q78,$AE$5:$AE$2991,"<="&AE78,$R$5:$R$2991,"<"&R78)) | AG78: =IF(OR(C78<>"Grayson Coulter",G78<'00_Control'!$B$7),"",--(AF78<5)) | AH78: =IF(OR(C78<>"Grayson Coulter",G78<'00_Control'!$B$7),"",--(AF78<10)) | AI78: =IF(AND(C78="Grayson Coulter",G78>='00_Control'!$B$7),"YES","NO") | AJ78: OK
A79: SM000075 | B79: SW010 | C79: Caeleb Dressel | D79: SwimCloud | E79: 2361642 | F79: 2839981 | G79: 41135 | H79: Speedo Junior National Championships (LCM) | I79: 18977 | K79: PRE | L79: =IF(K79="FIN",3,IF(OR(K79="SEM",K79="SEMI"),2,IF(OR(K79="PRE",K79="HEAT"),1,IF(V79="YES",4,2)))) | M79: LCM | N79: 100 | O79: Free | P79: 100 Free | Q79: LCM_100_FREE | R79: 50.85 | S79: =IF(R79="","",IF(R79>=60,INT(R79/60)&":"&TEXT(MOD(R79,60),"00.00"),TEXT(R79,"0.00"))) | T79: =IFERROR((G79-INDEX('01_Swimmers'!$E$5:$E$22,MATCH(B79,'01_Swimmers'!$A$5:$A$22,0)))/'00_Control'!$B$10,"") | U79: =IF(T79="","",INT(T79)) | V79: NO | W79: YES | X79: NO | Y79: 9 | Z79: 3 | AA79: 2 | AB79: https://www.swimcloud.com/results/18977/event/10/?id=2839981#time2839981 | AC79: SwimCloud API v6 2026-10-08 | AD79: Caeleb Dressel|2012-08-14|LCM|100|Free|50.85|Speedo Junior National Championships (LCM)|PRE|False | AE79: =G79+L79/1000+ROW()/1000000000 | AF79: =IF(C79<>"Grayson Coulter","",COUNTIFS($C$5:$C$2991,"Grayson Coulter",$Q$5:$Q$2991,Q79,$AE$5:$AE$2991,"<="&AE79,$R$5:$R$2991,"<"&R79)) | AG79: =IF(OR(C79<>"Grayson Coulter",G79<'00_Control'!$B$7),"",--(AF79<5)) | AH79: =IF(OR(C79<>"Grayson Coulter",G79<'00_Control'!$B$7),"",--(AF79<10)) | AI79: =IF(AND(C79="Grayson Coulter",G79>='00_Control'!$B$7),"YES","NO") | AJ79: OK
A80: SM000076 | B80: SW010 | C80: Caeleb Dressel | D80: SwimCloud | E80: 2361642 | F80: 2840047 | G80: 41135 | H80: Speedo Junior National Championships (LCM) | I80: 18977 | K80: FIN | L80: =IF(K80="FIN",3,IF(OR(K80="SEM",K80="SEMI"),2,IF(OR(K80="PRE",K80="HEAT"),1,IF(V80="YES",4,2)))) | M80: LCM | N80: 100 | O80: Free | P80: 100 Free | Q80: LCM_100_FREE | R80: 50.96 | S80: =IF(R80="","",IF(R80>=60,INT(R80/60)&":"&TEXT(MOD(R80,60),"00.00"),TEXT(R80,"0.00"))) | T80: =IFERROR((G80-INDEX('01_Swimmers'!$E$5:$E$22,MATCH(B80,'01_Swimmers'!$A$5:$A$22,0)))/'00_Control'!$B$10,"") | U80: =IF(T80="","",INT(T80)) | V80: NO | W80: YES | X80: NO | Y80: 3 | Z80: 5 | AA80: 2 | AB80: https://www.swimcloud.com/results/18977/event/10/?id=2840047#time2840047 | AC80: SwimCloud API v6 2026-10-08 | AD80: Caeleb Dressel|2012-08-14|LCM|100|Free|50.96|Speedo Junior National Championships (LCM)|FIN|False | AE80: =G80+L80/1000+ROW()/1000000000 | AF80: =IF(C80<>"Grayson Coulter","",COUNTIFS($C$5:$C$2991,"Grayson Coulter",$Q$5:$Q$2991,Q80,$AE$5:$AE$2991,"<="&AE80,$R$5:$R$2991,"<"&R80)) | AG80: =IF(OR(C80<>"Grayson Coulter",G80<'00_Control'!$B$7),"",--(AF80<5)) | AH80: =IF(OR(C80<>"Grayson Coulter",G80<'00_Control'!$B$7),"",--(AF80<10)) | AI80: =IF(AND(C80="Grayson Coulter",G80>='00_Control'!$B$7),"YES","NO") | AJ80: OK
... A126: SM000122 | B126: SW010 | C126: Caeleb Dressel | D126: SwimCloud | E126: 2361642 | F126: 6524247 | G126: 42197 | H126: Speedo Champions Series - Orlando | I126: 42623 | K126: FIN | L126: =IF(K126="FIN",3,IF(OR(K126="SEM",K126="SEMI"),2,IF(OR(K126="PRE",K126="HEAT"),1,IF(V126="YES",4,2)))) | M126: LCM | N126: 100 | O126: Free | P126: 100 Free | Q126: LCM_100_FREE | R126: 49.5 | S126: =IF(R126="","",IF(R126>=60,INT(R126/60)&":"&TEXT(MOD(R126,60),"00.00"),TEXT(R126,"0.00"))) | T126: =IFERROR((G126-INDEX('01_Swimmers'!$E$5:$E$22,MATCH(B126,'01_Swimmers'!$A$5:$A$22,0)))/'00_Control'!$B$10,"") | U126: =IF(T126="","",INT(T126)) | V126: NO | W126: YES | X126: NO | Y126: 1 | Z126: 4 | AA126: 1 | AB126: https://www.swimcloud.com/results/42623/event/36/?id=6524247#time6524247 | AC126: SwimCloud API v6 2026-10-08 | AD126: Caeleb Dressel|2015-07-12|LCM|100|Free|49.5|Speedo Champions Series - Orlando|FIN|False | AE126: =G126+L126/1000+ROW()/1000000000 | AF126: =IF(C126<>"Grayson Coulter","",COUNTIFS($C$5:$C$2991,"Grayson Coulter",$Q$5:$Q$2991,Q126,$AE$5:$AE$2991,"<="&AE126,$R$5:$R$2991,"<"&R126)) | AG126: =IF(OR(C126<>"Grayson Coulter",G126<'00_Control'!$B$7),"",--(AF126<5)) | AH126: =IF(OR(C126<>"Grayson Coulter",G126<'00_Control'!$B$7),"",--(AF126<10)) | AI126: =IF(AND(C126="Grayson Coulter",G126>='00_Control'!$B$7),"YES","NO") | AJ126: OK
A127: SM000123 | B127: SW010 | C127: Caeleb Dressel | D127: SwimCloud | E127: 2361642 | F127: 6432228 | G127: 42197 | H127: Southern Zone Senior Championships | I127: 39838 | K127: TIM | L127: =IF(K127="FIN",3,IF(OR(K127="SEM",K127="SEMI"),2,IF(OR(K127="PRE",K127="HEAT"),1,IF(V127="YES",4,2)))) | M127: LCM | N127: 100 | O127: Free | P127: 100 Free | Q127: LCM_100_FREE | R127: 49.64 | S127: =IF(R127="","",IF(R127>=60,INT(R127/60)&":"&TEXT(MOD(R127,60),"00.00"),TEXT(R127,"0.00"))) | T127: =IFERROR((G127-INDEX('01_Swimmers'!$E$5:$E$22,MATCH(B127,'01_Swimmers'!$A$5:$A$22,0)))/'00_Control'!$B$10,"") | U127: =IF(T127="","",INT(T127)) | V127: YES | W127: YES | X127: NO | Y127: 4 | Z127: 3 | AB127: https://www.swimcloud.com/results/39838/event/42/?id=6431280#time6431280 | AC127: SwimCloud API v6 2026-10-08 | AD127: Caeleb Dressel|2015-07-12|LCM|100|Free|49.64|Southern Zone Senior Championships|TIM|True | AE127: =G127+L127/1000+ROW()/1000000000 | AF127: =IF(C127<>"Grayson Coulter","",COUNTIFS($C$5:$C$2991,"Grayson Coulter",$Q$5:$Q$2991,Q127,$AE$5:$AE$2991,"<="&AE127,$R$5:$R$2991,"<"&R127)) | AG127: =IF(OR(C127<>"Grayson Coulter",G127<'00_Control'!$B$7),"",--(AF127<5)) | AH127: =IF(OR(C127<>"Grayson Coulter",G127<'00_Control'!$B$7),"",--(AF127<10)) | AI127: =IF(AND(C127="Grayson Coulter",G127>='00_Control'!$B$7),"YES","NO") | AJ127: OK
A128: SM000124 | B128: SW010 | C128: Caeleb Dressel | D128: SwimCloud | E128: 2361642 | F128: 6526141 | G128: 42197 | H128: Speedo Champions Series - Orlando | I128: 42623 | K128: TIM | L128: =IF(K128="FIN",3,IF(OR(K128="SEM",K128="SEMI"),2,IF(OR(K128="PRE",K128="HEAT"),1,IF(V128="YES",4,2)))) | M128: LCM | N128: 100 | O128: Free | P128: 100 Free | Q128: LCM_100_FREE | R128: 49.64 | S128: =IF(R128="","",IF(R128>=60,INT(R128/60)&":"&TEXT(MOD(R128,60),"00.00"),TEXT(R128,"0.00"))) | T128: =IFERROR((G128-INDEX('01_Swimmers'!$E$5:$E$22,MATCH(B128,'01_Swimmers'!$A$5:$A$22,0)))/'00_Control'!$B$10,"") | U128: =IF(T128="","",INT(T128)) | V128: YES | W128: YES | X128: NO | Y128: 4 | Z128: 3 | AB128: https://www.swimcloud.com/results/42623/event/42/?id=6525193#time6525193 | AC128: SwimCloud API v6 2026-10-08 | AD128: Caeleb Dressel|2015-07-12|LCM|100|Free|49.64|Speedo Champions Series - Orlando|TIM|True | AE128: =G128+L128/1000+ROW()/1000000000 | AF128: =IF(C128<>"Grayson Coulter","",COUNTIFS($C$5:$C$2991,"Grayson Coulter",$Q$5:$Q$2991,Q128,$AE$5:$AE$2991,"<="&AE128,$R$5:$R$2991,"<"&R128)) | AG128: =IF(OR(C128<>"Grayson Coulter",G128<'00_Control'!$B$7),"",--(AF128<5)) | AH128: =IF(OR(C128<>"Grayson Coulter",G128<'00_Control'!$B$7),"",--(AF128<10)) | AI128: =IF(AND(C128="Grayson Coulter",G128>='00_Control'!$B$7),"YES","NO") | AJ128: OK
A129: SM000125 | B129: SW010 | C129: Caeleb Dressel | D129: SwimCloud | E129: 2361642 | F129: 6358941 | G129: 42223 | H129: 2015 Phillips 66 National Championships | I129: 29376 | K129: PRE | L129: =IF(K129="FIN",3,IF(OR(K129="SEM",K129="SEMI"),2,IF(OR(K129="PRE",K129="HEAT"),1,IF(V129="YES",4,2)))) | M129: LCM | N129: 200 | O129: Free | P129: 200 Free | Q129: LCM_200_FREE | R129: 110.22 | S129: =IF(R129="","",IF(R129>=60,INT(R129/60)&":"&TEXT(MOD(R129,60),"00.00"),TEXT(R129,"0.00"))) | T129: =IFERROR((G129-INDEX('01_Swimmers'!$E$5:$E$22,MATCH(B129,'01_Swimmers'!$A$5:$A$22,0)))/'00_Control'!$B$10,"") | U129: =IF(T129="","",INT(T129)) | V129: NO | W129: YES | X129: NO | Y129: 11 | Z129: 6 | AA129: 20 | AB129: https://www.swimcloud.com/results/29376/event/9/?id=6358941#time6358941 | AC129: SwimCloud API v6 2026-10-08 | AD129: Caeleb Dressel|2015-08-07|LCM|200|Free|110.22|2015 Phillips 66 National Championships|PRE|False | AE129: =G129+L129/1000+ROW()/1000000000 | AF129: =IF(C129<>"Grayson Coulter","",COUNTIFS($C$5:$C$2991,"Grayson Coulter",$Q$5:$Q$2991,Q129,$AE$5:$AE$2991,"<="&AE129,$R$5:$R$2991,"<"&R129)) | AG129: =IF(OR(C129<>"Grayson Coulter",G129<'00_Control'!$B$7),"",--(AF129<5)) | AH129: =IF(OR(C129<>"Grayson Coulter",G129<'00_Control'!$B$7),"",--(AF129<10)) | AI129: =IF(AND(C129="Grayson Coulter",G129>='00_Control'!$B$7),"YES","NO") | AJ129: OK
A130: SM000126 | B130: SW010 | C130: Caeleb Dressel | D130: SwimCloud | E130: 2361642 | F130: 6358995 | G130: 42223 | H130: 2015 Phillips 66 National Championships | I130: 29376 | K130: FIN | L130: =IF(K130="FIN",3,IF(OR(K130="SEM",K130="SEMI"),2,IF(OR(K130="PRE",K130="HEAT"),1,IF(V130="YES",4,2)))) | M130: LCM | N130: 200 | O130: Free | P130: 200 Free | Q130: LCM_200_FREE | R130: 111.26 | S130: =IF(R130="","",IF(R130>=60,INT(R130/60)&":"&TEXT(MOD(R130,60),"00.00"),TEXT(R130,"0.00"))) | T130: =IFERROR((G130-INDEX('01_Swimmers'!$E$5:$E$22,MATCH(B130,'01_Swimmers'!$A$5:$A$22,0)))/'00_Control'!$B$10,"") | U130: =IF(T130="","",INT(T130)) | V130: NO | W130: YES | X130: NO | Y130: 1 | Z130: 4 | AA130: 21 | AB130: https://www.swimcloud.com/results/29376/event/9/?id=6358995#time6358995 | AC130: SwimCloud API v6 2026-10-08 | AD130: Caeleb Dressel|2015-08-07|LCM|200|Free|111.26|2015 Phillips 66 National Championships|FIN|False | AE130: =G130+L130/1000+ROW()/1000000000 | AF130: =IF(C130<>"Grayson Coulter","",COUNTIFS($C$5:$C$2991,"Grayson Coulter",$Q$5:$Q$2991,Q130,$AE$5:$AE$2991,"<="&AE130,$R$5:$R$2991,"<"&R130)) | AG130: =IF(OR(C130<>"Grayson Coulter",G130<'00_Control'!$B$7),"",--(AF130<5)) | AH130: =IF(OR(C130<>"Grayson Coulter",G130<'00_Control'!$B$7),"",--(AF130<10)) | AI130: =IF(AND(C130="Grayson Coulter",G130>='00_Control'!$B$7),"YES","NO") | AJ130: OK
A131: SM000127 | B131: SW010 | C131: Caeleb Dressel | D131: SwimCloud | E131: 2361642 | F131: 6357792 | G131: 42225 | H131: 2015 Phillips 66 National Championships | I131: 29376 | K131: PRE | L131: =IF(K131="FIN",3,IF(OR(K131="SEM",K131="SEMI"),2,IF(OR(K131="PRE",K131="HEAT"),1,IF(V131="YES",4,2)))) | M131: LCM | N131: 100 | O131: Free | P131: 100 Free | Q131: LCM_100_FREE | R131: 48.98 | S131: =IF(R131="","",IF(R131>=60,INT(R131/60)&":"&TEXT(MOD(R131,60),"00.00"),TEXT(R131,"0.00"))) | T131: =IFERROR((G131-INDEX('01_Swimmers'!$E$5:$E$22,MATCH(B131,'01_Swimmers'!$A$5:$A$22,0)))/'00_Control'!$B$10,"") | U131: =IF(T131="","",INT(T131)) | V131: NO | W131: YES | X131: NO | Y131: 7 | Z131: 7 | AA131: 1 | AB131: https://www.swimcloud.com/results/29376/event/20/?id=6357792#time6357792 | AC131: SwimCloud API v6 2026-10-08 | AD131: Caeleb Dressel|2015-08-09|LCM|100|Free|48.98|2015 Phillips 66 National Championships|PRE|False | AE131: =G131+L131/1000+ROW()/1000000000 | AF131: =IF(C131<>"Grayson Coulter","",COUNTIFS($C$5:$C$2991,"Grayson Coulter",$Q$5:$Q$2991,Q131,$AE$5:$AE$2991,"<="&AE131,$R$5:$R$2991,"<"&R131)) | AG131: =IF(OR(C131<>"Grayson Coulter",G131<'00_Control'!$B$7),"",--(AF131<5)) | AH131: =IF(OR(C131<>"Grayson Coulter",G131<'00_Control'!$B$7),"",--(AF131<10)) | AI131: =IF(AND(C131="Grayson Coulter",G131>='00_Control'!$B$7),"YES","NO") | AJ131: OK
A132: SM000128 | B132: SW010 | C132: Caeleb Dressel | D132: SwimCloud | E132: 2361642 | F132: 6357857 | G132: 42225 | H132: 2015 Phillips 66 National Championships | I132: 29376 | K132: FIN | L132: =IF(K132="FIN",3,IF(OR(K132="SEM",K132="SEMI"),2,IF(OR(K132="PRE",K132="HEAT"),1,IF(V132="YES",4,2)))) | M132: LCM | N132: 100 | O132: Free | P132: 100 Free | Q132: LCM_100_FREE | R132: 48.78 | S132: =IF(R132="","",IF(R132>=60,INT(R132/60)&":"&TEXT(MOD(R132,60),"00.00"),TEXT(R132,"0.00"))) | T132: =IFERROR((G132-INDEX('01_Swimmers'!$E$5:$E$22,MATCH(B132,'01_Swimmers'!$A$5:$A$22,0)))/'00_Control'!$B$10,"") | U132: =IF(T132="","",INT(T132)) | V132: NO | W132: YES | X132: NO | Y132: 3 | Z132: 4 | AA132: 1 | AB132: https://www.swimcloud.com/results/29376/event/20/?id=6357857#time6357857 | AC132: SwimCloud API v6 2026-10-08 | AD132: Caeleb Dressel|2015-08-09|LCM|100|Free|48.78|2015 Phillips 66 National Championships|FIN|False | AE132: =G132+L132/1000+ROW()/1000000000 | AF132: =IF(C132<>"Grayson Coulter","",COUNTIFS($C$5:$C$2991,"Grayson Coulter",$Q$5:$Q$2991,Q132,$AE$5:$AE$2991,"<="&AE132,$R$5:$R$2991,"<"&R132)) | AG132: =IF(OR(C132<>"Grayson Coulter",G132<'00_Control'!$B$7),"",--(AF132<5)) | AH132: =IF(OR(C132<>"Grayson Coulter",G132<'00_Control'!$B$7),"",--(AF132<10)) | AI132: =IF(AND(C132="Grayson Coulter",G132>='00_Control'!$B$7),"YES","NO") | AJ132: OK
A133: SM000129 | B133: SW010 | C133: Caeleb Dressel | D133: SwimCloud | E133: 2361642 | F133: 6969831 | G133: 42226 | H133: 2015 Phillips 66 National Championships Time Trials | I133: 54165 | K133: TIM | L133: =IF(K133="FIN",3,IF(OR(K133="SEM",K133="SEMI"),2,IF(OR(K133="PRE",K133="HEAT"),1,IF(V133="YES",4,2)))) | M133: LCM | N133: 100 | O133: Fly | P133: 100 Fly | Q133: LCM_100_FLY | R133: 52.99 | S133: =IF(R133="","",IF(R133>=60,INT(R133/60)&":"&TEXT(MOD(R133,60),"00.00"),TEXT(R133,"0.00"))) | T133: =IFERROR((G133-INDEX('01_Swimmers'!$E$5:$E$22,MATCH(B133,'01_Swimmers'!$A$5:$A$22,0)))/'00_Control'!$B$10,"") | U133: =IF(T133="","",INT(T133)) | V133: NO | W133: YES | X133: NO | Y133: 2 | Z133: 5 | AA133: 2 | AB133: https://www.swimcloud.com/results/54165/event/515/?id=6969831#time6969831 | AC133: SwimCloud API v6 2026-10-08 | AD133: Caeleb Dressel|2015-08-10|LCM|100|Fly|52.99|2015 Phillips 66 National Championships Time Trials|TIM|False | AE133: =G133+L133/1000+ROW()/1000000000 | AF133: =IF(C133<>"Grayson Coulter","",COUNTIFS($C$5:$C$2991,"Grayson Coulter",$Q$5:$Q$2991,Q133,$AE$5:$AE$2991,"<="&AE133,$R$5:$R$2991,"<"&R133)) | AG133: =IF(OR(C133<>"Grayson Coulter",G133<'00_Control'!$B$7),"",--(AF133<5)) | AH133: =IF(OR(C133<>"Grayson Coulter",G133<'00_Control'!$B$7),"",--(AF133<10)) | AI133: =IF(AND(C133="Grayson Coulter",G133>='00_Control'!$B$7),"YES","NO") | AJ133: OK
A134: SM000130 | B134: SW010 | C134: Caeleb Dressel | D134: SwimCloud | E134: 2361642 | F134: 7018901 | G134: 42293 | H134: Texas vs. Florida, Indiana - LCM | I134: 55151 | K134: TIM | L134: =IF(K134="FIN",3,IF(OR(K134="SEM",K134="SEMI"),2,IF(OR(K134="PRE",K134="HEAT"),1,IF(V134="YES",4,2)))) | M134: LCM | N134: 100 | O134: Fly | P134: 100 Fly | Q134: LCM_100_FLY | R134: 53.99 | S134: =IF(R134="","",IF(R134>=60,INT(R134/60)&":"&TEXT(MOD(R134,60),"00.00"),TEXT(R134,"0.00"))) | T134: =IFERROR((G134-INDEX('01_Swimmers'!$E$5:$E$22,MATCH(B134,'01_Swimmers'!$A$5:$A$22,0)))/'00_Control'!$B$10,"") | U134: =IF(T134="","",INT(T134)) | V134: NO | W134: YES | X134: NO | Y134: 2 | Z134: 2 | AA134: 1 | AB134: https://www.swimcloud.com/results/55151/event/24/?id=7018901#time7018901 | AC134: SwimCloud API v6 2026-10-08 | AD134: Caeleb Dressel|2015-10-16|LCM|100|Fly|53.99|Texas vs. Florida, Indiana - LCM|TIM|False | AE134: =G134+L134/1000+ROW()/1000000000 | AF134: =IF(C134<>"Grayson Coulter","",COUNTIFS($C$5:$C$2991,"Grayson Coulter",$Q$5:$Q$2991,Q134,$AE$5:$AE$2991,"<="&AE134,$R$5:$R$2991,"<"&R134)) | AG134: =IF(OR(C134<>"Grayson Coulter",G134<'00_Control'!$B$7),"",--(AF134<5)) | AH134: =IF(OR(C134<>"Grayson Coulter",G134<'00_Control'!$B$7),"",--(AF134<10)) | AI134: =IF(AND(C134="Grayson Coulter",G134>='00_Control'!$B$7),"YES","NO") | AJ134: OK
A135: SM000131 | B135: SW010 | C135: Caeleb Dressel | D135: SwimCloud | E135: 2361642 | F135: 7018887 | G135: 42293 | H135: Texas vs. Florida, Indiana - LCM | I135: 55151 | K135: TIM | L135: =IF(K135="FIN",3,IF(OR(K135="SEM",K135="SEMI"),2,IF(OR(K135="PRE",K135="HEAT"),1,IF(V135="YES",4,2)))) | M135: LCM | N135: 100 | O135: Free | P135: 100 Free | Q135: LCM_100_FREE | R135: 50.38 | S135: =IF(R135="","",IF(R135>=60,INT(R135/60)&":"&TEXT(MOD(R135,60),"00.00"),TEXT(R135,"0.00"))) | T135: =IFERROR((G135-INDEX('01_Swimmers'!$E$5:$E$22,MATCH(B135,'01_Swimmers'!$A$5:$A$22,0)))/'00_Control'!$B$10,"") | U135: =IF(T135="","",INT(T135)) | V135: NO | W135: YES | X135: NO | Y135: 2 | Z135: 5 | AA135: 2 | AB135: https://www.swimcloud.com/results/55151/event/16/?id=7018887#time7018887 | AC135: SwimCloud API v6 2026-10-08 | AD135: Caeleb Dressel|2015-10-16|LCM|100|Free|50.38|Texas vs. Florida, Indiana - LCM|TIM|False | AE135: =G135+L135/1000+ROW()/1000000000 | AF135: =IF(C135<>"Grayson Coulter","",COUNTIFS($C$5:$C$2991,"Grayson Coulter",$Q$5:$Q$2991,Q135,$AE$5:$AE$2991,"<="&AE135,$R$5:$R$2991,"<"&R135)) | AG135: =IF(OR(C135<>"Grayson Coulter",G135<'00_Control'!$B$7),"",--(AF135<5)) | AH135: =IF(OR(C135<>"Grayson Coulter",G135<'00_Control'!$B$7),"",--(AF135<10)) | AI135: =IF(AND(C135="Grayson Coulter",G135>='00_Control'!$B$7),"YES","NO") | AJ135: OK
A136: SM000132 | B136: SW010 | C136: Caeleb Dressel | D136: SwimCloud | E136: 2361642 | F136: 7067838 | G136: 42307 | H136: Florida vs. Georgia | I136: 55342 | K136: TIM | L136: =IF(K136="FIN",3,IF(OR(K136="SEM",K136="SEMI"),2,IF(OR(K136="PRE",K136="HEAT"),1,IF(V136="YES",4,2)))) | M136: LCM | N136: 100 | O136: Fly | P136: 100 Fly | Q136: LCM_100_FLY | R136: 55.07 | S136: =IF(R136="","",IF(R136>=60,INT(R136/60)&":"&TEXT(MOD(R136,60),"00.00"),TEXT(R136,"0.00"))) | T136: =IFERROR((G136-INDEX('01_Swimmers'!$E$5:$E$22,MATCH(B136,'01_Swimmers'!$A$5:$A$22,0)))/'00_Control'!$B$10,"") | U136: =IF(T136="","",INT(T136)) | V136: NO | W136: YES | X136: NO | Y136: 1 | Z136: 6 | AA136: 3 | AB136: https://www.swimcloud.com/results/55342/event/28/?id=7067838#time7067838 | AC136: SwimCloud API v6 2026-10-08 | AD136: Caeleb Dressel|2015-10-30|LCM|100|Fly|55.07|Florida vs. Georgia|TIM|False | AE136: =G136+L136/1000+ROW()/1000000000 | AF136: =IF(C136<>"Grayson Coulter","",COUNTIFS($C$5:$C$2991,"Grayson Coulter",$Q$5:$Q$2991,Q136,$AE$5:$AE$2991,"<="&AE136,$R$5:$R$2991,"<"&R136)) | AG136: =IF(OR(C136<>"Grayson Coulter",G136<'00_Control'!$B$7),"",--(AF136<5)) | AH136: =IF(OR(C136<>"Grayson Coulter",G136<'00_Control'!$B$7),"",--(AF136<10)) | AI136: =IF(AND(C136="Grayson Coulter",G136>='00_Control'!$B$7),"YES","NO") | AJ136: OK
A137: SM000133 | B137: SW010 | C137: Caeleb Dressel | D137: SwimCloud | E137: 2361642 | F137: 7067830 | G137: 42307 | H137: Florida vs. Georgia | I137: 55342 | K137: TIM | L137: =IF(K137="FIN",3,IF(OR(K137="SEM",K137="SEMI"),2,IF(OR(K137="PRE",K137="HEAT"),1,IF(V137="YES",4,2)))) | M137: LCM | N137: 100 | O137: Free | P137: 100 Free | Q137: LCM_100_FREE | R137: 51.61 | S137: =IF(R137="","",IF(R137>=60,INT(R137/60)&":"&TEXT(MOD(R137,60),"00.00"),TEXT(R137,"0.00"))) | T137: =IFERROR((G137-INDEX('01_Swimmers'!$E$5:$E$22,MATCH(B137,'01_Swimmers'!$A$5:$A$22,0)))/'00_Control'!$B$10,"") | U137: =IF(T137="","",INT(T137)) | V137: NO | W137: YES | X137: NO | Y137: 1 | Z137: 4 | AA137: 1 | AB137: https://www.swimcloud.com/results/55342/event/20/?id=7067830#time7067830 | AC137: SwimCloud API v6 2026-10-08 | AD137: Caeleb Dressel|2015-10-30|LCM|100|Free|51.61|Florida vs. Georgia|TIM|False | AE137: =G137+L137/1000+ROW()/1000000000 | AF137: =IF(C137<>"Grayson Coulter","",COUNTIFS($C$5:$C$2991,"Grayson Coulter",$Q$5:$Q$2991,Q137,$AE$5:$AE$2991,"<="&AE137,$R$5:$R$2991,"<"&R137)) | AG137: =IF(OR(C137<>"Grayson Coulter",G137<'00_Control'!$B$7),"",--(AF137<5)) | AH137: =IF(OR(C137<>"Grayson Coulter",G137<'00_Control'!$B$7),"",--(AF137<10)) | AI137: =IF(AND(C137="Grayson Coulter",G137>='00_Control'!$B$7),"YES","NO") | AJ137: OK
A138: SM000134 | B138: SW010 | C138: Caeleb Dressel | D138: SwimCloud | E138: 2361642 | F138: 7222966 | G138: 42329 | H138: Ohio State Invitational | I138: 56334 | K138: PRE | L138: =IF(K138="FIN",3,IF(OR(K138="SEM",K138="SEMI"),2,IF(OR(K138="PRE",K138="HEAT"),1,IF(V138="YES",4,2)))) | M138: LCM | N138: 100 | O138: Fly | P138: 100 Fly | Q138: LCM_100_FLY | R138: 54.06 | S138: =IF(R138="","",IF(R138>=60,INT(R138/60)&":"&TEXT(MOD(R138,60),"00.00"),TEXT(R138,"0.00"))) | T138: =IFERROR((G138-INDEX('01_Swimmers'!$E$5:$E$22,MATCH(B138,'01_Swimmers'!$A$5:$A$22,0)))/'00_Control'!$B$10,"") | U138: =IF(T138="","",INT(T138)) | V138: NO | W138: YES | X138: NO | Y138: 2 | Z138: 5 | AA138: 2 | AB138: https://www.swimcloud.com/results/56334/event/16/?id=7222966#time7222966 | AC138: SwimCloud API v6 2026-10-08 | AD138: Caeleb Dressel|2015-11-21|LCM|100|Fly|54.06|Ohio State Invitational|PRE|False | AE138: =G138+L138/1000+ROW()/1000000000 | AF138: =IF(C138<>"Grayson Coulter","",COUNTIFS($C$5:$C$2991,"Grayson Coulter",$Q$5:$Q$2991,Q138,$AE$5:$AE$2991,"<="&AE138,$R$5:$R$2991,"<"&R138)) | AG138: =IF(OR(C138<>"Grayson Coulter",G138<'00_Control'!$B$7),"",--(AF138<5)) | AH138: =IF(OR(C138<>"Grayson Coulter",G138<'00_Control'!$B$7),"",--(AF138<10)) | AI138: =IF(AND(C138="Grayson Coulter",G138>='00_Control'!$B$7),"YES","NO") | AJ138: OK
A139: SM000135 | B139: SW010 | C139: Caeleb Dressel | D139: SwimCloud | E139: 2361642 | F139: 7223241 | G139: 42330 | H139: Ohio State Invitational | I139: 56334 | K139: PRE | L139: =IF(K139="FIN",3,IF(OR(K139="SEM",K139="SEMI"),2,IF(OR(K139="PRE",K139="HEAT"),1,IF(V139="YES",4,2)))) | M139: LCM | N139: 100 | O139: Free | P139: 100 Free | Q139: LCM_100_FREE | R139: 49.99 | S139: =IF(R139="","",IF(R139>=60,INT(R139/60)&":"&TEXT(MOD(R139,60),"00.00"),TEXT(R139,"0.00"))) | T139: =IFERROR((G139-INDEX('01_Swimmers'!$E$5:$E$22,MATCH(B139,'01_Swimmers'!$A$5:$A$22,0)))/'00_Control'!$B$10,"") | U139: =IF(T139="","",INT(T139)) | V139: NO | W139: YES | X139: NO | Y139: 4 | Z139: 5 | AA139: 1 | AB139: https://www.swimcloud.com/results/56334/event/30/?id=7223241#time7223241 | AC139: SwimCloud API v6 2026-10-08 | AD139: Caeleb Dressel|2015-11-22|LCM|100|Free|49.99|Ohio State Invitational|PRE|False | AE139: =G139+L139/1000+ROW()/1000000000 | AF139: =IF(C139<>"Grayson Coulter","",COUNTIFS($C$5:$C$2991,"Grayson Coulter",$Q$5:$Q$2991,Q139,$AE$5:$AE$2991,"<="&AE139,$R$5:$R$2991,"<"&R139)) | AG139: =IF(OR(C139<>"Grayson Coulter",G139<'00_Control'!$B$7),"",--(AF139<5)) | AH139: =IF(OR(C139<>"Grayson Coulter",G139<'00_Control'!$B$7),"",--(AF139<10)) | AI139: =IF(AND(C139="Grayson Coulter",G139>='00_Control'!$B$7),"YES","NO") | AJ139: OK
A140: SM000136 | B140: SW010 | C140: Caeleb Dressel | D140: SwimCloud | E140: 2361642 | F140: 7447281 | G140: 42392 | H140: Florida vs. Auburn | I140: 57104 | K140: TIM | L140: =IF(K140="FIN",3,IF(OR(K140="SEM",K140="SEMI"),2,IF(OR(K140="PRE",K140="HEAT"),1,IF(V140="YES",4,2)))) | M140: LCM | N140: 100 | O140: Free | P140: 100 Free | Q140: LCM_100_FREE | R140: 50.94 | S140: =IF(R140="","",IF(R140>=60,INT(R140/60)&":"&TEXT(MOD(R140,60),"00.00"),TEXT(R140,"0.00"))) | T140: =IFERROR((G140-INDEX('01_Swimmers'!$E$5:$E$22,MATCH(B140,'01_Swimmers'!$A$5:$A$22,0)))/'00_Control'!$B$10,"") | U140: =IF(T140="","",INT(T140)) | V140: NO | W140: YES | X140: NO | Y140: 1 | Z140: 8 | AA140: 1 | AB140: https://www.swimcloud.com/results/57104/event/20/?id=7447281#time7447281 | AC140: SwimCloud API v6 2026-10-08 | AD140: Caeleb Dressel|2016-01-23|LCM|100|Free|50.94|Florida vs. Auburn|TIM|False | AE140: =G140+L140/1000+ROW()/1000000000 | AF140: =IF(C140<>"Grayson Coulter","",COUNTIFS($C$5:$C$2991,"Grayson Coulter",$Q$5:$Q$2991,Q140,$AE$5:$AE$2991,"<="&AE140,$R$5:$R$2991,"<"&R140)) | AG140: =IF(OR(C140<>"Grayson Coulter",G140<'00_Control'!$B$7),"",--(AF140<5)) | AH140: =IF(OR(C140<>"Grayson Coulter",G140<'00_Control'!$B$7),"",--(AF140<10)) | AI140: =IF(AND(C140="Grayson Coulter",G140>='00_Control'!$B$7),"YES","NO") | AJ140: OK
... A150: SM000146 | B150: SW010 | C150: Caeleb Dressel | D150: SwimCloud | E150: 2361642 | F150: 141503415 | G150: 42552 | H150: USA Swimming Olympic Team Trials | I150: 54015 | K150: PRE | L150: =IF(K150="FIN",3,IF(OR(K150="SEM",K150="SEMI"),2,IF(OR(K150="PRE",K150="HEAT"),1,IF(V150="YES",4,2)))) | M150: LCM | N150: 100 | O150: Fly | P150: 100 Fly | Q150: LCM_100_FLY | R150: 52.22 | S150: =IF(R150="","",IF(R150>=60,INT(R150/60)&":"&TEXT(MOD(R150,60),"00.00"),TEXT(R150,"0.00"))) | T150: =IFERROR((G150-INDEX('01_Swimmers'!$E$5:$E$22,MATCH(B150,'01_Swimmers'!$A$5:$A$22,0)))/'00_Control'!$B$10,"") | U150: =IF(T150="","",INT(T150)) | V150: NO | W150: YES | X150: NO | Y150: 14 | Z150: 2 | AA150: 7 | AB150: https://www.swimcloud.com/results/54015/event/23/?id=141503415#time141503415 | AC150: SwimCloud API v6 2026-10-08 | AD150: Caeleb Dressel|2016-07-01|LCM|100|Fly|52.22|USA Swimming Olympic Team Trials|PRE|False | AE150: =G150+L150/1000+ROW()/1000000000 | AF150: =IF(C150<>"Grayson Coulter","",COUNTIFS($C$5:$C$2991,"Grayson Coulter",$Q$5:$Q$2991,Q150,$AE$5:$AE$2991,"<="&AE150,$R$5:$R$2991,"<"&R150)) | AG150: =IF(OR(C150<>"Grayson Coulter",G150<'00_Control'!$B$7),"",--(AF150<5)) | AH150: =IF(OR(C150<>"Grayson Coulter",G150<'00_Control'!$B$7),"",--(AF150<10)) | AI150: =IF(AND(C150="Grayson Coulter",G150>='00_Control'!$B$7),"YES","NO") | AJ150: OK
A151: SM000147 | B151: SW010 | C151: Caeleb Dressel | D151: SwimCloud | E151: 2361642 | F151: 15004547 | G151: 42591 | H151: 2016 Olympic Games | I151: 106117 | K151: PRE | L151: =IF(K151="FIN",3,IF(OR(K151="SEM",K151="SEMI"),2,IF(OR(K151="PRE",K151="HEAT"),1,IF(V151="YES",4,2)))) | M151: LCM | N151: 100 | O151: Free | P151: 100 Free | Q151: LCM_100_FREE | R151: 47.91 | S151: =IF(R151="","",IF(R151>=60,INT(R151/60)&":"&TEXT(MOD(R151,60),"00.00"),TEXT(R151,"0.00"))) | T151: =IFERROR((G151-INDEX('01_Swimmers'!$E$5:$E$22,MATCH(B151,'01_Swimmers'!$A$5:$A$22,0)))/'00_Control'!$B$10,"") | U151: =IF(T151="","",INT(T151)) | V151: NO | W151: YES | X151: NO | Y151: 0 | AA151: 18 | AB151: https://www.swimcloud.com/results/106117/event/4/?id=15004547#time15004547 | AC151: SwimCloud API v6 2026-10-08 | AD151: Caeleb Dressel|2016-08-09|LCM|100|Free|47.91|2016 Olympic Games|PRE|False | AE151: =G151+L151/1000+ROW()/1000000000 | AF151: =IF(C151<>"Grayson Coulter","",COUNTIFS($C$5:$C$2991,"Grayson Coulter",$Q$5:$Q$2991,Q151,$AE$5:$AE$2991,"<="&AE151,$R$5:$R$2991,"<"&R151)) | AG151: =IF(OR(C151<>"Grayson Coulter",G151<'00_Control'!$B$7),"",--(AF151<5)) | AH151: =IF(OR(C151<>"Grayson Coulter",G151<'00_Control'!$B$7),"",--(AF151<10)) | AI151: =IF(AND(C151="Grayson Coulter",G151>='00_Control'!$B$7),"YES","NO") | AJ151: OK
A152: SM000148 | B152: SW010 | C152: Caeleb Dressel | D152: SwimCloud | E152: 2361642 | F152: 15004543 | G152: 42591 | H152: 2016 Olympic Games | I152: 106117 | K152: PRE | L152: =IF(K152="FIN",3,IF(OR(K152="SEM",K152="SEMI"),2,IF(OR(K152="PRE",K152="HEAT"),1,IF(V152="YES",4,2)))) | M152: LCM | N152: 100 | O152: Free | P152: 100 Free | Q152: LCM_100_FREE | R152: 47.97 | S152: =IF(R152="","",IF(R152>=60,INT(R152/60)&":"&TEXT(MOD(R152,60),"00.00"),TEXT(R152,"0.00"))) | T152: =IFERROR((G152-INDEX('01_Swimmers'!$E$5:$E$22,MATCH(B152,'01_Swimmers'!$A$5:$A$22,0)))/'00_Control'!$B$10,"") | U152: =IF(T152="","",INT(T152)) | V152: NO | W152: YES | X152: NO | Y152: 0 | AA152: 5 | AB152: https://www.swimcloud.com/results/106117/event/4/?id=15004543#time15004543 | AC152: SwimCloud API v6 2026-10-08 | AD152: Caeleb Dressel|2016-08-09|LCM|100|Free|47.97|2016 Olympic Games|PRE|False | AE152: =G152+L152/1000+ROW()/1000000000 | AF152: =IF(C152<>"Grayson Coulter","",COUNTIFS($C$5:$C$2991,"Grayson Coulter",$Q$5:$Q$2991,Q152,$AE$5:$AE$2991,"<="&AE152,$R$5:$R$2991,"<"&R152)) | AG152: =IF(OR(C152<>"Grayson Coulter",G152<'00_Control'!$B$7),"",--(AF152<5)) | AH152: =IF(OR(C152<>"Grayson Coulter",G152<'00_Control'!$B$7),"",--(AF152<10)) | AI152: =IF(AND(C152="Grayson Coulter",G152>='00_Control'!$B$7),"YES","NO") | AJ152: OK
A153: SM000149 | B153: SW010 | C153: Caeleb Dressel | D153: SwimCloud | E153: 2361642 | F153: 15004618 | G153: 42591 | H153: 2016 Olympic Games | I153: 106117 | K153: FIN | L153: =IF(K153="FIN",3,IF(OR(K153="SEM",K153="SEMI"),2,IF(OR(K153="PRE",K153="HEAT"),1,IF(V153="YES",4,2)))) | M153: LCM | N153: 100 | O153: Free | P153: 100 Free | Q153: LCM_100_FREE | R153: 48.02 | S153: =IF(R153="","",IF(R153>=60,INT(R153/60)&":"&TEXT(MOD(R153,60),"00.00"),TEXT(R153,"0.00"))) | T153: =IFERROR((G153-INDEX('01_Swimmers'!$E$5:$E$22,MATCH(B153,'01_Swimmers'!$A$5:$A$22,0)))/'00_Control'!$B$10,"") | U153: =IF(T153="","",INT(T153)) | V153: NO | W153: YES | X153: NO | Y153: 0 | AA153: 6 | AB153: https://www.swimcloud.com/results/106117/event/4/?id=15004618#time15004618 | AC153: SwimCloud API v6 2026-10-08 | AD153: Caeleb Dressel|2016-08-09|LCM|100|Free|48.02|2016 Olympic Games|FIN|False | AE153: =G153+L153/1000+ROW()/1000000000 | AF153: =IF(C153<>"Grayson Coulter","",COUNTIFS($C$5:$C$2991,"Grayson Coulter",$Q$5:$Q$2991,Q153,$AE$5:$AE$2991,"<="&AE153,$R$5:$R$2991,"<"&R153)) | AG153: =IF(OR(C153<>"Grayson Coulter",G153<'00_Control'!$B$7),"",--(AF153<5)) | AH153: =IF(OR(C153<>"Grayson Coulter",G153<'00_Control'!$B$7),"",--(AF153<10)) | AI153: =IF(AND(C153="Grayson Coulter",G153>='00_Control'!$B$7),"YES","NO") | AJ153: OK
A154: SM000150 | B154: SW010 | C154: Caeleb Dressel | D154: SwimCloud | E154: 2361642 | F154: 9135423 | G154: 42888 | H154: Arena Pro Swim Series - Santa Clara | I154: 76269 | K154: PRE | L154: =IF(K154="FIN",3,IF(OR(K154="SEM",K154="SEMI"),2,IF(OR(K154="PRE",K154="HEAT"),1,IF(V154="YES",4,2)))) | M154: LCM | N154: 100 | O154: Fly | P154: 100 Fly | Q154: LCM_100_FLY | R154: 53.34 | S154: =IF(R154="","",IF(R154>=60,INT(R154/60)&":"&TEXT(MOD(R154,60),"00.00"),TEXT(R154,"0.00"))) | T154: =IFERROR((G154-INDEX('01_Swimmers'!$E$5:$E$22,MATCH(B154,'01_Swimmers'!$A$5:$A$22,0)))/'00_Control'!$B$10,"") | U154: =IF(T154="","",INT(T154)) | V154: NO | W154: YES | X154: NO | Y154: 7 | Z154: 6 | AA154: 2 | AB154: https://www.swimcloud.com/results/76269/event/4/?id=9135423#time9135423 | AC154: SwimCloud API v6 2026-10-08 | AD154: Caeleb Dressel|2017-06-02|LCM|100|Fly|53.34|Arena Pro Swim Series - Santa Clara|PRE|False | AE154: =G154+L154/1000+ROW()/1000000000 | AF154: =IF(C154<>"Grayson Coulter","",COUNTIFS($C$5:$C$2991,"Grayson Coulter",$Q$5:$Q$2991,Q154,$AE$5:$AE$2991,"<="&AE154,$R$5:$R$2991,"<"&R154)) | AG154: =IF(OR(C154<>"Grayson Coulter",G154<'00_Control'!$B$7),"",--(AF154<5)) | AH154: =IF(OR(C154<>"Grayson Coulter",G154<'00_Control'!$B$7),"",--(AF154<10)) | AI154: =IF(AND(C154="Grayson Coulter",G154>='00_Control'!$B$7),"YES","NO") | AJ154: OK
A155: SM000151 | B155: SW010 | C155: Caeleb Dressel | D155: SwimCloud | E155: 2361642 | F155: 9135468 | G155: 42888 | H155: Arena Pro Swim Series - Santa Clara | I155: 76269 | K155: FIN | L155: =IF(K155="FIN",3,IF(OR(K155="SEM",K155="SEMI"),2,IF(OR(K155="PRE",K155="HEAT"),1,IF(V155="YES",4,2)))) | M155: LCM | N155: 100 | O155: Fly | P155: 100 Fly | Q155: LCM_100_FLY | R155: 52.29 | S155: =IF(R155="","",IF(R155>=60,INT(R155/60)&":"&TEXT(MOD(R155,60),"00.00"),TEXT(R155,"0.00"))) | T155: =IFERROR((G155-INDEX('01_Swimmers'!$E$5:$E$22,MATCH(B155,'01_Swimmers'!$A$5:$A$22,0)))/'00_Control'!$B$10,"") | U155: =IF(T155="","",INT(T155)) | V155: NO | W155: YES | X155: NO | Y155: 2 | Z155: 6 | AA155: 2 | AB155: https://www.swimcloud.com/results/76269/event/4/?id=9135468#time9135468 | AC155: SwimCloud API v6 2026-10-08 | AD155: Caeleb Dressel|2017-06-02|LCM|100|Fly|52.29|Arena Pro Swim Series - Santa Clara|FIN|False | AE155: =G155+L155/1000+ROW()/1000000000 | AF155: =IF(C155<>"Grayson Coulter","",COUNTIFS($C$5:$C$2991,"Grayson Coulter",$Q$5:$Q$2991,Q155,$AE$5:$AE$2991,"<="&AE155,$R$5:$R$2991,"<"&R155)) | AG155: =IF(OR(C155<>"Grayson Coulter",G155<'00_Control'!$B$7),"",--(AF155<5)) | AH155: =IF(OR(C155<>"Grayson Coulter",G155<'00_Control'!$B$7),"",--(AF155<10)) | AI155: =IF(AND(C155="Grayson Coulter",G155>='00_Control'!$B$7),"YES","NO") | AJ155: OK
A156: SM000152 | B156: SW010 | C156: Caeleb Dressel | D156: SwimCloud | E156: 2361642 | F156: 9134241 | G156: 42888 | H156: Arena Pro Swim Series - Santa Clara | I156: 76269 | K156: PRE | L156: =IF(K156="FIN",3,IF(OR(K156="SEM",K156="SEMI"),2,IF(OR(K156="PRE",K156="HEAT"),1,IF(V156="YES",4,2)))) | M156: LCM | N156: 100 | O156: Free | P156: 100 Free | Q156: LCM_100_FREE | R156: 49.38 | S156: =IF(R156="","",IF(R156>=60,INT(R156/60)&":"&TEXT(MOD(R156,60),"00.00"),TEXT(R156,"0.00"))) | T156: =IFERROR((G156-INDEX('01_Swimmers'!$E$5:$E$22,MATCH(B156,'01_Swimmers'!$A$5:$A$22,0)))/'00_Control'!$B$10,"") | U156: =IF(T156="","",INT(T156)) | V156: NO | W156: YES | X156: NO | Y156: 11 | Z156: 5 | AA156: 1 | AB156: https://www.swimcloud.com/results/76269/event/8/?id=9134241#time9134241 | AC156: SwimCloud API v6 2026-10-08 | AD156: Caeleb Dressel|2017-06-02|LCM|100|Free|49.38|Arena Pro Swim Series - Santa Clara|PRE|False | AE156: =G156+L156/1000+ROW()/1000000000 | AF156: =IF(C156<>"Grayson Coulter","",COUNTIFS($C$5:$C$2991,"Grayson Coulter",$Q$5:$Q$2991,Q156,$AE$5:$AE$2991,"<="&AE156,$R$5:$R$2991,"<"&R156)) | AG156: =IF(OR(C156<>"Grayson Coulter",G156<'00_Control'!$B$7),"",--(AF156<5)) | AH156: =IF(OR(C156<>"Grayson Coulter",G156<'00_Control'!$B$7),"",--(AF156<10)) | AI156: =IF(AND(C156="Grayson Coulter",G156>='00_Control'!$B$7),"YES","NO") | AJ156: OK
A157: SM000153 | B157: SW010 | C157: Caeleb Dressel | D157: SwimCloud | E157: 2361642 | F157: 9134291 | G157: 42888 | H157: Arena Pro Swim Series - Santa Clara | I157: 76269 | K157: FIN | L157: =IF(K157="FIN",3,IF(OR(K157="SEM",K157="SEMI"),2,IF(OR(K157="PRE",K157="HEAT"),1,IF(V157="YES",4,2)))) | M157: LCM | N157: 100 | O157: Free | P157: 100 Free | Q157: LCM_100_FREE | R157: 49.26 | S157: =IF(R157="","",IF(R157>=60,INT(R157/60)&":"&TEXT(MOD(R157,60),"00.00"),TEXT(R157,"0.00"))) | T157: =IFERROR((G157-INDEX('01_Swimmers'!$E$5:$E$22,MATCH(B157,'01_Swimmers'!$A$5:$A$22,0)))/'00_Control'!$B$10,"") | U157: =IF(T157="","",INT(T157)) | V157: NO | W157: YES | X157: NO | Y157: 2 | Z157: 5 | AA157: 2 | AB157: https://www.swimcloud.com/results/76269/event/8/?id=9134291#time9134291 | AC157: SwimCloud API v6 2026-10-08 | AD157: Caeleb Dressel|2017-06-02|LCM|100|Free|49.26|Arena Pro Swim Series - Santa Clara|FIN|False | AE157: =G157+L157/1000+ROW()/1000000000 | AF157: =IF(C157<>"Grayson Coulter","",COUNTIFS($C$5:$C$2991,"Grayson Coulter",$Q$5:$Q$2991,Q157,$AE$5:$AE$2991,"<="&AE157,$R$5:$R$2991,"<"&R157)) | AG157: =IF(OR(C157<>"Grayson Coulter",G157<'00_Control'!$B$7),"",--(AF157<5)) | AH157: =IF(OR(C157<>"Grayson Coulter",G157<'00_Control'!$B$7),"",--(AF157<10)) | AI157: =IF(AND(C157="Grayson Coulter",G157>='00_Control'!$B$7),"YES","NO") | AJ157: OK
A158: SM000154 | B158: SW010 | C158: Caeleb Dressel | D158: SwimCloud | E158: 2361642 | F158: 9137213 | G158: 42913 | H158: Phillips 66 Summer National Championships | I158: 76270 | K158: PRE | L158: =IF(K158="FIN",3,IF(OR(K158="SEM",K158="SEMI"),2,IF(OR(K158="PRE",K158="HEAT"),1,IF(V158="YES",4,2)))) | M158: LCM | N158: 100 | O158: Free | P158: 100 Free | Q158: LCM_100_FREE | R158: 48.56 | S158: =IF(R158="","",IF(R158>=60,INT(R158/60)&":"&TEXT(MOD(R158,60),"00.00"),TEXT(R158,"0.00"))) | T158: =IFERROR((G158-INDEX('01_Swimmers'!$E$5:$E$22,MATCH(B158,'01_Swimmers'!$A$5:$A$22,0)))/'00_Control'!$B$10,"") | U158: =IF(T158="","",INT(T158)) | V158: NO | W158: YES | X158: NO | Y158: 9 | Z158: 4 | AA158: 2 | AB158: https://www.swimcloud.com/results/76270/event/4/?id=9137213#time9137213 | AC158: SwimCloud API v6 2026-10-08 | AD158: Caeleb Dressel|2017-06-27|LCM|100|Free|48.56|Phillips 66 Summer National Championships|PRE|False | AE158: =G158+L158/1000+ROW()/1000000000 | AF158: =IF(C158<>"Grayson Coulter","",COUNTIFS($C$5:$C$2991,"Grayson Coulter",$Q$5:$Q$2991,Q158,$AE$5:$AE$2991,"<="&AE158,$R$5:$R$2991,"<"&R158)) | AG158: =IF(OR(C158<>"Grayson Coulter",G158<'00_Control'!$B$7),"",--(AF158<5)) | AH158: =IF(OR(C158<>"Grayson Coulter",G158<'00_Control'!$B$7),"",--(AF158<10)) | AI158: =IF(AND(C158="Grayson Coulter",G158>='00_Control'!$B$7),"YES","NO") | AJ158: OK
A159: SM000155 | B159: SW010 | C159: Caeleb Dressel | D159: SwimCloud | E159: 2361642 | F159: 9137246 | G159: 42913 | H159: Phillips 66 Summer National Championships | I159: 76270 | K159: FIN | L159: =IF(K159="FIN",3,IF(OR(K159="SEM",K159="SEMI"),2,IF(OR(K159="PRE",K159="HEAT"),1,IF(V159="YES",4,2)))) | M159: LCM | N159: 100 | O159: Free | P159: 100 Free | Q159: LCM_100_FREE | R159: 47.97 | S159: =IF(R159="","",IF(R159>=60,INT(R159/60)&":"&TEXT(MOD(R159,60),"00.00"),TEXT(R159,"0.00"))) | T159: =IFERROR((G159-INDEX('01_Swimmers'!$E$5:$E$22,MATCH(B159,'01_Swimmers'!$A$5:$A$22,0)))/'00_Control'!$B$10,"") | U159: =IF(T159="","",INT(T159)) | V159: NO | W159: YES | X159: NO | Y159: 3 | Z159: 3 | AA159: 2 | AB159: https://www.swimcloud.com/results/76270/event/4/?id=9137246#time9137246 | AC159: SwimCloud API v6 2026-10-08 | AD159: Caeleb Dressel|2017-06-27|LCM|100|Free|47.97|Phillips 66 Summer National Championships|FIN|False | AE159: =G159+L159/1000+ROW()/1000000000 | AF159: =IF(C159<>"Grayson Coulter","",COUNTIFS($C$5:$C$2991,"Grayson Coulter",$Q$5:$Q$2991,Q159,$AE$5:$AE$2991,"<="&AE159,$R$5:$R$2991,"<"&R159)) | AG159: =IF(OR(C159<>"Grayson Coulter",G159<'00_Control'!$B$7),"",--(AF159<5)) | AH159: =IF(OR(C159<>"Grayson Coulter",G159<'00_Control'!$B$7),"",--(AF159<10)) | AI159: =IF(AND(C159="Grayson Coulter",G159>='00_Control'!$B$7),"YES","NO") | AJ159: OK
A160: SM000156 | B160: SW010 | C160: Caeleb Dressel | D160: SwimCloud | E160: 2361642 | F160: 9137322 | G160: 42914 | H160: Phillips 66 Summer National Championships | I160: 76270 | K160: PRE | L160: =IF(K160="FIN",3,IF(OR(K160="SEM",K160="SEMI"),2,IF(OR(K160="PRE",K160="HEAT"),1,IF(V160="YES",4,2)))) | M160: LCM | N160: 200 | O160: Free | P160: 200 Free | Q160: LCM_200_FREE | R160: 107.45 | S160: =IF(R160="","",IF(R160>=60,INT(R160/60)&":"&TEXT(MOD(R160,60),"00.00"),TEXT(R160,"0.00"))) | T160: =IFERROR((G160-INDEX('01_Swimmers'!$E$5:$E$22,MATCH(B160,'01_Swimmers'!$A$5:$A$22,0)))/'00_Control'!$B$10,"") | U160: =IF(T160="","",INT(T160)) | V160: NO | W160: YES | X160: NO | Y160: 9 | Z160: 6 | AA160: 3 | AB160: https://www.swimcloud.com/results/76270/event/8/?id=9137322#time9137322 | AC160: SwimCloud API v6 2026-10-08 | AD160: Caeleb Dressel|2017-06-28|LCM|200|Free|107.45|Phillips 66 Summer National Championships|PRE|False | AE160: =G160+L160/1000+ROW()/1000000000 | AF160: =IF(C160<>"Grayson Coulter","",COUNTIFS($C$5:$C$2991,"Grayson Coulter",$Q$5:$Q$2991,Q160,$AE$5:$AE$2991,"<="&AE160,$R$5:$R$2991,"<"&R160)) | AG160: =IF(OR(C160<>"Grayson Coulter",G160<'00_Control'!$B$7),"",--(AF160<5)) | AH160: =IF(OR(C160<>"Grayson Coulter",G160<'00_Control'!$B$7),"",--(AF160<10)) | AI160: =IF(AND(C160="Grayson Coulter",G160>='00_Control'!$B$7),"YES","NO") | AJ160: OK
A161: SM000157 | B161: SW010 | C161: Caeleb Dressel | D161: SwimCloud | E161: 2361642 | F161: 9137356 | G161: 42914 | H161: Phillips 66 Summer National Championships | I161: 76270 | K161: FIN | L161: =IF(K161="FIN",3,IF(OR(K161="SEM",K161="SEMI"),2,IF(OR(K161="PRE",K161="HEAT"),1,IF(V161="YES",4,2)))) | M161: LCM | N161: 200 | O161: Free | P161: 200 Free | Q161: LCM_200_FREE | R161: 107.51 | S161: =IF(R161="","",IF(R161>=60,INT(R161/60)&":"&TEXT(MOD(R161,60),"00.00"),TEXT(R161,"0.00"))) | T161: =IFERROR((G161-INDEX('01_Swimmers'!$E$5:$E$22,MATCH(B161,'01_Swimmers'!$A$5:$A$22,0)))/'00_Control'!$B$10,"") | U161: =IF(T161="","",INT(T161)) | V161: NO | W161: YES | X161: NO | Y161: 3 | Z161: 3 | AA161: 6 | AB161: https://www.swimcloud.com/results/76270/event/8/?id=9137356#time9137356 | AC161: SwimCloud API v6 2026-10-08 | AD161: Caeleb Dressel|2017-06-28|LCM|200|Free|107.51|Phillips 66 Summer National Championships|FIN|False | AE161: =G161+L161/1000+ROW()/1000000000 | AF161: =IF(C161<>"Grayson Coulter","",COUNTIFS($C$5:$C$2991,"Grayson Coulter",$Q$5:$Q$2991,Q161,$AE$5:$AE$2991,"<="&AE161,$R$5:$R$2991,"<"&R161)) | AG161: =IF(OR(C161<>"Grayson Coulter",G161<'00_Control'!$B$7),"",--(AF161<5)) | AH161: =IF(OR(C161<>"Grayson Coulter",G161<'00_Control'!$B$7),"",--(AF161<10)) | AI161: =IF(AND(C161="Grayson Coulter",G161>='00_Control'!$B$7),"YES","NO") | AJ161: OK
A162: SM000158 | B162: SW010 | C162: Caeleb Dressel | D162: SwimCloud | E162: 2361642 | F162: 9138559 | G162: 42915 | H162: Phillips 66 Summer National Championships | I162: 76270 | K162: PRE | L162: =IF(K162="FIN",3,IF(OR(K162="SEM",K162="SEMI"),2,IF(OR(K162="PRE",K162="HEAT"),1,IF(V162="YES",4,2)))) | M162: LCM | N162: 100 | O162: Fly | P162: 100 Fly | Q162: LCM_100_FLY | R162: 51.38 | S162: =IF(R162="","",IF(R162>=60,INT(R162/60)&":"&TEXT(MOD(R162,60),"00.00"),TEXT(R162,"0.00"))) | T162: =IFERROR((G162-INDEX('01_Swimmers'!$E$5:$E$22,MATCH(B162,'01_Swimmers'!$A$5:$A$22,0)))/'00_Control'!$B$10,"") | U162: =IF(T162="","",INT(T162)) | V162: NO | W162: YES | X162: NO | Y162: 8 | Z162: 5 | AA162: 2 | AB162: https://www.swimcloud.com/results/76270/event/18/?id=9138559#time9138559 | AC162: SwimCloud API v6 2026-10-08 | AD162: Caeleb Dressel|2017-06-29|LCM|100|Fly|51.38|Phillips 66 Summer National Championships|PRE|False | AE162: =G162+L162/1000+ROW()/1000000000 | AF162: =IF(C162<>"Grayson Coulter","",COUNTIFS($C$5:$C$2991,"Grayson Coulter",$Q$5:$Q$2991,Q162,$AE$5:$AE$2991,"<="&AE162,$R$5:$R$2991,"<"&R162)) | AG162: =IF(OR(C162<>"Grayson Coulter",G162<'00_Control'!$B$7),"",--(AF162<5)) | AH162: =IF(OR(C162<>"Grayson Coulter",G162<'00_Control'!$B$7),"",--(AF162<10)) | AI162: =IF(AND(C162="Grayson Coulter",G162>='00_Control'!$B$7),"YES","NO") | AJ162: OK
A163: SM000159 | B163: SW010 | C163: Caeleb Dressel | D163: SwimCloud | E163: 2361642 | F163: 9138629 | G163: 42915 | H163: Phillips 66 Summer National Championships | I163: 76270 | K163: FIN | L163: =IF(K163="FIN",3,IF(OR(K163="SEM",K163="SEMI"),2,IF(OR(K163="PRE",K163="HEAT"),1,IF(V163="YES",4,2)))) | M163: LCM | N163: 100 | O163: Fly | P163: 100 Fly | Q163: LCM_100_FLY | R163: 50.87 | S163: =IF(R163="","",IF(R163>=60,INT(R163/60)&":"&TEXT(MOD(R163,60),"00.00"),TEXT(R163,"0.00"))) | T163: =IFERROR((G163-INDEX('01_Swimmers'!$E$5:$E$22,MATCH(B163,'01_Swimmers'!$A$5:$A$22,0)))/'00_Control'!$B$10,"") | U163: =IF(T163="","",INT(T163)) | V163: NO | W163: YES | X163: NO | Y163: 3 | Z163: 5 | AA163: 1 | AB163: https://www.swimcloud.com/results/76270/event/18/?id=9138629#time9138629 | AC163: SwimCloud API v6 2026-10-08 | AD163: Caeleb Dressel|2017-06-29|LCM|100|Fly|50.87|Phillips 66 Summer National Championships|FIN|False | AE163: =G163+L163/1000+ROW()/1000000000 | AF163: =IF(C163<>"Grayson Coulter","",COUNTIFS($C$5:$C$2991,"Grayson Coulter",$Q$5:$Q$2991,Q163,$AE$5:$AE$2991,"<="&AE163,$R$5:$R$2991,"<"&R163)) | AG163: =IF(OR(C163<>"Grayson Coulter",G163<'00_Control'!$B$7),"",--(AF163<5)) | AH163: =IF(OR(C163<>"Grayson Coulter",G163<'00_Control'!$B$7),"",--(AF163<10)) | AI163: =IF(AND(C163="Grayson Coulter",G163>='00_Control'!$B$7),"YES","NO") | AJ163: OK
A164: SM000160 | B164: SW010 | C164: Caeleb Dressel | D164: SwimCloud | E164: 2361642 | F164: 12265315 | G164: 42939 | H164: 17th FINA World Championships | I164: 96880 | K164: FIN | L164: =IF(K164="FIN",3,IF(OR(K164="SEM",K164="SEMI"),2,IF(OR(K164="PRE",K164="HEAT"),1,IF(V164="YES",4,2)))) | M164: LCM | N164: 100 | O164: Free | P164: 100 Free | Q164: LCM_100_FREE | R164: 47.26 | S164: =IF(R164="","",IF(R164>=60,INT(R164/60)&":"&TEXT(MOD(R164,60),"00.00"),TEXT(R164,"0.00"))) | T164: =IFERROR((G164-INDEX('01_Swimmers'!$E$5:$E$22,MATCH(B164,'01_Swimmers'!$A$5:$A$22,0)))/'00_Control'!$B$10,"") | U164: =IF(T164="","",INT(T164)) | V164: YES | W164: YES | X164: NO | Y164: 31 | Z164: 3 | AB164: https://www.swimcloud.com/results/96880/event/8/?id=12265081#time12265081 | AC164: SwimCloud API v6 2026-10-08 | AD164: Caeleb Dressel|2017-07-23|LCM|100|Free|47.26|17th FINA World Championships|FIN|True | AE164: =G164+L164/1000+ROW()/1000000000 | AF164: =IF(C164<>"Grayson Coulter","",COUNTIFS($C$5:$C$2991,"Grayson Coulter",$Q$5:$Q$2991,Q164,$AE$5:$AE$2991,"<="&AE164,$R$5:$R$2991,"<"&R164)) | AG164: =IF(OR(C164<>"Grayson Coulter",G164<'00_Control'!$B$7),"",--(AF164<5)) | AH164: =IF(OR(C164<>"Grayson Coulter",G164<'00_Control'!$B$7),"",--(AF164<10)) | AI164: =IF(AND(C164="Grayson Coulter",G164>='00_Control'!$B$7),"YES","NO") | AJ164: OK
A165: SM000161 | B165: SW010 | C165: Caeleb Dressel | D165: SwimCloud | E165: 2361642 | F165: 12262556 | G165: 42942 | H165: 17th FINA World Championships | I165: 96880 | K165: PRE | L165: =IF(K165="FIN",3,IF(OR(K165="SEM",K165="SEMI"),2,IF(OR(K165="PRE",K165="HEAT"),1,IF(V165="YES",4,2)))) | M165: LCM | N165: 100 | O165: Free | P165: 100 Free | Q165: LCM_100_FREE | R165: 48.26 | S165: =IF(R165="","",IF(R165>=60,INT(R165/60)&":"&TEXT(MOD(R165,60),"00.00"),TEXT(R165,"0.00"))) | T165: =IFERROR((G165-INDEX('01_Swimmers'!$E$5:$E$22,MATCH(B165,'01_Swimmers'!$A$5:$A$22,0)))/'00_Control'!$B$10,"") | U165: =IF(T165="","",INT(T165)) | V165: NO | W165: YES | X165: NO | Y165: 11 | Z165: 5 | AA165: 3 | AB165: https://www.swimcloud.com/results/96880/event/19/?id=12262556#time12262556 | AC165: SwimCloud API v6 2026-10-08 | AD165: Caeleb Dressel|2017-07-26|LCM|100|Free|48.26|17th FINA World Championships|PRE|False | AE165: =G165+L165/1000+ROW()/1000000000 | AF165: =IF(C165<>"Grayson Coulter","",COUNTIFS($C$5:$C$2991,"Grayson Coulter",$Q$5:$Q$2991,Q165,$AE$5:$AE$2991,"<="&AE165,$R$5:$R$2991,"<"&R165)) | AG165: =IF(OR(C165<>"Grayson Coulter",G165<'00_Control'!$B$7),"",--(AF165<5)) | AH165: =IF(OR(C165<>"Grayson Coulter",G165<'00_Control'!$B$7),"",--(AF165<10)) | AI165: =IF(AND(C165="Grayson Coulter",G165>='00_Control'!$B$7),"YES","NO") | AJ165: OK
A166: SM000162 | B166: SW010 | C166: Caeleb Dressel | D166: SwimCloud | E166: 2361642 | F166: 12262668 | G166: 42942 | H166: 17th FINA World Championships | I166: 96880 | K166: SEM | L166: =IF(K166="FIN",3,IF(OR(K166="SEM",K166="SEMI"),2,IF(OR(K166="PRE",K166="HEAT"),1,IF(V166="YES",4,2)))) | M166: LCM | N166: 100 | O166: Free | P166: 100 Free | Q166: LCM_100_FREE | R166: 47.66 | S166: =IF(R166="","",IF(R166>=60,INT(R166/60)&":"&TEXT(MOD(R166,60),"00.00"),TEXT(R166,"0.00"))) | T166: =IFERROR((G166-INDEX('01_Swimmers'!$E$5:$E$22,MATCH(B166,'01_Swimmers'!$A$5:$A$22,0)))/'00_Control'!$B$10,"") | U166: =IF(T166="","",INT(T166)) | V166: NO | W166: YES | X166: NO | Y166: 21 | Z166: 5 | AB166: https://www.swimcloud.com/results/96880/event/19/?id=12262668#time12262668 | AC166: SwimCloud API v6 2026-10-08 | AD166: Caeleb Dressel|2017-07-26|LCM|100|Free|47.66|17th FINA World Championships|SEM|False | AE166: =G166+L166/1000+ROW()/1000000000 | AF166: =IF(C166<>"Grayson Coulter","",COUNTIFS($C$5:$C$2991,"Grayson Coulter",$Q$5:$Q$2991,Q166,$AE$5:$AE$2991,"<="&AE166,$R$5:$R$2991,"<"&R166)) | AG166: =IF(OR(C166<>"Grayson Coulter",G166<'00_Control'!$B$7),"",--(AF166<5)) | AH166: =IF(OR(C166<>"Grayson Coulter",G166<'00_Control'!$B$7),"",--(AF166<10)) | AI166: =IF(AND(C166="Grayson Coulter",G166>='00_Control'!$B$7),"YES","NO") | AJ166: OK
A167: SM000163 | B167: SW010 | C167: Caeleb Dressel | D167: SwimCloud | E167: 2361642 | F167: 12262653 | G167: 42943 | H167: 17th FINA World Championships | I167: 96880 | K167: FIN | L167: =IF(K167="FIN",3,IF(OR(K167="SEM",K167="SEMI"),2,IF(OR(K167="PRE",K167="HEAT"),1,IF(V167="YES",4,2)))) | M167: LCM | N167: 100 | O167: Free | P167: 100 Free | Q167: LCM_100_FREE | R167: 47.17 | S167: =IF(R167="","",IF(R167>=60,INT(R167/60)&":"&TEXT(MOD(R167,60),"00.00"),TEXT(R167,"0.00"))) | T167: =IFERROR((G167-INDEX('01_Swimmers'!$E$5:$E$22,MATCH(B167,'01_Swimmers'!$A$5:$A$22,0)))/'00_Control'!$B$10,"") | U167: =IF(T167="","",INT(T167)) | V167: NO | W167: YES | X167: NO | Y167: 31 | Z167: 5 | AA167: 1 | AB167: https://www.swimcloud.com/results/96880/event/19/?id=12262653#time12262653 | AC167: SwimCloud API v6 2026-10-08 | AD167: Caeleb Dressel|2017-07-27|LCM|100|Free|47.17|17th FINA World Championships|FIN|False | AE167: =G167+L167/1000+ROW()/1000000000 | AF167: =IF(C167<>"Grayson Coulter","",COUNTIFS($C$5:$C$2991,"Grayson Coulter",$Q$5:$Q$2991,Q167,$AE$5:$AE$2991,"<="&AE167,$R$5:$R$2991,"<"&R167)) | AG167: =IF(OR(C167<>"Grayson Coulter",G167<'00_Control'!$B$7),"",--(AF167<5)) | AH167: =IF(OR(C167<>"Grayson Coulter",G167<'00_Control'!$B$7),"",--(AF167<10)) | AI167: =IF(AND(C167="Grayson Coulter",G167>='00_Control'!$B$7),"YES","NO") | AJ167: OK
A168: SM000164 | B168: SW010 | C168: Caeleb Dressel | D168: SwimCloud | E168: 2361642 | F168: 12264182 | G168: 42944 | H168: 17th FINA World Championships | I168: 96880 | K168: PRE | L168: =IF(K168="FIN",3,IF(OR(K168="SEM",K168="SEMI"),2,IF(OR(K168="PRE",K168="HEAT"),1,IF(V168="YES",4,2)))) | M168: LCM | N168: 100 | O168: Fly | P168: 100 Fly | Q168: LCM_100_FLY | R168: 50.08 | S168: =IF(R168="","",IF(R168>=60,INT(R168/60)&":"&TEXT(MOD(R168,60),"00.00"),TEXT(R168,"0.00"))) | T168: =IFERROR((G168-INDEX('01_Swimmers'!$E$5:$E$22,MATCH(B168,'01_Swimmers'!$A$5:$A$22,0)))/'00_Control'!$B$10,"") | U168: =IF(T168="","",INT(T168)) | V168: NO | W168: YES | X168: NO | Y168: 6 | Z168: 4 | AA168: 1 | AB168: https://www.swimcloud.com/results/96880/event/30/?id=12264182#time12264182 | AC168: SwimCloud API v6 2026-10-08 | AD168: Caeleb Dressel|2017-07-28|LCM|100|Fly|50.08|17th FINA World Championships|PRE|False | AE168: =G168+L168/1000+ROW()/1000000000 | AF168: =IF(C168<>"Grayson Coulter","",COUNTIFS($C$5:$C$2991,"Grayson Coulter",$Q$5:$Q$2991,Q168,$AE$5:$AE$2991,"<="&AE168,$R$5:$R$2991,"<"&R168)) | AG168: =IF(OR(C168<>"Grayson Coulter",G168<'00_Control'!$B$7),"",--(AF168<5)) | AH168: =IF(OR(C168<>"Grayson Coulter",G168<'00_Control'!$B$7),"",--(AF168<10)) | AI168: =IF(AND(C168="Grayson Coulter",G168>='00_Control'!$B$7),"YES","NO") | AJ168: OK
A169: SM000165 | B169: SW010 | C169: Caeleb Dressel | D169: SwimCloud | E169: 2361642 | F169: 12264206 | G169: 42944 | H169: 17th FINA World Championships | I169: 96880 | K169: SEM | L169: =IF(K169="FIN",3,IF(OR(K169="SEM",K169="SEMI"),2,IF(OR(K169="PRE",K169="HEAT"),1,IF(V169="YES",4,2)))) | M169: LCM | N169: 100 | O169: Fly | P169: 100 Fly | Q169: LCM_100_FLY | R169: 50.07 | S169: =IF(R169="","",IF(R169>=60,INT(R169/60)&":"&TEXT(MOD(R169,60),"00.00"),TEXT(R169,"0.00"))) | T169: =IFERROR((G169-INDEX('01_Swimmers'!$E$5:$E$22,MATCH(B169,'01_Swimmers'!$A$5:$A$22,0)))/'00_Control'!$B$10,"") | U169: =IF(T169="","",INT(T169)) | V169: NO | W169: YES | X169: NO | Y169: 21 | Z169: 4 | AB169: https://www.swimcloud.com/results/96880/event/30/?id=12264206#time12264206 | AC169: SwimCloud API v6 2026-10-08 | AD169: Caeleb Dressel|2017-07-28|LCM|100|Fly|50.07|17th FINA World Championships|SEM|False | AE169: =G169+L169/1000+ROW()/1000000000 | AF169: =IF(C169<>"Grayson Coulter","",COUNTIFS($C$5:$C$2991,"Grayson Coulter",$Q$5:$Q$2991,Q169,$AE$5:$AE$2991,"<="&AE169,$R$5:$R$2991,"<"&R169)) | AG169: =IF(OR(C169<>"Grayson Coulter",G169<'00_Control'!$B$7),"",--(AF169<5)) | AH169: =IF(OR(C169<>"Grayson Coulter",G169<'00_Control'!$B$7),"",--(AF169<10)) | AI169: =IF(AND(C169="Grayson Coulter",G169>='00_Control'!$B$7),"YES","NO") | AJ169: OK
A170: SM000166 | B170: SW010 | C170: Caeleb Dressel | D170: SwimCloud | E170: 2361642 | F170: 12264190 | G170: 42945 | H170: 17th FINA World Championships | I170: 96880 | K170: FIN | L170: =IF(K170="FIN",3,IF(OR(K170="SEM",K170="SEMI"),2,IF(OR(K170="PRE",K170="HEAT"),1,IF(V170="YES",4,2)))) | M170: LCM | N170: 100 | O170: Fly | P170: 100 Fly | Q170: LCM_100_FLY | R170: 49.86 | S170: =IF(R170="","",IF(R170>=60,INT(R170/60)&":"&TEXT(MOD(R170,60),"00.00"),TEXT(R170,"0.00"))) | T170: =IFERROR((G170-INDEX('01_Swimmers'!$E$5:$E$22,MATCH(B170,'01_Swimmers'!$A$5:$A$22,0)))/'00_Control'!$B$10,"") | U170: =IF(T170="","",INT(T170)) | V170: NO | W170: YES | X170: NO | Y170: 31 | Z170: 4 | AA170: 1 | AB170: https://www.swimcloud.com/results/96880/event/30/?id=12264190#time12264190 | AC170: SwimCloud API v6 2026-10-08 | AD170: Caeleb Dressel|2017-07-29|LCM|100|Fly|49.86|17th FINA World Championships|FIN|False | AE170: =G170+L170/1000+ROW()/1000000000 | AF170: =IF(C170<>"Grayson Coulter","",COUNTIFS($C$5:$C$2991,"Grayson Coulter",$Q$5:$Q$2991,Q170,$AE$5:$AE$2991,"<="&AE170,$R$5:$R$2991,"<"&R170)) | AG170: =IF(OR(C170<>"Grayson Coulter",G170<'00_Control'!$B$7),"",--(AF170<5)) | AH170: =IF(OR(C170<>"Grayson Coulter",G170<'00_Control'!$B$7),"",--(AF170<10)) | AI170: =IF(AND(C170="Grayson Coulter",G170>='00_Control'!$B$7),"YES","NO") | AJ170: OK
A171: SM000167 | B171: SW010 | C171: Caeleb Dressel | D171: SwimCloud | E171: 2361642 | F171: 12265283 | G171: 42945 | H171: 17th FINA World Championships | I171: 96880 | K171: FIN | L171: =IF(K171="FIN",3,IF(OR(K171="SEM",K171="SEMI"),2,IF(OR(K171="PRE",K171="HEAT"),1,IF(V171="YES",4,2)))) | M171: LCM | N171: 100 | O171: Free | P171: 100 Free | Q171: LCM_100_FREE | R171: 47.22 | S171: =IF(R171="","",IF(R171>=60,INT(R171/60)&":"&TEXT(MOD(R171,60),"00.00"),TEXT(R171,"0.00"))) | T171: =IFERROR((G171-INDEX('01_Swimmers'!$E$5:$E$22,MATCH(B171,'01_Swimmers'!$A$5:$A$22,0)))/'00_Control'!$B$10,"") | U171: =IF(T171="","",INT(T171)) | V171: YES | W171: YES | X171: NO | Y171: 31 | Z171: 5 | AB171: https://www.swimcloud.com/results/96880/event/37/?id=12265073#time12265073 | AC171: SwimCloud API v6 2026-10-08 | AD171: Caeleb Dressel|2017-07-29|LCM|100|Free|47.22|17th FINA World Championships|FIN|True | AE171: =G171+L171/1000+ROW()/1000000000 | AF171: =IF(C171<>"Grayson Coulter","",COUNTIFS($C$5:$C$2991,"Grayson Coulter",$Q$5:$Q$2991,Q171,$AE$5:$AE$2991,"<="&AE171,$R$5:$R$2991,"<"&R171)) | AG171: =IF(OR(C171<>"Grayson Coulter",G171<'00_Control'!$B$7),"",--(AF171<5)) | AH171: =IF(OR(C171<>"Grayson Coulter",G171<'00_Control'!$B$7),"",--(AF171<10)) | AI171: =IF(AND(C171="Grayson Coulter",G171>='00_Control'!$B$7),"YES","NO") | AJ171: OK
A172: SM000168 | B172: SW010 | C172: Caeleb Dressel | D172: SwimCloud | E172: 2361642 | F172: 19389722 | G172: 43238 | H172: GA SCAT Atlanta Classic Swim Meet | I172: 119471 | K172: PRE | L172: =IF(K172="FIN",3,IF(OR(K172="SEM",K172="SEMI"),2,IF(OR(K172="PRE",K172="HEAT"),1,IF(V172="YES",4,2)))) | M172: LCM | N172: 200 | O172: Free | P172: 200 Free | Q172: LCM_200_FREE | R172: 115.04 | S172: =IF(R172="","",IF(R172>=60,INT(R172/60)&":"&TEXT(MOD(R172,60),"00.00"),TEXT(R172,"0.00"))) | T172: =IFERROR((G172-INDEX('01_Swimmers'!$E$5:$E$22,MATCH(B172,'01_Swimmers'!$A$5:$A$22,0)))/'00_Control'!$B$10,"") | U172: =IF(T172="","",INT(T172)) | V172: NO | W172: YES | X172: NO | Y172: 6 | Z172: 6 | AA172: 16 | AB172: https://www.swimcloud.com/results/119471/event/2/?id=19389722#time19389722 | AC172: SwimCloud API v6 2026-10-08 | AD172: Caeleb Dressel|2018-05-18|LCM|200|Free|115.04|GA SCAT Atlanta Classic Swim Meet|PRE|False | AE172: =G172+L172/1000+ROW()/1000000000 | AF172: =IF(C172<>"Grayson Coulter","",COUNTIFS($C$5:$C$2991,"Grayson Coulter",$Q$5:$Q$2991,Q172,$AE$5:$AE$2991,"<="&AE172,$R$5:$R$2991,"<"&R172)) | AG172: =IF(OR(C172<>"Grayson Coulter",G172<'00_Control'!$B$7),"",--(AF172<5)) | AH172: =IF(OR(C172<>"Grayson Coulter",G172<'00_Control'!$B$7),"",--(AF172<10)) | AI172: =IF(AND(C172="Grayson Coulter",G172>='00_Control'!$B$7),"YES","NO") | AJ172: OK
A173: SM000169 | B173: SW010 | C173: Caeleb Dressel | D173: SwimCloud | E173: 2361642 | F173: 19389723 | G173: 43238 | H173: GA SCAT Atlanta Classic Swim Meet | I173: 119471 | K173: FIN | L173: =IF(K173="FIN",3,IF(OR(K173="SEM",K173="SEMI"),2,IF(OR(K173="PRE",K173="HEAT"),1,IF(V173="YES",4,2)))) | M173: LCM | N173: 200 | O173: Free | P173: 200 Free | Q173: LCM_200_FREE | R173: 111.96 | S173: =IF(R173="","",IF(R173>=60,INT(R173/60)&":"&TEXT(MOD(R173,60),"00.00"),TEXT(R173,"0.00"))) | T173: =IFERROR((G173-INDEX('01_Swimmers'!$E$5:$E$22,MATCH(B173,'01_Swimmers'!$A$5:$A$22,0)))/'00_Control'!$B$10,"") | U173: =IF(T173="","",INT(T173)) | V173: NO | W173: YES | X173: NO | Y173: 3 | Z173: 8 | AA173: 11 | AB173: https://www.swimcloud.com/results/119471/event/2/?id=19389723#time19389723 | AC173: SwimCloud API v6 2026-10-08 | AD173: Caeleb Dressel|2018-05-18|LCM|200|Free|111.96|GA SCAT Atlanta Classic Swim Meet|FIN|False | AE173: =G173+L173/1000+ROW()/1000000000 | AF173: =IF(C173<>"Grayson Coulter","",COUNTIFS($C$5:$C$2991,"Grayson Coulter",$Q$5:$Q$2991,Q173,$AE$5:$AE$2991,"<="&AE173,$R$5:$R$2991,"<"&R173)) | AG173: =IF(OR(C173<>"Grayson Coulter",G173<'00_Control'!$B$7),"",--(AF173<5)) | AH173: =IF(OR(C173<>"Grayson Coulter",G173<'00_Control'!$B$7),"",--(AF173<10)) | AI173: =IF(AND(C173="Grayson Coulter",G173>='00_Control'!$B$7),"YES","NO") | AJ173: OK
A174: SM000170 | B174: SW010 | C174: Caeleb Dressel | D174: SwimCloud | E174: 2361642 | F174: 19390007 | G174: 43240 | H174: GA SCAT Atlanta Classic Swim Meet | I174: 119471 | K174: PRE | L174: =IF(K174="FIN",3,IF(OR(K174="SEM",K174="SEMI"),2,IF(OR(K174="PRE",K174="HEAT"),1,IF(V174="YES",4,2)))) | M174: LCM | N174: 100 | O174: Free | P174: 100 Free | Q174: LCM_100_FREE | R174: 51.32 | S174: =IF(R174="","",IF(R174>=60,INT(R174/60)&":"&TEXT(MOD(R174,60),"00.00"),TEXT(R174,"0.00"))) | T174: =IFERROR((G174-INDEX('01_Swimmers'!$E$5:$E$22,MATCH(B174,'01_Swimmers'!$A$5:$A$22,0)))/'00_Control'!$B$10,"") | U174: =IF(T174="","",INT(T174)) | V174: NO | W174: YES | X174: NO | Y174: 7 | Z174: 4 | AA174: 7 | AB174: https://www.swimcloud.com/results/119471/event/24/?id=19390007#time19390007 | AC174: SwimCloud API v6 2026-10-08 | AD174: Caeleb Dressel|2018-05-20|LCM|100|Free|51.32|GA SCAT Atlanta Classic Swim Meet|PRE|False | AE174: =G174+L174/1000+ROW()/1000000000 | AF174: =IF(C174<>"Grayson Coulter","",COUNTIFS($C$5:$C$2991,"Grayson Coulter",$Q$5:$Q$2991,Q174,$AE$5:$AE$2991,"<="&AE174,$R$5:$R$2991,"<"&R174)) | AG174: =IF(OR(C174<>"Grayson Coulter",G174<'00_Control'!$B$7),"",--(AF174<5)) | AH174: =IF(OR(C174<>"Grayson Coulter",G174<'00_Control'!$B$7),"",--(AF174<10)) | AI174: =IF(AND(C174="Grayson Coulter",G174>='00_Control'!$B$7),"YES","NO") | AJ174: OK
A175: SM000171 | B175: SW010 | C175: Caeleb Dressel | D175: SwimCloud | E175: 2361642 | F175: 19390008 | G175: 43240 | H175: GA SCAT Atlanta Classic Swim Meet | I175: 119471 | K175: FIN | L175: =IF(K175="FIN",3,IF(OR(K175="SEM",K175="SEMI"),2,IF(OR(K175="PRE",K175="HEAT"),1,IF(V175="YES",4,2)))) | M175: LCM | N175: 100 | O175: Free | P175: 100 Free | Q175: LCM_100_FREE | R175: 49.65 | S175: =IF(R175="","",IF(R175>=60,INT(R175/60)&":"&TEXT(MOD(R175,60),"00.00"),TEXT(R175,"0.00"))) | T175: =IFERROR((G175-INDEX('01_Swimmers'!$E$5:$E$22,MATCH(B175,'01_Swimmers'!$A$5:$A$22,0)))/'00_Control'!$B$10,"") | U175: =IF(T175="","",INT(T175)) | V175: NO | W175: YES | X175: NO | Y175: 4 | Z175: 3 | AA175: 1 | AB175: https://www.swimcloud.com/results/119471/event/24/?id=19390008#time19390008 | AC175: SwimCloud API v6 2026-10-08 | AD175: Caeleb Dressel|2018-05-20|LCM|100|Free|49.65|GA SCAT Atlanta Classic Swim Meet|FIN|False | AE175: =G175+L175/1000+ROW()/1000000000 | AF175: =IF(C175<>"Grayson Coulter","",COUNTIFS($C$5:$C$2991,"Grayson Coulter",$Q$5:$Q$2991,Q175,$AE$5:$AE$2991,"<="&AE175,$R$5:$R$2991,"<"&R175)) | AG175: =IF(OR(C175<>"Grayson Coulter",G175<'00_Control'!$B$7),"",--(AF175<5)) | AH175: =IF(OR(C175<>"Grayson Coulter",G175<'00_Control'!$B$7),"",--(AF175<10)) | AI175: =IF(AND(C175="Grayson Coulter",G175>='00_Control'!$B$7),"YES","NO") | AJ175: OK
A176: SM000172 | B176: SW010 | C176: Caeleb Dressel | D176: SwimCloud | E176: 2361642 | F176: 18939900 | G176: 43252 | H176: Mel Zajac Jr. Internation | I176: 118125 | K176: PRE | L176: =IF(K176="FIN",3,IF(OR(K176="SEM",K176="SEMI"),2,IF(OR(K176="PRE",K176="HEAT"),1,IF(V176="YES",4,2)))) | M176: LCM | N176: 200 | O176: Free | P176: 200 Free | Q176: LCM_200_FREE | R176: 112.41 | S176: =IF(R176="","",IF(R176>=60,INT(R176/60)&":"&TEXT(MOD(R176,60),"00.00"),TEXT(R176,"0.00"))) | T176: =IFERROR((G176-INDEX('01_Swimmers'!$E$5:$E$22,MATCH(B176,'01_Swimmers'!$A$5:$A$22,0)))/'00_Control'!$B$10,"") | U176: =IF(T176="","",INT(T176)) | V176: NO | W176: YES | X176: NO | Y176: 7 | Z176: 6 | AA176: 3 | AB176: https://www.swimcloud.com/results/118125/event/7/?id=18939900#time18939900 | AC176: SwimCloud API v6 2026-10-08 | AD176: Caeleb Dressel|2018-06-01|LCM|200|Free|112.41|Mel Zajac Jr. Internation|PRE|False | AE176: =G176+L176/1000+ROW()/1000000000 | AF176: =IF(C176<>"Grayson Coulter","",COUNTIFS($C$5:$C$2991,"Grayson Coulter",$Q$5:$Q$2991,Q176,$AE$5:$AE$2991,"<="&AE176,$R$5:$R$2991,"<"&R176)) | AG176: =IF(OR(C176<>"Grayson Coulter",G176<'00_Control'!$B$7),"",--(AF176<5)) | AH176: =IF(OR(C176<>"Grayson Coulter",G176<'00_Control'!$B$7),"",--(AF176<10)) | AI176: =IF(AND(C176="Grayson Coulter",G176>='00_Control'!$B$7),"YES","NO") | AJ176: OK
A177: SM000173 | B177: SW010 | C177: Caeleb Dressel | D177: SwimCloud | E177: 2361642 | F177: 18939983 | G177: 43252 | H177: Mel Zajac Jr. Internation | I177: 118125 | K177: FIN | L177: =IF(K177="FIN",3,IF(OR(K177="SEM",K177="SEMI"),2,IF(OR(K177="PRE",K177="HEAT"),1,IF(V177="YES",4,2)))) | M177: LCM | N177: 200 | O177: Free | P177: 200 Free | Q177: LCM_200_FREE | R177: 108.73 | S177: =IF(R177="","",IF(R177>=60,INT(R177/60)&":"&TEXT(MOD(R177,60),"00.00"),TEXT(R177,"0.00"))) | T177: =IFERROR((G177-INDEX('01_Swimmers'!$E$5:$E$22,MATCH(B177,'01_Swimmers'!$A$5:$A$22,0)))/'00_Control'!$B$10,"") | U177: =IF(T177="","",INT(T177)) | V177: NO | W177: YES | X177: NO | Y177: 3 | Z177: 3 | AA177: 1 | AB177: https://www.swimcloud.com/results/118125/event/7/?id=18939983#time18939983 | AC177: SwimCloud API v6 2026-10-08 | AD177: Caeleb Dressel|2018-06-01|LCM|200|Free|108.73|Mel Zajac Jr. Internation|FIN|False | AE177: =G177+L177/1000+ROW()/1000000000 | AF177: =IF(C177<>"Grayson Coulter","",COUNTIFS($C$5:$C$2991,"Grayson Coulter",$Q$5:$Q$2991,Q177,$AE$5:$AE$2991,"<="&AE177,$R$5:$R$2991,"<"&R177)) | AG177: =IF(OR(C177<>"Grayson Coulter",G177<'00_Control'!$B$7),"",--(AF177<5)) | AH177: =IF(OR(C177<>"Grayson Coulter",G177<'00_Control'!$B$7),"",--(AF177<10)) | AI177: =IF(AND(C177="Grayson Coulter",G177>='00_Control'!$B$7),"YES","NO") | AJ177: OK
A178: SM000174 | B178: SW010 | C178: Caeleb Dressel | D178: SwimCloud | E178: 2361642 | F178: 18940213 | G178: 43253 | H178: Mel Zajac Jr. Internation | I178: 118125 | K178: PRE | L178: =IF(K178="FIN",3,IF(OR(K178="SEM",K178="SEMI"),2,IF(OR(K178="PRE",K178="HEAT"),1,IF(V178="YES",4,2)))) | M178: LCM | N178: 100 | O178: Fly | P178: 100 Fly | Q178: LCM_100_FLY | R178: 54.28 | S178: =IF(R178="","",IF(R178>=60,INT(R178/60)&":"&TEXT(MOD(R178,60),"00.00"),TEXT(R178,"0.00"))) | T178: =IFERROR((G178-INDEX('01_Swimmers'!$E$5:$E$22,MATCH(B178,'01_Swimmers'!$A$5:$A$22,0)))/'00_Control'!$B$10,"") | U178: =IF(T178="","",INT(T178)) | V178: NO | W178: YES | X178: NO | Y178: 7 | Z178: 5 | AA178: 2 | AB178: https://www.swimcloud.com/results/118125/event/16/?id=18940213#time18940213 | AC178: SwimCloud API v6 2026-10-08 | AD178: Caeleb Dressel|2018-06-02|LCM|100|Fly|54.28|Mel Zajac Jr. Internation|PRE|False | AE178: =G178+L178/1000+ROW()/1000000000 | AF178: =IF(C178<>"Grayson Coulter","",COUNTIFS($C$5:$C$2991,"Grayson Coulter",$Q$5:$Q$2991,Q178,$AE$5:$AE$2991,"<="&AE178,$R$5:$R$2991,"<"&R178)) | AG178: =IF(OR(C178<>"Grayson Coulter",G178<'00_Control'!$B$7),"",--(AF178<5)) | AH178: =IF(OR(C178<>"Grayson Coulter",G178<'00_Control'!$B$7),"",--(AF178<10)) | AI178: =IF(AND(C178="Grayson Coulter",G178>='00_Control'!$B$7),"YES","NO") | AJ178: OK
A179: SM000175 | B179: SW010 | C179: Caeleb Dressel | D179: SwimCloud | E179: 2361642 | F179: 18940297 | G179: 43253 | H179: Mel Zajac Jr. Internation | I179: 118125 | K179: FIN | L179: =IF(K179="FIN",3,IF(OR(K179="SEM",K179="SEMI"),2,IF(OR(K179="PRE",K179="HEAT"),1,IF(V179="YES",4,2)))) | M179: LCM | N179: 100 | O179: Fly | P179: 100 Fly | Q179: LCM_100_FLY | R179: 52.45 | S179: =IF(R179="","",IF(R179>=60,INT(R179/60)&":"&TEXT(MOD(R179,60),"00.00"),TEXT(R179,"0.00"))) | T179: =IFERROR((G179-INDEX('01_Swimmers'!$E$5:$E$22,MATCH(B179,'01_Swimmers'!$A$5:$A$22,0)))/'00_Control'!$B$10,"") | U179: =IF(T179="","",INT(T179)) | V179: NO | W179: YES | X179: NO | Y179: 3 | Z179: 5 | AA179: 1 | AB179: https://www.swimcloud.com/results/118125/event/16/?id=18940297#time18940297 | AC179: SwimCloud API v6 2026-10-08 | AD179: Caeleb Dressel|2018-06-02|LCM|100|Fly|52.45|Mel Zajac Jr. Internation|FIN|False | AE179: =G179+L179/1000+ROW()/1000000000 | AF179: =IF(C179<>"Grayson Coulter","",COUNTIFS($C$5:$C$2991,"Grayson Coulter",$Q$5:$Q$2991,Q179,$AE$5:$AE$2991,"<="&AE179,$R$5:$R$2991,"<"&R179)) | AG179: =IF(OR(C179<>"Grayson Coulter",G179<'00_Control'!$B$7),"",--(AF179<5)) | AH179: =IF(OR(C179<>"Grayson Coulter",G179<'00_Control'!$B$7),"",--(AF179<10)) | AI179: =IF(AND(C179="Grayson Coulter",G179>='00_Control'!$B$7),"YES","NO") | AJ179: OK
A180: SM000176 | B180: SW010 | C180: Caeleb Dressel | D180: SwimCloud | E180: 2361642 | F180: 18940495 | G180: 43254 | H180: Mel Zajac Jr. Internation | I180: 118125 | K180: PRE | L180: =IF(K180="FIN",3,IF(OR(K180="SEM",K180="SEMI"),2,IF(OR(K180="PRE",K180="HEAT"),1,IF(V180="YES",4,2)))) | M180: LCM | N180: 100 | O180: Free | P180: 100 Free | Q180: LCM_100_FREE | R180: 50.68 | S180: =IF(R180="","",IF(R180>=60,INT(R180/60)&":"&TEXT(MOD(R180,60),"00.00"),TEXT(R180,"0.00"))) | T180: =IFERROR((G180-INDEX('01_Swimmers'!$E$5:$E$22,MATCH(B180,'01_Swimmers'!$A$5:$A$22,0)))/'00_Control'!$B$10,"") | U180: =IF(T180="","",INT(T180)) | V180: NO | W180: YES | X180: NO | Y180: 6 | Z180: 4 | AA180: 2 | AB180: https://www.swimcloud.com/results/118125/event/35/?id=18940495#time18940495 | AC180: SwimCloud API v6 2026-10-08 | AD180: Caeleb Dressel|2018-06-03|LCM|100|Free|50.68|Mel Zajac Jr. Internation|PRE|False | AE180: =G180+L180/1000+ROW()/1000000000 | AF180: =IF(C180<>"Grayson Coulter","",COUNTIFS($C$5:$C$2991,"Grayson Coulter",$Q$5:$Q$2991,Q180,$AE$5:$AE$2991,"<="&AE180,$R$5:$R$2991,"<"&R180)) | AG180: =IF(OR(C180<>"Grayson Coulter",G180<'00_Control'!$B$7),"",--(AF180<5)) | AH180: =IF(OR(C180<>"Grayson Coulter",G180<'00_Control'!$B$7),"",--(AF180<10)) | AI180: =IF(AND(C180="Grayson Coulter",G180>='00_Control'!$B$7),"YES","NO") | AJ180: OK
A181: SM000177 | B181: SW010 | C181: Caeleb Dressel | D181: SwimCloud | E181: 2361642 | F181: 18940638 | G181: 43254 | H181: Mel Zajac Jr. Internation | I181: 118125 | K181: FIN | L181: =IF(K181="FIN",3,IF(OR(K181="SEM",K181="SEMI"),2,IF(OR(K181="PRE",K181="HEAT"),1,IF(V181="YES",4,2)))) | M181: LCM | N181: 100 | O181: Free | P181: 100 Free | Q181: LCM_100_FREE | R181: 49.58 | S181: =IF(R181="","",IF(R181>=60,INT(R181/60)&":"&TEXT(MOD(R181,60),"00.00"),TEXT(R181,"0.00"))) | T181: =IFERROR((G181-INDEX('01_Swimmers'!$E$5:$E$22,MATCH(B181,'01_Swimmers'!$A$5:$A$22,0)))/'00_Control'!$B$10,"") | U181: =IF(T181="","",INT(T181)) | V181: NO | W181: YES | X181: NO | Y181: 3 | Z181: 5 | AA181: 2 | AB181: https://www.swimcloud.com/results/118125/event/35/?id=18940638#time18940638 | AC181: SwimCloud API v6 2026-10-08 | AD181: Caeleb Dressel|2018-06-03|LCM|100|Free|49.58|Mel Zajac Jr. Internation|FIN|False | AE181: =G181+L181/1000+ROW()/1000000000 | AF181: =IF(C181<>"Grayson Coulter","",COUNTIFS($C$5:$C$2991,"Grayson Coulter",$Q$5:$Q$2991,Q181,$AE$5:$AE$2991,"<="&AE181,$R$5:$R$2991,"<"&R181)) | AG181: =IF(OR(C181<>"Grayson Coulter",G181<'00_Control'!$B$7),"",--(AF181<5)) | AH181: =IF(OR(C181<>"Grayson Coulter",G181<'00_Control'!$B$7),"",--(AF181<10)) | AI181: =IF(AND(C181="Grayson Coulter",G181>='00_Control'!$B$7),"YES","NO") | AJ181: OK
A182: SM000178 | B182: SW010 | C182: Caeleb Dressel | D182: SwimCloud | E182: 2361642 | F182: 18207687 | G182: 43259 | H182: TYR Pro Swim Series - Santa Clara | I182: 116513 | K182: PRE | L182: =IF(K182="FIN",3,IF(OR(K182="SEM",K182="SEMI"),2,IF(OR(K182="PRE",K182="HEAT"),1,IF(V182="YES",4,2)))) | M182: LCM | N182: 100 | O182: Fly | P182: 100 Fly | Q182: LCM_100_FLY | R182: 53.15 | S182: =IF(R182="","",IF(R182>=60,INT(R182/60)&":"&TEXT(MOD(R182,60),"00.00"),TEXT(R182,"0.00"))) | T182: =IFERROR((G182-INDEX('01_Swimmers'!$E$5:$E$22,MATCH(B182,'01_Swimmers'!$A$5:$A$22,0)))/'00_Control'!$B$10,"") | U182: =IF(T182="","",INT(T182)) | V182: NO | W182: YES | X182: NO | Y182: 7 | Z182: 5 | AA182: 4 | AB182: https://www.swimcloud.com/results/116513/event/6/?id=18207687#time18207687 | AC182: SwimCloud API v6 2026-10-08 | AD182: Caeleb Dressel|2018-06-08|LCM|100|Fly|53.15|TYR Pro Swim Series - Santa Clara|PRE|False | AE182: =G182+L182/1000+ROW()/1000000000 | AF182: =IF(C182<>"Grayson Coulter","",COUNTIFS($C$5:$C$2991,"Grayson Coulter",$Q$5:$Q$2991,Q182,$AE$5:$AE$2991,"<="&AE182,$R$5:$R$2991,"<"&R182)) | AG182: =IF(OR(C182<>"Grayson Coulter",G182<'00_Control'!$B$7),"",--(AF182<5)) | AH182: =IF(OR(C182<>"Grayson Coulter",G182<'00_Control'!$B$7),"",--(AF182<10)) | AI182: =IF(AND(C182="Grayson Coulter",G182>='00_Control'!$B$7),"YES","NO") | AJ182: OK
A183: SM000179 | B183: SW010 | C183: Caeleb Dressel | D183: SwimCloud | E183: 2361642 | F183: 18207775 | G183: 43259 | H183: TYR Pro Swim Series - Santa Clara | I183: 116513 | K183: FIN | L183: =IF(K183="FIN",3,IF(OR(K183="SEM",K183="SEMI"),2,IF(OR(K183="PRE",K183="HEAT"),1,IF(V183="YES",4,2)))) | M183: LCM | N183: 100 | O183: Fly | P183: 100 Fly | Q183: LCM_100_FLY | R183: 52.2 | S183: =IF(R183="","",IF(R183>=60,INT(R183/60)&":"&TEXT(MOD(R183,60),"00.00"),TEXT(R183,"0.00"))) | T183: =IFERROR((G183-INDEX('01_Swimmers'!$E$5:$E$22,MATCH(B183,'01_Swimmers'!$A$5:$A$22,0)))/'00_Control'!$B$10,"") | U183: =IF(T183="","",INT(T183)) | V183: NO | W183: YES | X183: NO | Y183: 2 | Z183: 7 | AA183: 1 | AB183: https://www.swimcloud.com/results/116513/event/6/?id=18207775#time18207775 | AC183: SwimCloud API v6 2026-10-08 | AD183: Caeleb Dressel|2018-06-08|LCM|100|Fly|52.2|TYR Pro Swim Series - Santa Clara|FIN|False | AE183: =G183+L183/1000+ROW()/1000000000 | AF183: =IF(C183<>"Grayson Coulter","",COUNTIFS($C$5:$C$2991,"Grayson Coulter",$Q$5:$Q$2991,Q183,$AE$5:$AE$2991,"<="&AE183,$R$5:$R$2991,"<"&R183)) | AG183: =IF(OR(C183<>"Grayson Coulter",G183<'00_Control'!$B$7),"",--(AF183<5)) | AH183: =IF(OR(C183<>"Grayson Coulter",G183<'00_Control'!$B$7),"",--(AF183<10)) | AI183: =IF(AND(C183="Grayson Coulter",G183>='00_Control'!$B$7),"YES","NO") | AJ183: OK
... A196: SM000192 | B196: SW010 | C196: Caeleb Dressel | D196: SwimCloud | E196: 2361642 | F196: 20180809 | G196: 43322 | H196: Pan Pacific Championships | I196: 122897 | K196: PRE | L196: =IF(K196="FIN",3,IF(OR(K196="SEM",K196="SEMI"),2,IF(OR(K196="PRE",K196="HEAT"),1,IF(V196="YES",4,2)))) | M196: LCM | N196: 200 | O196: Free | P196: 200 Free | Q196: LCM_200_FREE | R196: 107.89 | S196: =IF(R196="","",IF(R196>=60,INT(R196/60)&":"&TEXT(MOD(R196,60),"00.00"),TEXT(R196,"0.00"))) | T196: =IFERROR((G196-INDEX('01_Swimmers'!$E$5:$E$22,MATCH(B196,'01_Swimmers'!$A$5:$A$22,0)))/'00_Control'!$B$10,"") | U196: =IF(T196="","",INT(T196)) | V196: NO | W196: YES | X196: NO | Y196: 5 | Z196: 7 | AA196: 18 | AB196: https://www.swimcloud.com/results/122897/event/17/?id=20180809#time20180809 | AC196: SwimCloud API v6 2026-10-08 | AD196: Caeleb Dressel|2018-08-10|LCM|200|Free|107.89|Pan Pacific Championships|PRE|False | AE196: =G196+L196/1000+ROW()/1000000000 | AF196: =IF(C196<>"Grayson Coulter","",COUNTIFS($C$5:$C$2991,"Grayson Coulter",$Q$5:$Q$2991,Q196,$AE$5:$AE$2991,"<="&AE196,$R$5:$R$2991,"<"&R196)) | AG196: =IF(OR(C196<>"Grayson Coulter",G196<'00_Control'!$B$7),"",--(AF196<5)) | AH196: =IF(OR(C196<>"Grayson Coulter",G196<'00_Control'!$B$7),"",--(AF196<10)) | AI196: =IF(AND(C196="Grayson Coulter",G196>='00_Control'!$B$7),"YES","NO") | AJ196: OK
A197: SM000193 | B197: SW010 | C197: Caeleb Dressel | D197: SwimCloud | E197: 2361642 | F197: 22327924 | G197: 43445 | H197: 14th FINA World Short Course Championships | I197: 137600 | K197: FIN | L197: =IF(K197="FIN",3,IF(OR(K197="SEM",K197="SEMI"),2,IF(OR(K197="PRE",K197="HEAT"),1,IF(V197="YES",4,2)))) | M197: SCM | N197: 100 | O197: Free | P197: 100 Free | Q197: SCM_100_FREE | R197: 45.66 | S197: =IF(R197="","",IF(R197>=60,INT(R197/60)&":"&TEXT(MOD(R197,60),"00.00"),TEXT(R197,"0.00"))) | T197: =IFERROR((G197-INDEX('01_Swimmers'!$E$5:$E$22,MATCH(B197,'01_Swimmers'!$A$5:$A$22,0)))/'00_Control'!$B$10,"") | U197: =IF(T197="","",INT(T197)) | V197: YES | W197: YES | X197: NO | Y197: 1 | Z197: 3 | AB197: https://www.swimcloud.com/results/137600/event/11/?id=22326664#time22326664 | AC197: SwimCloud API v6 2026-10-08 | AD197: Caeleb Dressel|2018-12-11|SCM|100|Free|45.66|14th FINA World Short Course Championships|FIN|True | AE197: =G197+L197/1000+ROW()/1000000000 | AF197: =IF(C197<>"Grayson Coulter","",COUNTIFS($C$5:$C$2991,"Grayson Coulter",$Q$5:$Q$2991,Q197,$AE$5:$AE$2991,"<="&AE197,$R$5:$R$2991,"<"&R197)) | AG197: =IF(OR(C197<>"Grayson Coulter",G197<'00_Control'!$B$7),"",--(AF197<5)) | AH197: =IF(OR(C197<>"Grayson Coulter",G197<'00_Control'!$B$7),"",--(AF197<10)) | AI197: =IF(AND(C197="Grayson Coulter",G197>='00_Control'!$B$7),"YES","NO") | AJ197: OK
A198: SM000194 | B198: SW010 | C198: Caeleb Dressel | D198: SwimCloud | E198: 2361642 | F198: 22326557 | G198: 43446 | H198: 14th FINA World Short Course Championships | I198: 137600 | K198: PRE | L198: =IF(K198="FIN",3,IF(OR(K198="SEM",K198="SEMI"),2,IF(OR(K198="PRE",K198="HEAT"),1,IF(V198="YES",4,2)))) | M198: SCM | N198: 100 | O198: Fly | P198: 100 Fly | Q198: SCM_100_FLY | R198: 49.23 | S198: =IF(R198="","",IF(R198>=60,INT(R198/60)&":"&TEXT(MOD(R198,60),"00.00"),TEXT(R198,"0.00"))) | T198: =IFERROR((G198-INDEX('01_Swimmers'!$E$5:$E$22,MATCH(B198,'01_Swimmers'!$A$5:$A$22,0)))/'00_Control'!$B$10,"") | U198: =IF(T198="","",INT(T198)) | V198: NO | W198: YES | X198: NO | Y198: 6 | Z198: 6 | AA198: 1 | AB198: https://www.swimcloud.com/results/137600/event/15/?id=22326557#time22326557 | AC198: SwimCloud API v6 2026-10-08 | AD198: Caeleb Dressel|2018-12-12|SCM|100|Fly|49.23|14th FINA World Short Course Championships|PRE|False | AE198: =G198+L198/1000+ROW()/1000000000 | AF198: =IF(C198<>"Grayson Coulter","",COUNTIFS($C$5:$C$2991,"Grayson Coulter",$Q$5:$Q$2991,Q198,$AE$5:$AE$2991,"<="&AE198,$R$5:$R$2991,"<"&R198)) | AG198: =IF(OR(C198<>"Grayson Coulter",G198<'00_Control'!$B$7),"",--(AF198<5)) | AH198: =IF(OR(C198<>"Grayson Coulter",G198<'00_Control'!$B$7),"",--(AF198<10)) | AI198: =IF(AND(C198="Grayson Coulter",G198>='00_Control'!$B$7),"YES","NO") | AJ198: OK
A199: SM000195 | B199: SW010 | C199: Caeleb Dressel | D199: SwimCloud | E199: 2361642 | F199: 22326558 | G199: 43446 | H199: 14th FINA World Short Course Championships | I199: 137600 | K199: SEM | L199: =IF(K199="FIN",3,IF(OR(K199="SEM",K199="SEMI"),2,IF(OR(K199="PRE",K199="HEAT"),1,IF(V199="YES",4,2)))) | M199: SCM | N199: 100 | O199: Fly | P199: 100 Fly | Q199: SCM_100_FLY | R199: 48.93 | S199: =IF(R199="","",IF(R199>=60,INT(R199/60)&":"&TEXT(MOD(R199,60),"00.00"),TEXT(R199,"0.00"))) | T199: =IFERROR((G199-INDEX('01_Swimmers'!$E$5:$E$22,MATCH(B199,'01_Swimmers'!$A$5:$A$22,0)))/'00_Control'!$B$10,"") | U199: =IF(T199="","",INT(T199)) | V199: NO | W199: YES | X199: NO | Y199: 2 | Z199: 4 | AA199: 1 | AB199: https://www.swimcloud.com/results/137600/event/15/?id=22326558#time22326558 | AC199: SwimCloud API v6 2026-10-08 | AD199: Caeleb Dressel|2018-12-12|SCM|100|Fly|48.93|14th FINA World Short Course Championships|SEM|False | AE199: =G199+L199/1000+ROW()/1000000000 | AF199: =IF(C199<>"Grayson Coulter","",COUNTIFS($C$5:$C$2991,"Grayson Coulter",$Q$5:$Q$2991,Q199,$AE$5:$AE$2991,"<="&AE199,$R$5:$R$2991,"<"&R199)) | AG199: =IF(OR(C199<>"Grayson Coulter",G199<'00_Control'!$B$7),"",--(AF199<5)) | AH199: =IF(OR(C199<>"Grayson Coulter",G199<'00_Control'!$B$7),"",--(AF199<10)) | AI199: =IF(AND(C199="Grayson Coulter",G199>='00_Control'!$B$7),"YES","NO") | AJ199: OK
A200: SM000196 | B200: SW010 | C200: Caeleb Dressel | D200: SwimCloud | E200: 2361642 | F200: 22326556 | G200: 43447 | H200: 14th FINA World Short Course Championships | I200: 137600 | K200: FIN | L200: =IF(K200="FIN",3,IF(OR(K200="SEM",K200="SEMI"),2,IF(OR(K200="PRE",K200="HEAT"),1,IF(V200="YES",4,2)))) | M200: SCM | N200: 100 | O200: Fly | P200: 100 Fly | Q200: SCM_100_FLY | R200: 48.71 | S200: =IF(R200="","",IF(R200>=60,INT(R200/60)&":"&TEXT(MOD(R200,60),"00.00"),TEXT(R200,"0.00"))) | T200: =IFERROR((G200-INDEX('01_Swimmers'!$E$5:$E$22,MATCH(B200,'01_Swimmers'!$A$5:$A$22,0)))/'00_Control'!$B$10,"") | U200: =IF(T200="","",INT(T200)) | V200: NO | W200: YES | X200: NO | Y200: 1 | Z200: 4 | AA200: 2 | AB200: https://www.swimcloud.com/results/137600/event/15/?id=22326556#time22326556 | AC200: SwimCloud API v6 2026-10-08 | AD200: Caeleb Dressel|2018-12-13|SCM|100|Fly|48.71|14th FINA World Short Course Championships|FIN|False | AE200: =G200+L200/1000+ROW()/1000000000 | AF200: =IF(C200<>"Grayson Coulter","",COUNTIFS($C$5:$C$2991,"Grayson Coulter",$Q$5:$Q$2991,Q200,$AE$5:$AE$2991,"<="&AE200,$R$5:$R$2991,"<"&R200)) | AG200: =IF(OR(C200<>"Grayson Coulter",G200<'00_Control'!$B$7),"",--(AF200<5)) | AH200: =IF(OR(C200<>"Grayson Coulter",G200<'00_Control'!$B$7),"",--(AF200<10)) | AI200: =IF(AND(C200="Grayson Coulter",G200>='00_Control'!$B$7),"YES","NO") | AJ200: OK
A201: SM000197 | B201: SW010 | C201: Caeleb Dressel | D201: SwimCloud | E201: 2361642 | F201: 22326560 | G201: 43449 | H201: 14th FINA World Short Course Championships | I201: 137600 | K201: PRE | L201: =IF(K201="FIN",3,IF(OR(K201="SEM",K201="SEMI"),2,IF(OR(K201="PRE",K201="HEAT"),1,IF(V201="YES",4,2)))) | M201: SCM | N201: 100 | O201: Free | P201: 100 Free | Q201: SCM_100_FREE | R201: 45.98 | S201: =IF(R201="","",IF(R201>=60,INT(R201/60)&":"&TEXT(MOD(R201,60),"00.00"),TEXT(R201,"0.00"))) | T201: =IFERROR((G201-INDEX('01_Swimmers'!$E$5:$E$22,MATCH(B201,'01_Swimmers'!$A$5:$A$22,0)))/'00_Control'!$B$10,"") | U201: =IF(T201="","",INT(T201)) | V201: NO | W201: YES | X201: NO | Y201: 9 | AA201: 1 | AB201: https://www.swimcloud.com/results/137600/event/37/?id=22326560#time22326560 | AC201: SwimCloud API v6 2026-10-08 | AD201: Caeleb Dressel|2018-12-15|SCM|100|Free|45.98|14th FINA World Short Course Championships|PRE|False | AE201: =G201+L201/1000+ROW()/1000000000 | AF201: =IF(C201<>"Grayson Coulter","",COUNTIFS($C$5:$C$2991,"Grayson Coulter",$Q$5:$Q$2991,Q201,$AE$5:$AE$2991,"<="&AE201,$R$5:$R$2991,"<"&R201)) | AG201: =IF(OR(C201<>"Grayson Coulter",G201<'00_Control'!$B$7),"",--(AF201<5)) | AH201: =IF(OR(C201<>"Grayson Coulter",G201<'00_Control'!$B$7),"",--(AF201<10)) | AI201: =IF(AND(C201="Grayson Coulter",G201>='00_Control'!$B$7),"YES","NO") | AJ201: OK
A202: SM000198 | B202: SW010 | C202: Caeleb Dressel | D202: SwimCloud | E202: 2361642 | F202: 22326561 | G202: 43449 | H202: 14th FINA World Short Course Championships | I202: 137600 | K202: SEM | L202: =IF(K202="FIN",3,IF(OR(K202="SEM",K202="SEMI"),2,IF(OR(K202="PRE",K202="HEAT"),1,IF(V202="YES",4,2)))) | M202: SCM | N202: 100 | O202: Free | P202: 100 Free | Q202: SCM_100_FREE | R202: 46.09 | S202: =IF(R202="","",IF(R202>=60,INT(R202/60)&":"&TEXT(MOD(R202,60),"00.00"),TEXT(R202,"0.00"))) | T202: =IFERROR((G202-INDEX('01_Swimmers'!$E$5:$E$22,MATCH(B202,'01_Swimmers'!$A$5:$A$22,0)))/'00_Control'!$B$10,"") | U202: =IF(T202="","",INT(T202)) | V202: NO | W202: YES | X202: NO | Y202: 2 | Z202: 4 | AA202: 3 | AB202: https://www.swimcloud.com/results/137600/event/37/?id=22326561#time22326561 | AC202: SwimCloud API v6 2026-10-08 | AD202: Caeleb Dressel|2018-12-15|SCM|100|Free|46.09|14th FINA World Short Course Championships|SEM|False | AE202: =G202+L202/1000+ROW()/1000000000 | AF202: =IF(C202<>"Grayson Coulter","",COUNTIFS($C$5:$C$2991,"Grayson Coulter",$Q$5:$Q$2991,Q202,$AE$5:$AE$2991,"<="&AE202,$R$5:$R$2991,"<"&R202)) | AG202: =IF(OR(C202<>"Grayson Coulter",G202<'00_Control'!$B$7),"",--(AF202<5)) | AH202: =IF(OR(C202<>"Grayson Coulter",G202<'00_Control'!$B$7),"",--(AF202<10)) | AI202: =IF(AND(C202="Grayson Coulter",G202>='00_Control'!$B$7),"YES","NO") | AJ202: OK
A203: SM000199 | B203: SW010 | C203: Caeleb Dressel | D203: SwimCloud | E203: 2361642 | F203: 22326559 | G203: 43450 | H203: 14th FINA World Short Course Championships | I203: 137600 | K203: FIN | L203: =IF(K203="FIN",3,IF(OR(K203="SEM",K203="SEMI"),2,IF(OR(K203="PRE",K203="HEAT"),1,IF(V203="YES",4,2)))) | M203: SCM | N203: 100 | O203: Free | P203: 100 Free | Q203: SCM_100_FREE | R203: 45.62 | S203: =IF(R203="","",IF(R203>=60,INT(R203/60)&":"&TEXT(MOD(R203,60),"00.00"),TEXT(R203,"0.00"))) | T203: =IFERROR((G203-INDEX('01_Swimmers'!$E$5:$E$22,MATCH(B203,'01_Swimmers'!$A$5:$A$22,0)))/'00_Control'!$B$10,"") | U203: =IF(T203="","",INT(T203)) | V203: NO | W203: YES | X203: NO | Y203: 1 | Z203: 3 | AA203: 1 | AB203: https://www.swimcloud.com/results/137600/event/37/?id=22326559#time22326559 | AC203: SwimCloud API v6 2026-10-08 | AD203: Caeleb Dressel|2018-12-16|SCM|100|Free|45.62|14th FINA World Short Course Championships|FIN|False | AE203: =G203+L203/1000+ROW()/1000000000 | AF203: =IF(C203<>"Grayson Coulter","",COUNTIFS($C$5:$C$2991,"Grayson Coulter",$Q$5:$Q$2991,Q203,$AE$5:$AE$2991,"<="&AE203,$R$5:$R$2991,"<"&R203)) | AG203: =IF(OR(C203<>"Grayson Coulter",G203<'00_Control'!$B$7),"",--(AF203<5)) | AH203: =IF(OR(C203<>"Grayson Coulter",G203<'00_Control'!$B$7),"",--(AF203<10)) | AI203: =IF(AND(C203="Grayson Coulter",G203>='00_Control'!$B$7),"YES","NO") | AJ203: OK
A204: SM000200 | B204: SW010 | C204: Caeleb Dressel | D204: SwimCloud | E204: 2361642 | F204: 25633574 | G204: 43531 | H204: TYR Pro Swim Series - Des Moines | I204: 128901 | K204: PRE | L204: =IF(K204="FIN",3,IF(OR(K204="SEM",K204="SEMI"),2,IF(OR(K204="PRE",K204="HEAT"),1,IF(V204="YES",4,2)))) | M204: LCM | N204: 100 | O204: Free | P204: 100 Free | Q204: LCM_100_FREE | R204: 50.49 | S204: =IF(R204="","",IF(R204>=60,INT(R204/60)&":"&TEXT(MOD(R204,60),"00.00"),TEXT(R204,"0.00"))) | T204: =IFERROR((G204-INDEX('01_Swimmers'!$E$5:$E$22,MATCH(B204,'01_Swimmers'!$A$5:$A$22,0)))/'00_Control'!$B$10,"") | U204: =IF(T204="","",INT(T204)) | V204: NO | W204: YES | X204: NO | Y204: 9 | Z204: 4 | AA204: 15 | AB204: https://www.swimcloud.com/results/128901/event/4/?id=25633574#time25633574 | AC204: SwimCloud API v6 2026-10-08 | AD204: Caeleb Dressel|2019-03-07|LCM|100|Free|50.49|TYR Pro Swim Series - Des Moines|PRE|False | AE204: =G204+L204/1000+ROW()/1000000000 | AF204: =IF(C204<>"Grayson Coulter","",COUNTIFS($C$5:$C$2991,"Grayson Coulter",$Q$5:$Q$2991,Q204,$AE$5:$AE$2991,"<="&AE204,$R$5:$R$2991,"<"&R204)) | AG204: =IF(OR(C204<>"Grayson Coulter",G204<'00_Control'!$B$7),"",--(AF204<5)) | AH204: =IF(OR(C204<>"Grayson Coulter",G204<'00_Control'!$B$7),"",--(AF204<10)) | AI204: =IF(AND(C204="Grayson Coulter",G204>='00_Control'!$B$7),"YES","NO") | AJ204: OK
A205: SM000201 | B205: SW010 | C205: Caeleb Dressel | D205: SwimCloud | E205: 2361642 | F205: 25633575 | G205: 43531 | H205: TYR Pro Swim Series - Des Moines | I205: 128901 | K205: FIN | L205: =IF(K205="FIN",3,IF(OR(K205="SEM",K205="SEMI"),2,IF(OR(K205="PRE",K205="HEAT"),1,IF(V205="YES",4,2)))) | M205: LCM | N205: 100 | O205: Free | P205: 100 Free | Q205: LCM_100_FREE | R205: 48.71 | S205: =IF(R205="","",IF(R205>=60,INT(R205/60)&":"&TEXT(MOD(R205,60),"00.00"),TEXT(R205,"0.00"))) | T205: =IFERROR((G205-INDEX('01_Swimmers'!$E$5:$E$22,MATCH(B205,'01_Swimmers'!$A$5:$A$22,0)))/'00_Control'!$B$10,"") | U205: =IF(T205="","",INT(T205)) | V205: NO | W205: YES | X205: NO | Y205: 1 | Z205: 7 | AA205: 9 | AB205: https://www.swimcloud.com/results/128901/event/4/?id=25633575#time25633575 | AC205: SwimCloud API v6 2026-10-08 | AD205: Caeleb Dressel|2019-03-07|LCM|100|Free|48.71|TYR Pro Swim Series - Des Moines|FIN|False | AE205: =G205+L205/1000+ROW()/1000000000 | AF205: =IF(C205<>"Grayson Coulter","",COUNTIFS($C$5:$C$2991,"Grayson Coulter",$Q$5:$Q$2991,Q205,$AE$5:$AE$2991,"<="&AE205,$R$5:$R$2991,"<"&R205)) | AG205: =IF(OR(C205<>"Grayson Coulter",G205<'00_Control'!$B$7),"",--(AF205<5)) | AH205: =IF(OR(C205<>"Grayson Coulter",G205<'00_Control'!$B$7),"",--(AF205<10)) | AI205: =IF(AND(C205="Grayson Coulter",G205>='00_Control'!$B$7),"YES","NO") | AJ205: OK
A206: SM000202 | B206: SW010 | C206: Caeleb Dressel | D206: SwimCloud | E206: 2361642 | F206: 25633676 | G206: 43532 | H206: TYR Pro Swim Series - Des Moines | I206: 128901 | K206: PRE | L206: =IF(K206="FIN",3,IF(OR(K206="SEM",K206="SEMI"),2,IF(OR(K206="PRE",K206="HEAT"),1,IF(V206="YES",4,2)))) | M206: LCM | N206: 200 | O206: Free | P206: 200 Free | Q206: LCM_200_FREE | R206: 110.17 | S206: =IF(R206="","",IF(R206>=60,INT(R206/60)&":"&TEXT(MOD(R206,60),"00.00"),TEXT(R206,"0.00"))) | T206: =IFERROR((G206-INDEX('01_Swimmers'!$E$5:$E$22,MATCH(B206,'01_Swimmers'!$A$5:$A$22,0)))/'00_Control'!$B$10,"") | U206: =IF(T206="","",INT(T206)) | V206: NO | W206: YES | X206: NO | Y206: 5 | Z206: 5 | AA206: 7 | AB206: https://www.swimcloud.com/results/128901/event/14/?id=25633676#time25633676 | AC206: SwimCloud API v6 2026-10-08 | AD206: Caeleb Dressel|2019-03-08|LCM|200|Free|110.17|TYR Pro Swim Series - Des Moines|PRE|False | AE206: =G206+L206/1000+ROW()/1000000000 | AF206: =IF(C206<>"Grayson Coulter","",COUNTIFS($C$5:$C$2991,"Grayson Coulter",$Q$5:$Q$2991,Q206,$AE$5:$AE$2991,"<="&AE206,$R$5:$R$2991,"<"&R206)) | AG206: =IF(OR(C206<>"Grayson Coulter",G206<'00_Control'!$B$7),"",--(AF206<5)) | AH206: =IF(OR(C206<>"Grayson Coulter",G206<'00_Control'!$B$7),"",--(AF206<10)) | AI206: =IF(AND(C206="Grayson Coulter",G206>='00_Control'!$B$7),"YES","NO") | AJ206: OK
A207: SM000203 | B207: SW010 | C207: Caeleb Dressel | D207: SwimCloud | E207: 2361642 | F207: 25633677 | G207: 43532 | H207: TYR Pro Swim Series - Des Moines | I207: 128901 | K207: FIN | L207: =IF(K207="FIN",3,IF(OR(K207="SEM",K207="SEMI"),2,IF(OR(K207="PRE",K207="HEAT"),1,IF(V207="YES",4,2)))) | M207: LCM | N207: 200 | O207: Free | P207: 200 Free | Q207: LCM_200_FREE | R207: 109.68 | S207: =IF(R207="","",IF(R207>=60,INT(R207/60)&":"&TEXT(MOD(R207,60),"00.00"),TEXT(R207,"0.00"))) | T207: =IFERROR((G207-INDEX('01_Swimmers'!$E$5:$E$22,MATCH(B207,'01_Swimmers'!$A$5:$A$22,0)))/'00_Control'!$B$10,"") | U207: =IF(T207="","",INT(T207)) | V207: NO | W207: YES | X207: NO | Y207: 2 | Z207: 1 | AA207: 6 | AB207: https://www.swimcloud.com/results/128901/event/14/?id=25633677#time25633677 | AC207: SwimCloud API v6 2026-10-08 | AD207: Caeleb Dressel|2019-03-08|LCM|200|Free|109.68|TYR Pro Swim Series - Des Moines|FIN|False | AE207: =G207+L207/1000+ROW()/1000000000 | AF207: =IF(C207<>"Grayson Coulter","",COUNTIFS($C$5:$C$2991,"Grayson Coulter",$Q$5:$Q$2991,Q207,$AE$5:$AE$2991,"<="&AE207,$R$5:$R$2991,"<"&R207)) | AG207: =IF(OR(C207<>"Grayson Coulter",G207<'00_Control'!$B$7),"",--(AF207<5)) | AH207: =IF(OR(C207<>"Grayson Coulter",G207<'00_Control'!$B$7),"",--(AF207<10)) | AI207: =IF(AND(C207="Grayson Coulter",G207>='00_Control'!$B$7),"YES","NO") | AJ207: OK
A208: SM000204 | B208: SW010 | C208: Caeleb Dressel | D208: SwimCloud | E208: 2361642 | F208: 25634874 | G208: 43533 | H208: TYR Pro Swim Series - Des Moines | I208: 128901 | K208: PRE | L208: =IF(K208="FIN",3,IF(OR(K208="SEM",K208="SEMI"),2,IF(OR(K208="PRE",K208="HEAT"),1,IF(V208="YES",4,2)))) | M208: LCM | N208: 100 | O208: Fly | P208: 100 Fly | Q208: LCM_100_FLY | R208: 52.78 | S208: =IF(R208="","",IF(R208>=60,INT(R208/60)&":"&TEXT(MOD(R208,60),"00.00"),TEXT(R208,"0.00"))) | T208: =IFERROR((G208-INDEX('01_Swimmers'!$E$5:$E$22,MATCH(B208,'01_Swimmers'!$A$5:$A$22,0)))/'00_Control'!$B$10,"") | U208: =IF(T208="","",INT(T208)) | V208: NO | W208: YES | X208: NO | Y208: 5 | Z208: 4 | AA208: 3 | AB208: https://www.swimcloud.com/results/128901/event/31/?id=25634874#time25634874 | AC208: SwimCloud API v6 2026-10-08 | AD208: Caeleb Dressel|2019-03-09|LCM|100|Fly|52.78|TYR Pro Swim Series - Des Moines|PRE|False | AE208: =G208+L208/1000+ROW()/1000000000 | AF208: =IF(C208<>"Grayson Coulter","",COUNTIFS($C$5:$C$2991,"Grayson Coulter",$Q$5:$Q$2991,Q208,$AE$5:$AE$2991,"<="&AE208,$R$5:$R$2991,"<"&R208)) | AG208: =IF(OR(C208<>"Grayson Coulter",G208<'00_Control'!$B$7),"",--(AF208<5)) | AH208: =IF(OR(C208<>"Grayson Coulter",G208<'00_Control'!$B$7),"",--(AF208<10)) | AI208: =IF(AND(C208="Grayson Coulter",G208>='00_Control'!$B$7),"YES","NO") | AJ208: OK
A209: SM000205 | B209: SW010 | C209: Caeleb Dressel | D209: SwimCloud | E209: 2361642 | F209: 25634875 | G209: 43533 | H209: TYR Pro Swim Series - Des Moines | I209: 128901 | K209: FIN | L209: =IF(K209="FIN",3,IF(OR(K209="SEM",K209="SEMI"),2,IF(OR(K209="PRE",K209="HEAT"),1,IF(V209="YES",4,2)))) | M209: LCM | N209: 100 | O209: Fly | P209: 100 Fly | Q209: LCM_100_FLY | R209: 51.51 | S209: =IF(R209="","",IF(R209>=60,INT(R209/60)&":"&TEXT(MOD(R209,60),"00.00"),TEXT(R209,"0.00"))) | T209: =IFERROR((G209-INDEX('01_Swimmers'!$E$5:$E$22,MATCH(B209,'01_Swimmers'!$A$5:$A$22,0)))/'00_Control'!$B$10,"") | U209: =IF(T209="","",INT(T209)) | V209: NO | W209: YES | X209: NO | Y209: 2 | Z209: 3 | AA209: 1 | AB209: https://www.swimcloud.com/results/128901/event/31/?id=25634875#time25634875 | AC209: SwimCloud API v6 2026-10-08 | AD209: Caeleb Dressel|2019-03-09|LCM|100|Fly|51.51|TYR Pro Swim Series - Des Moines|FIN|False | AE209: =G209+L209/1000+ROW()/1000000000 | AF209: =IF(C209<>"Grayson Coulter","",COUNTIFS($C$5:$C$2991,"Grayson Coulter",$Q$5:$Q$2991,Q209,$AE$5:$AE$2991,"<="&AE209,$R$5:$R$2991,"<"&R209)) | AG209: =IF(OR(C209<>"Grayson Coulter",G209<'00_Control'!$B$7),"",--(AF209<5)) | AH209: =IF(OR(C209<>"Grayson Coulter",G209<'00_Control'!$B$7),"",--(AF209<10)) | AI209: =IF(AND(C209="Grayson Coulter",G209>='00_Control'!$B$7),"YES","NO") | AJ209: OK
A210: SM000206 | B210: SW010 | C210: Caeleb Dressel | D210: SwimCloud | E210: 2361642 | F210: 25972442 | G210: 43566 | H210: TYR Pro Swim Series - Richmond | I210: 144820 | K210: PRE | L210: =IF(K210="FIN",3,IF(OR(K210="SEM",K210="SEMI"),2,IF(OR(K210="PRE",K210="HEAT"),1,IF(V210="YES",4,2)))) | M210: LCM | N210: 100 | O210: Fly | P210: 100 Fly | Q210: LCM_100_FLY | R210: 52.55 | S210: =IF(R210="","",IF(R210>=60,INT(R210/60)&":"&TEXT(MOD(R210,60),"00.00"),TEXT(R210,"0.00"))) | T210: =IFERROR((G210-INDEX('01_Swimmers'!$E$5:$E$22,MATCH(B210,'01_Swimmers'!$A$5:$A$22,0)))/'00_Control'!$B$10,"") | U210: =IF(T210="","",INT(T210)) | V210: NO | W210: YES | X210: NO | Y210: 8 | Z210: 4 | AA210: 1 | AB210: https://www.swimcloud.com/results/144820/event/10/?id=25972442#time25972442 | AC210: SwimCloud API v6 2026-10-08 | AD210: Caeleb Dressel|2019-04-11|LCM|100|Fly|52.55|TYR Pro Swim Series - Richmond|PRE|False | AE210: =G210+L210/1000+ROW()/1000000000 | AF210: =IF(C210<>"Grayson Coulter","",COUNTIFS($C$5:$C$2991,"Grayson Coulter",$Q$5:$Q$2991,Q210,$AE$5:$AE$2991,"<="&AE210,$R$5:$R$2991,"<"&R210)) | AG210: =IF(OR(C210<>"Grayson Coulter",G210<'00_Control'!$B$7),"",--(AF210<5)) | AH210: =IF(OR(C210<>"Grayson Coulter",G210<'00_Control'!$B$7),"",--(AF210<10)) | AI210: =IF(AND(C210="Grayson Coulter",G210>='00_Control'!$B$7),"YES","NO") | AJ210: OK
A211: SM000207 | B211: SW010 | C211: Caeleb Dressel | D211: SwimCloud | E211: 2361642 | F211: 25972443 | G211: 43566 | H211: TYR Pro Swim Series - Richmond | I211: 144820 | K211: FIN | L211: =IF(K211="FIN",3,IF(OR(K211="SEM",K211="SEMI"),2,IF(OR(K211="PRE",K211="HEAT"),1,IF(V211="YES",4,2)))) | M211: LCM | N211: 100 | O211: Fly | P211: 100 Fly | Q211: LCM_100_FLY | R211: 52.08 | S211: =IF(R211="","",IF(R211>=60,INT(R211/60)&":"&TEXT(MOD(R211,60),"00.00"),TEXT(R211,"0.00"))) | T211: =IFERROR((G211-INDEX('01_Swimmers'!$E$5:$E$22,MATCH(B211,'01_Swimmers'!$A$5:$A$22,0)))/'00_Control'!$B$10,"") | U211: =IF(T211="","",INT(T211)) | V211: NO | W211: YES | X211: NO | Y211: 2 | Z211: 4 | AA211: 1 | AB211: https://www.swimcloud.com/results/144820/event/10/?id=25972443#time25972443 | AC211: SwimCloud API v6 2026-10-08 | AD211: Caeleb Dressel|2019-04-11|LCM|100|Fly|52.08|TYR Pro Swim Series - Richmond|FIN|False | AE211: =G211+L211/1000+ROW()/1000000000 | AF211: =IF(C211<>"Grayson Coulter","",COUNTIFS($C$5:$C$2991,"Grayson Coulter",$Q$5:$Q$2991,Q211,$AE$5:$AE$2991,"<="&AE211,$R$5:$R$2991,"<"&R211)) | AG211: =IF(OR(C211<>"Grayson Coulter",G211<'00_Control'!$B$7),"",--(AF211<5)) | AH211: =IF(OR(C211<>"Grayson Coulter",G211<'00_Control'!$B$7),"",--(AF211<10)) | AI211: =IF(AND(C211="Grayson Coulter",G211>='00_Control'!$B$7),"YES","NO") | AJ211: OK
A212: SM000208 | B212: SW010 | C212: Caeleb Dressel | D212: SwimCloud | E212: 2361642 | F212: 25972346 | G212: 43566 | H212: TYR Pro Swim Series - Richmond | I212: 144820 | K212: PRE | L212: =IF(K212="FIN",3,IF(OR(K212="SEM",K212="SEMI"),2,IF(OR(K212="PRE",K212="HEAT"),1,IF(V212="YES",4,2)))) | M212: LCM | N212: 200 | O212: Free | P212: 200 Free | Q212: LCM_200_FREE | R212: 109.67 | S212: =IF(R212="","",IF(R212>=60,INT(R212/60)&":"&TEXT(MOD(R212,60),"00.00"),TEXT(R212,"0.00"))) | T212: =IFERROR((G212-INDEX('01_Swimmers'!$E$5:$E$22,MATCH(B212,'01_Swimmers'!$A$5:$A$22,0)))/'00_Control'!$B$10,"") | U212: =IF(T212="","",INT(T212)) | V212: NO | W212: YES | X212: NO | Y212: 9 | Z212: 5 | AA212: 2 | AB212: https://www.swimcloud.com/results/144820/event/4/?id=25972346#time25972346 | AC212: SwimCloud API v6 2026-10-08 | AD212: Caeleb Dressel|2019-04-11|LCM|200|Free|109.67|TYR Pro Swim Series - Richmond|PRE|False | AE212: =G212+L212/1000+ROW()/1000000000 | AF212: =IF(C212<>"Grayson Coulter","",COUNTIFS($C$5:$C$2991,"Grayson Coulter",$Q$5:$Q$2991,Q212,$AE$5:$AE$2991,"<="&AE212,$R$5:$R$2991,"<"&R212)) | AG212: =IF(OR(C212<>"Grayson Coulter",G212<'00_Control'!$B$7),"",--(AF212<5)) | AH212: =IF(OR(C212<>"Grayson Coulter",G212<'00_Control'!$B$7),"",--(AF212<10)) | AI212: =IF(AND(C212="Grayson Coulter",G212>='00_Control'!$B$7),"YES","NO") | AJ212: OK
A213: SM000209 | B213: SW010 | C213: Caeleb Dressel | D213: SwimCloud | E213: 2361642 | F213: 25972347 | G213: 43566 | H213: TYR Pro Swim Series - Richmond | I213: 144820 | K213: FIN | L213: =IF(K213="FIN",3,IF(OR(K213="SEM",K213="SEMI"),2,IF(OR(K213="PRE",K213="HEAT"),1,IF(V213="YES",4,2)))) | M213: LCM | N213: 200 | O213: Free | P213: 200 Free | Q213: LCM_200_FREE | R213: 107.31 | S213: =IF(R213="","",IF(R213>=60,INT(R213/60)&":"&TEXT(MOD(R213,60),"00.00"),TEXT(R213,"0.00"))) | T213: =IFERROR((G213-INDEX('01_Swimmers'!$E$5:$E$22,MATCH(B213,'01_Swimmers'!$A$5:$A$22,0)))/'00_Control'!$B$10,"") | U213: =IF(T213="","",INT(T213)) | V213: NO | W213: YES | X213: NO | Y213: 2 | Z213: 5 | AA213: 1 | AB213: https://www.swimcloud.com/results/144820/event/4/?id=25972347#time25972347 | AC213: SwimCloud API v6 2026-10-08 | AD213: Caeleb Dressel|2019-04-11|LCM|200|Free|107.31|TYR Pro Swim Series - Richmond|FIN|False | AE213: =G213+L213/1000+ROW()/1000000000 | AF213: =IF(C213<>"Grayson Coulter","",COUNTIFS($C$5:$C$2991,"Grayson Coulter",$Q$5:$Q$2991,Q213,$AE$5:$AE$2991,"<="&AE213,$R$5:$R$2991,"<"&R213)) | AG213: =IF(OR(C213<>"Grayson Coulter",G213<'00_Control'!$B$7),"",--(AF213<5)) | AH213: =IF(OR(C213<>"Grayson Coulter",G213<'00_Control'!$B$7),"",--(AF213<10)) | AI213: =IF(AND(C213="Grayson Coulter",G213>='00_Control'!$B$7),"YES","NO") | AJ213: OK
... A223: SM000219 | B223: SW010 | C223: Caeleb Dressel | D223: SwimCloud | E223: 2361642 | F223: 27009261 | G223: 43639 | H223: CA MVN Fran Crippen Memorial Swim Meet of Champions | I223: 129860 | K223: FIN | L223: =IF(K223="FIN",3,IF(OR(K223="SEM",K223="SEMI"),2,IF(OR(K223="PRE",K223="HEAT"),1,IF(V223="YES",4,2)))) | M223: LCM | N223: 100 | O223: Fly | P223: 100 Fly | Q223: LCM_100_FLY | R223: 50.36 | S223: =IF(R223="","",IF(R223>=60,INT(R223/60)&":"&TEXT(MOD(R223,60),"00.00"),TEXT(R223,"0.00"))) | T223: =IFERROR((G223-INDEX('01_Swimmers'!$E$5:$E$22,MATCH(B223,'01_Swimmers'!$A$5:$A$22,0)))/'00_Control'!$B$10,"") | U223: =IF(T223="","",INT(T223)) | V223: NO | W223: YES | X223: NO | Y223: 3 | Z223: 4 | AA223: 1 | AB223: https://www.swimcloud.com/results/129860/event/34/?id=27009261#time27009261 | AC223: SwimCloud API v6 2026-10-08 | AD223: Caeleb Dressel|2019-06-23|LCM|100|Fly|50.36|CA MVN Fran Crippen Memorial Swim Meet of Champions|FIN|False | AE223: =G223+L223/1000+ROW()/1000000000 | AF223: =IF(C223<>"Grayson Coulter","",COUNTIFS($C$5:$C$2991,"Grayson Coulter",$Q$5:$Q$2991,Q223,$AE$5:$AE$2991,"<="&AE223,$R$5:$R$2991,"<"&R223)) | AG223: =IF(OR(C223<>"Grayson Coulter",G223<'00_Control'!$B$7),"",--(AF223<5)) | AH223: =IF(OR(C223<>"Grayson Coulter",G223<'00_Control'!$B$7),"",--(AF223<10)) | AI223: =IF(AND(C223="Grayson Coulter",G223>='00_Control'!$B$7),"YES","NO") | AJ223: OK
A224: SM000220 | B224: SW010 | C224: Caeleb Dressel | D224: SwimCloud | E224: 2361642 | F224: 28191667 | G224: 43667 | H224: 18th FINA World Championships | I224: 149555 | K224: FIN | L224: =IF(K224="FIN",3,IF(OR(K224="SEM",K224="SEMI"),2,IF(OR(K224="PRE",K224="HEAT"),1,IF(V224="YES",4,2)))) | M224: LCM | N224: 100 | O224: Free | P224: 100 Free | Q224: LCM_100_FREE | R224: 47.63 | S224: =IF(R224="","",IF(R224>=60,INT(R224/60)&":"&TEXT(MOD(R224,60),"00.00"),TEXT(R224,"0.00"))) | T224: =IFERROR((G224-INDEX('01_Swimmers'!$E$5:$E$22,MATCH(B224,'01_Swimmers'!$A$5:$A$22,0)))/'00_Control'!$B$10,"") | U224: =IF(T224="","",INT(T224)) | V224: YES | W224: YES | X224: NO | Y224: 1 | Z224: 4 | AB224: https://www.swimcloud.com/results/149555/event/8/?id=28190587#time28190587 | AC224: SwimCloud API v6 2026-10-08 | AD224: Caeleb Dressel|2019-07-21|LCM|100|Free|47.63|18th FINA World Championships|FIN|True | AE224: =G224+L224/1000+ROW()/1000000000 | AF224: =IF(C224<>"Grayson Coulter","",COUNTIFS($C$5:$C$2991,"Grayson Coulter",$Q$5:$Q$2991,Q224,$AE$5:$AE$2991,"<="&AE224,$R$5:$R$2991,"<"&R224)) | AG224: =IF(OR(C224<>"Grayson Coulter",G224<'00_Control'!$B$7),"",--(AF224<5)) | AH224: =IF(OR(C224<>"Grayson Coulter",G224<'00_Control'!$B$7),"",--(AF224<10)) | AI224: =IF(AND(C224="Grayson Coulter",G224>='00_Control'!$B$7),"YES","NO") | AJ224: OK
A225: SM000221 | B225: SW010 | C225: Caeleb Dressel | D225: SwimCloud | E225: 2361642 | F225: 28190472 | G225: 43670 | H225: 18th FINA World Championships | I225: 149555 | K225: PRE | L225: =IF(K225="FIN",3,IF(OR(K225="SEM",K225="SEMI"),2,IF(OR(K225="PRE",K225="HEAT"),1,IF(V225="YES",4,2)))) | M225: LCM | N225: 100 | O225: Free | P225: 100 Free | Q225: LCM_100_FREE | R225: 47.32 | S225: =IF(R225="","",IF(R225>=60,INT(R225/60)&":"&TEXT(MOD(R225,60),"00.00"),TEXT(R225,"0.00"))) | T225: =IFERROR((G225-INDEX('01_Swimmers'!$E$5:$E$22,MATCH(B225,'01_Swimmers'!$A$5:$A$22,0)))/'00_Control'!$B$10,"") | U225: =IF(T225="","",INT(T225)) | V225: NO | W225: YES | X225: NO | Y225: 11 | Z225: 5 | AA225: 1 | AB225: https://www.swimcloud.com/results/149555/event/19/?id=28190472#time28190472 | AC225: SwimCloud API v6 2026-10-08 | AD225: Caeleb Dressel|2019-07-24|LCM|100|Free|47.32|18th FINA World Championships|PRE|False | AE225: =G225+L225/1000+ROW()/1000000000 | AF225: =IF(C225<>"Grayson Coulter","",COUNTIFS($C$5:$C$2991,"Grayson Coulter",$Q$5:$Q$2991,Q225,$AE$5:$AE$2991,"<="&AE225,$R$5:$R$2991,"<"&R225)) | AG225: =IF(OR(C225<>"Grayson Coulter",G225<'00_Control'!$B$7),"",--(AF225<5)) | AH225: =IF(OR(C225<>"Grayson Coulter",G225<'00_Control'!$B$7),"",--(AF225<10)) | AI225: =IF(AND(C225="Grayson Coulter",G225>='00_Control'!$B$7),"YES","NO") | AJ225: OK
A226: SM000222 | B226: SW010 | C226: Caeleb Dressel | D226: SwimCloud | E226: 2361642 | F226: 28190473 | G226: 43670 | H226: 18th FINA World Championships | I226: 149555 | K226: SEM | L226: =IF(K226="FIN",3,IF(OR(K226="SEM",K226="SEMI"),2,IF(OR(K226="PRE",K226="HEAT"),1,IF(V226="YES",4,2)))) | M226: LCM | N226: 100 | O226: Free | P226: 100 Free | Q226: LCM_100_FREE | R226: 47.35 | S226: =IF(R226="","",IF(R226>=60,INT(R226/60)&":"&TEXT(MOD(R226,60),"00.00"),TEXT(R226,"0.00"))) | T226: =IFERROR((G226-INDEX('01_Swimmers'!$E$5:$E$22,MATCH(B226,'01_Swimmers'!$A$5:$A$22,0)))/'00_Control'!$B$10,"") | U226: =IF(T226="","",INT(T226)) | V226: NO | W226: YES | X226: NO | Y226: 2 | Z226: 4 | AA226: 1 | AB226: https://www.swimcloud.com/results/149555/event/19/?id=28190473#time28190473 | AC226: SwimCloud API v6 2026-10-08 | AD226: Caeleb Dressel|2019-07-24|LCM|100|Free|47.35|18th FINA World Championships|SEM|False | AE226: =G226+L226/1000+ROW()/1000000000 | AF226: =IF(C226<>"Grayson Coulter","",COUNTIFS($C$5:$C$2991,"Grayson Coulter",$Q$5:$Q$2991,Q226,$AE$5:$AE$2991,"<="&AE226,$R$5:$R$2991,"<"&R226)) | AG226: =IF(OR(C226<>"Grayson Coulter",G226<'00_Control'!$B$7),"",--(AF226<5)) | AH226: =IF(OR(C226<>"Grayson Coulter",G226<'00_Control'!$B$7),"",--(AF226<10)) | AI226: =IF(AND(C226="Grayson Coulter",G226>='00_Control'!$B$7),"YES","NO") | AJ226: OK
...

Sheet 05_Record_Benchmarks
A1: NZ age-group record benchmarks
A2: Current NZ individual age-group records, ages 13-18. Times are stored as display text plus formula-derived numeric seconds.
A4: Record Key | B4: Course | C4: Sex | D4: Age | E4: Event | F4: Record Holder(s) | G4: Holder 1 | H4: Holder 2 | I4: Record Time | J4: Record Seconds | K4: Record Date(s) | L4: Record Basis | M4: Record Source URL | N4: Joint Record? | O4: Top 20 Eligible? | P4: Next Fastest Swimmer | Q4: Next Fastest Time | R4: Next Fastest Seconds | S4: Margin % | T4: Comparator Verified? | U4: Outstanding Rank | V4: Outstanding Key | W4: Review Notes | X4: Source Notes
A5: NZ|SCM|M|13|50 Free | B5: SCM | C5: Male | D5: 13 | E5: 50 Free | F5: Grayson Coulter | G5: Grayson Coulter | I5: 23.61 | J5: =IF(I5="","",IF(ISNUMBER(SEARCH(":",I5)),VALUE(LEFT(I5,SEARCH(":",I5)-1))*60+VALUE(MID(I5,SEARCH(":",I5)+1,99)),VALUE(I5))) | K5: 25.09.25 | L5: Swimming New Zealand Short Course Records by Age - user-supplied PDF | N5: NO | O5: YES | Q5: 24.21 | R5: =IF(Q5="","",IF(ISNUMBER(SEARCH(":",Q5)),VALUE(LEFT(Q5,SEARCH(":",Q5)-1))*60+VALUE(MID(Q5,SEARCH(":",Q5)+1,99)),VALUE(Q5))) | S5: =IF(OR(J5="",R5=""),"",(R5-J5)/R5) | T5: =IF(OR(P5<>"",N5="YES"),"YES","NO") | U5: =IF(AND(O5="YES",T5="YES",S5<>""),COUNTIFS($C$5:$C$424,C5,$S$5:$S$424,">"&S5)+COUNTIFS($C$5:C5,C5,$S$5:S5,S5),"") | V5: =IF(U5="","",C5&"|"&U5) | X5: Next-fastest time supplied in user workbook; swimmer name not yet supplied.
A6: NZ|SCM|M|13|100 Free | B6: SCM | C6: Male | D6: 13 | E6: 100 Free | F6: Grayson Coulter | G6: Grayson Coulter | I6: 50.58 | J6: =IF(I6="","",IF(ISNUMBER(SEARCH(":",I6)),VALUE(LEFT(I6,SEARCH(":",I6)-1))*60+VALUE(MID(I6,SEARCH(":",I6)+1,99)),VALUE(I6))) | K6: 22.09.25 | L6: Swimming New Zealand Short Course Records by Age - user-supplied PDF | N6: NO | O6: YES | P6: Hayden Church | Q6: 53.40 | R6: =IF(Q6="","",IF(ISNUMBER(SEARCH(":",Q6)),VALUE(LEFT(Q6,SEARCH(":",Q6)-1))*60+VALUE(MID(Q6,SEARCH(":",Q6)+1,99)),VALUE(Q6))) | S6: =IF(OR(J6="",R6=""),"",(R6-J6)/R6) | T6: =IF(OR(P6<>"",N6="YES"),"YES","NO") | U6: =IF(AND(O6="YES",T6="YES",S6<>""),COUNTIFS($C$5:$C$424,C6,$S$5:$S$424,">"&S6)+COUNTIFS($C$5:C6,C6,$S$5:S6,S6),"") | V6: =IF(U6="","",C6&"|"&U6) | X6: Next-fastest time supplied in user workbook; swimmer name not yet supplied.
A7: NZ|SCM|M|13|200 Free | B7: SCM | C7: Male | D7: 13 | E7: 200 Free | F7: Grayson Coulter | G7: Grayson Coulter | I7: 1:49.18 | J7: =IF(I7="","",IF(ISNUMBER(SEARCH(":",I7)),VALUE(LEFT(I7,SEARCH(":",I7)-1))*60+VALUE(MID(I7,SEARCH(":",I7)+1,99)),VALUE(I7))) | K7: 24.09.25 | L7: Swimming New Zealand Short Course Records by Age - user-supplied PDF | N7: NO | O7: YES | P7: Hayden Church | Q7: 1:57.71 | R7: =IF(Q7="","",IF(ISNUMBER(SEARCH(":",Q7)),VALUE(LEFT(Q7,SEARCH(":",Q7)-1))*60+VALUE(MID(Q7,SEARCH(":",Q7)+1,99)),VALUE(Q7))) | S7: =IF(OR(J7="",R7=""),"",(R7-J7)/R7) | T7: =IF(OR(P7<>"",N7="YES"),"YES","NO") | U7: =IF(AND(O7="YES",T7="YES",S7<>""),COUNTIFS($C$5:$C$424,C7,$S$5:$S$424,">"&S7)+COUNTIFS($C$5:C7,C7,$S$5:S7,S7),"") | V7: =IF(U7="","",C7&"|"&U7) | X7: Next-fastest time supplied in user workbook; swimmer name not yet supplied.
A8: NZ|SCM|M|13|400 Free | B8: SCM | C8: Male | D8: 13 | E8: 400 Free | F8: Grayson Coulter | G8: Grayson Coulter | I8: 3:56.78 | J8: =IF(I8="","",IF(ISNUMBER(SEARCH(":",I8)),VALUE(LEFT(I8,SEARCH(":",I8)-1))*60+VALUE(MID(I8,SEARCH(":",I8)+1,99)),VALUE(I8))) | K8: 24.07.25 | L8: Swimming New Zealand Short Course Records by Age - user-supplied PDF | N8: NO | O8: YES | P8: Michael Mincham | Q8: 4:09.27 | R8: =IF(Q8="","",IF(ISNUMBER(SEARCH(":",Q8)),VALUE(LEFT(Q8,SEARCH(":",Q8)-1))*60+VALUE(MID(Q8,SEARCH(":",Q8)+1,99)),VALUE(Q8))) | S8: =IF(OR(J8="",R8=""),"",(R8-J8)/R8) | T8: =IF(OR(P8<>"",N8="YES"),"YES","NO") | U8: =IF(AND(O8="YES",T8="YES",S8<>""),COUNTIFS($C$5:$C$424,C8,$S$5:$S$424,">"&S8)+COUNTIFS($C$5:C8,C8,$S$5:S8,S8),"") | V8: =IF(U8="","",C8&"|"&U8) | X8: Next-fastest time supplied in user workbook; swimmer name not yet supplied.
A9: NZ|SCM|M|13|800 Free | B9: SCM | C9: Male | D9: 13 | E9: 800 Free | F9: Michael Mincham | G9: Michael Mincham | I9: 8:30.77 | J9: =IF(I9="","",IF(ISNUMBER(SEARCH(":",I9)),VALUE(LEFT(I9,SEARCH(":",I9)-1))*60+VALUE(MID(I9,SEARCH(":",I9)+1,99)),VALUE(I9))) | K9: 29.05.10 | L9: Swimming New Zealand Short Course Records by Age - user-supplied PDF | N9: NO | O9: YES | Q9: 8:41.93 | R9: =IF(Q9="","",IF(ISNUMBER(SEARCH(":",Q9)),VALUE(LEFT(Q9,SEARCH(":",Q9)-1))*60+VALUE(MID(Q9,SEARCH(":",Q9)+1,99)),VALUE(Q9))) | S9: =IF(OR(J9="",R9=""),"",(R9-J9)/R9) | T9: =IF(OR(P9<>"",N9="YES"),"YES","NO") | U9: =IF(AND(O9="YES",T9="YES",S9<>""),COUNTIFS($C$5:$C$424,C9,$S$5:$S$424,">"&S9)+COUNTIFS($C$5:C9,C9,$S$5:S9,S9),"") | V9: =IF(U9="","",C9&"|"&U9) | X9: Next-fastest time supplied in user workbook; swimmer name not yet supplied.
A10: NZ|SCM|M|13|1500 Free | B10: SCM | C10: Male | D10: 13 | E10: 1500 Free | F10: Thomas Heaton | G10: Thomas Heaton | I10: 16:27.41 | J10: =IF(I10="","",IF(ISNUMBER(SEARCH(":",I10)),VALUE(LEFT(I10,SEARCH(":",I10)-1))*60+VALUE(MID(I10,SEARCH(":",I10)+1,99)),VALUE(I10))) | K10: 04.10.12 | L10: Swimming New Zealand Short Course Records by Age - user-supplied PDF | N10: NO | O10: YES | Q10: 16:33.56 | R10: =IF(Q10="","",IF(ISNUMBER(SEARCH(":",Q10)),VALUE(LEFT(Q10,SEARCH(":",Q10)-1))*60+VALUE(MID(Q10,SEARCH(":",Q10)+1,99)),VALUE(Q10))) | S10: =IF(OR(J10="",R10=""),"",(R10-J10)/R10) | T10: =IF(OR(P10<>"",N10="YES"),"YES","NO") | U10: =IF(AND(O10="YES",T10="YES",S10<>""),COUNTIFS($C$5:$C$424,C10,$S$5:$S$424,">"&S10)+COUNTIFS($C$5:C10,C10,$S$5:S10,S10),"") | V10: =IF(U10="","",C10&"|"&U10) | X10: Next-fastest time supplied in user workbook; swimmer name not yet supplied.
A11: NZ|SCM|M|13|50 Back | B11: SCM | C11: Male | D11: 13 | E11: 50 Back | F11: Kase Glintmeyer | G11: Kase Glintmeyer | I11: 27.35 | J11: =IF(I11="","",IF(ISNUMBER(SEARCH(":",I11)),VALUE(LEFT(I11,SEARCH(":",I11)-1))*60+VALUE(MID(I11,SEARCH(":",I11)+1,99)),VALUE(I11))) | K11: 23.08.24 | L11: Swimming New Zealand Short Course Records by Age - user-supplied PDF | N11: NO | O11: YES | Q11: 27.85 | R11: =IF(Q11="","",IF(ISNUMBER(SEARCH(":",Q11)),VALUE(LEFT(Q11,SEARCH(":",Q11)-1))*60+VALUE(MID(Q11,SEARCH(":",Q11)+1,99)),VALUE(Q11))) | S11: =IF(OR(J11="",R11=""),"",(R11-J11)/R11) | T11: =IF(OR(P11<>"",N11="YES"),"YES","NO") | U11: =IF(AND(O11="YES",T11="YES",S11<>""),COUNTIFS($C$5:$C$424,C11,$S$5:$S$424,">"&S11)+COUNTIFS($C$5:C11,C11,$S$5:S11,S11),"") | V11: =IF(U11="","",C11&"|"&U11) | X11: Next-fastest time supplied in user workbook; swimmer name not yet supplied.
A12: NZ|SCM|M|13|100 Back | B12: SCM | C12: Male | D12: 13 | E12: 100 Back | F12: Grayson Coulter | G12: Grayson Coulter | I12: 58.20 | J12: =IF(I12="","",IF(ISNUMBER(SEARCH(":",I12)),VALUE(LEFT(I12,SEARCH(":",I12)-1))*60+VALUE(MID(I12,SEARCH(":",I12)+1,99)),VALUE(I12))) | K12: 25.07.25 | L12: Swimming New Zealand Short Course Records by Age - user-supplied PDF | N12: NO | O12: YES | Q12: 59.33 | R12: =IF(Q12="","",IF(ISNUMBER(SEARCH(":",Q12)),VALUE(LEFT(Q12,SEARCH(":",Q12)-1))*60+VALUE(MID(Q12,SEARCH(":",Q12)+1,99)),VALUE(Q12))) | S12: =IF(OR(J12="",R12=""),"",(R12-J12)/R12) | T12: =IF(OR(P12<>"",N12="YES"),"YES","NO") | U12: =IF(AND(O12="YES",T12="YES",S12<>""),COUNTIFS($C$5:$C$424,C12,$S$5:$S$424,">"&S12)+COUNTIFS($C$5:C12,C12,$S$5:S12,S12),"") | V12: =IF(U12="","",C12&"|"&U12) | X12: Next-fastest time supplied in user workbook; swimmer name not yet supplied.
A13: NZ|SCM|M|13|200 Back | B13: SCM | C13: Male | D13: 13 | E13: 200 Back | F13: Ariel Muchirahondo | G13: Ariel Muchirahondo | I13: 2:06.33 | J13: =IF(I13="","",IF(ISNUMBER(SEARCH(":",I13)),VALUE(LEFT(I13,SEARCH(":",I13)-1))*60+VALUE(MID(I13,SEARCH(":",I13)+1,99)),VALUE(I13))) | K13: 22.10.22 | L13: Swimming New Zealand Short Course Records by Age - user-supplied PDF | N13: NO | O13: YES | Q13: 2:08.16 | R13: =IF(Q13="","",IF(ISNUMBER(SEARCH(":",Q13)),VALUE(LEFT(Q13,SEARCH(":",Q13)-1))*60+VALUE(MID(Q13,SEARCH(":",Q13)+1,99)),VALUE(Q13))) | S13: =IF(OR(J13="",R13=""),"",(R13-J13)/R13) | T13: =IF(OR(P13<>"",N13="YES"),"YES","NO") | U13: =IF(AND(O13="YES",T13="YES",S13<>""),COUNTIFS($C$5:$C$424,C13,$S$5:$S$424,">"&S13)+COUNTIFS($C$5:C13,C13,$S$5:S13,S13),"") | V13: =IF(U13="","",C13&"|"&U13) | X13: Next-fastest time supplied in user workbook; swimmer name not yet supplied.
A14: NZ|SCM|M|13|50 Breast | B14: SCM | C14: Male | D14: 13 | E14: 50 Breast | F14: Cameron Karpik | G14: Cameron Karpik | I14: 30.35 | J14: =IF(I14="","",IF(ISNUMBER(SEARCH(":",I14)),VALUE(LEFT(I14,SEARCH(":",I14)-1))*60+VALUE(MID(I14,SEARCH(":",I14)+1,99)),VALUE(I14))) | K14: 25.08.22 | L14: Swimming New Zealand Short Course Records by Age - user-supplied PDF | N14: NO | O14: YES | Q14: 30.68 | R14: =IF(Q14="","",IF(ISNUMBER(SEARCH(":",Q14)),VALUE(LEFT(Q14,SEARCH(":",Q14)-1))*60+VALUE(MID(Q14,SEARCH(":",Q14)+1,99)),VALUE(Q14))) | S14: =IF(OR(J14="",R14=""),"",(R14-J14)/R14) | T14: =IF(OR(P14<>"",N14="YES"),"YES","NO") | U14: =IF(AND(O14="YES",T14="YES",S14<>""),COUNTIFS($C$5:$C$424,C14,$S$5:$S$424,">"&S14)+COUNTIFS($C$5:C14,C14,$S$5:S14,S14),"") | V14: =IF(U14="","",C14&"|"&U14) | X14: Next-fastest time supplied in user workbook; swimmer name not yet supplied.
A15: NZ|SCM|M|13|100 Breast | B15: SCM | C15: Male | D15: 13 | E15: 100 Breast | F15: Cameron Karpik | G15: Cameron Karpik | I15: 1:06.33 | J15: =IF(I15="","",IF(ISNUMBER(SEARCH(":",I15)),VALUE(LEFT(I15,SEARCH(":",I15)-1))*60+VALUE(MID(I15,SEARCH(":",I15)+1,99)),VALUE(I15))) | K15: 26.08.22 | L15: Swimming New Zealand Short Course Records by Age - user-supplied PDF | N15: NO | O15: YES | Q15: 1:06.77 | R15: =IF(Q15="","",IF(ISNUMBER(SEARCH(":",Q15)),VALUE(LEFT(Q15,SEARCH(":",Q15)-1))*60+VALUE(MID(Q15,SEARCH(":",Q15)+1,99)),VALUE(Q15))) | S15: =IF(OR(J15="",R15=""),"",(R15-J15)/R15) | T15: =IF(OR(P15<>"",N15="YES"),"YES","NO") | U15: =IF(AND(O15="YES",T15="YES",S15<>""),COUNTIFS($C$5:$C$424,C15,$S$5:$S$424,">"&S15)+COUNTIFS($C$5:C15,C15,$S$5:S15,S15),"") | V15: =IF(U15="","",C15&"|"&U15) | X15: Next-fastest time supplied in user workbook; swimmer name not yet supplied.
A16: NZ|SCM|M|13|200 Breast | B16: SCM | C16: Male | D16: 13 | E16: 200 Breast | F16: Erik Kahr | G16: Erik Kahr | I16: 2:22.10 | J16: =IF(I16="","",IF(ISNUMBER(SEARCH(":",I16)),VALUE(LEFT(I16,SEARCH(":",I16)-1))*60+VALUE(MID(I16,SEARCH(":",I16)+1,99)),VALUE(I16))) | K16: 29.09.09 | L16: Swimming New Zealand Short Course Records by Age - user-supplied PDF | N16: NO | O16: YES | Q16: 2:24.15 | R16: =IF(Q16="","",IF(ISNUMBER(SEARCH(":",Q16)),VALUE(LEFT(Q16,SEARCH(":",Q16)-1))*60+VALUE(MID(Q16,SEARCH(":",Q16)+1,99)),VALUE(Q16))) | S16: =IF(OR(J16="",R16=""),"",(R16-J16)/R16) | T16: =IF(OR(P16<>"",N16="YES"),"YES","NO") | U16: =IF(AND(O16="YES",T16="YES",S16<>""),COUNTIFS($C$5:$C$424,C16,$S$5:$S$424,">"&S16)+COUNTIFS($C$5:C16,C16,$S$5:S16,S16),"") | V16: =IF(U16="","",C16&"|"&U16) | X16: Next-fastest time supplied in user workbook; swimmer name not yet supplied.
A17: NZ|SCM|M|13|50 Fly | B17: SCM | C17: Male | D17: 13 | E17: 50 Fly | F17: Grayson Coulter | G17: Grayson Coulter | I17: 25.64 | J17: =IF(I17="","",IF(ISNUMBER(SEARCH(":",I17)),VALUE(LEFT(I17,SEARCH(":",I17)-1))*60+VALUE(MID(I17,SEARCH(":",I17)+1,99)),VALUE(I17))) | K17: 22.09.25 | L17: Swimming New Zealand Short Course Records by Age - user-supplied PDF | N17: NO | O17: YES | P17: Taiko Torepe-Ormsby | Q17: 26.42 | R17: =IF(Q17="","",IF(ISNUMBER(SEARCH(":",Q17)),VALUE(LEFT(Q17,SEARCH(":",Q17)-1))*60+VALUE(MID(Q17,SEARCH(":",Q17)+1,99)),VALUE(Q17))) | S17: =IF(OR(J17="",R17=""),"",(R17-J17)/R17) | T17: =IF(OR(P17<>"",N17="YES"),"YES","NO") | U17: =IF(AND(O17="YES",T17="YES",S17<>""),COUNTIFS($C$5:$C$424,C17,$S$5:$S$424,">"&S17)+COUNTIFS($C$5:C17,C17,$S$5:S17,S17),"") | V17: =IF(U17="","",C17&"|"&U17) | X17: Next-fastest time supplied in user workbook; swimmer name not yet supplied.
A18: NZ|SCM|M|13|100 Fly | B18: SCM | C18: Male | D18: 13 | E18: 100 Fly | F18: Grayson Coulter | G18: Grayson Coulter | I18: 56.90 | J18: =IF(I18="","",IF(ISNUMBER(SEARCH(":",I18)),VALUE(LEFT(I18,SEARCH(":",I18)-1))*60+VALUE(MID(I18,SEARCH(":",I18)+1,99)),VALUE(I18))) | K18: 26.07.25 | L18: Swimming New Zealand Short Course Records by Age - user-supplied PDF | N18: NO | O18: YES | P18: Mason Wang | Q18: 58.99 | R18: =IF(Q18="","",IF(ISNUMBER(SEARCH(":",Q18)),VALUE(LEFT(Q18,SEARCH(":",Q18)-1))*60+VALUE(MID(Q18,SEARCH(":",Q18)+1,99)),VALUE(Q18))) | S18: =IF(OR(J18="",R18=""),"",(R18-J18)/R18) | T18: =IF(OR(P18<>"",N18="YES"),"YES","NO") | U18: =IF(AND(O18="YES",T18="YES",S18<>""),COUNTIFS($C$5:$C$424,C18,$S$5:$S$424,">"&S18)+COUNTIFS($C$5:C18,C18,$S$5:S18,S18),"") | V18: =IF(U18="","",C18&"|"&U18) | X18: Next-fastest time supplied in user workbook; swimmer name not yet supplied.
A19: NZ|SCM|M|13|200 Fly | B19: SCM | C19: Male | D19: 13 | E19: 200 Fly | F19: Mitchell Donaldson | G19: Mitchell Donaldson | I19: 2:10.81 | J19: =IF(I19="","",IF(ISNUMBER(SEARCH(":",I19)),VALUE(LEFT(I19,SEARCH(":",I19)-1))*60+VALUE(MID(I19,SEARCH(":",I19)+1,99)),VALUE(I19))) | K19: 27.09.06 | L19: Swimming New Zealand Short Course Records by Age - user-supplied PDF | N19: NO | O19: YES | Q19: 2:11.88 | R19: =IF(Q19="","",IF(ISNUMBER(SEARCH(":",Q19)),VALUE(LEFT(Q19,SEARCH(":",Q19)-1))*60+VALUE(MID(Q19,SEARCH(":",Q19)+1,99)),VALUE(Q19))) | S19: =IF(OR(J19="",R19=""),"",(R19-J19)/R19) | T19: =IF(OR(P19<>"",N19="YES"),"YES","NO") | U19: =IF(AND(O19="YES",T19="YES",S19<>""),COUNTIFS($C$5:$C$424,C19,$S$5:$S$424,">"&S19)+COUNTIFS($C$5:C19,C19,$S$5:S19,S19),"") | V19: =IF(U19="","",C19&"|"&U19) | X19: Next-fastest time supplied in user workbook; swimmer name not yet supplied.
A20: NZ|SCM|M|13|100 IM | B20: SCM | C20: Male | D20: 13 | E20: 100 IM | F20: Grayson Coulter | G20: Grayson Coulter | I20: 58.42 | J20: =IF(I20="","",IF(ISNUMBER(SEARCH(":",I20)),VALUE(LEFT(I20,SEARCH(":",I20)-1))*60+VALUE(MID(I20,SEARCH(":",I20)+1,99)),VALUE(I20))) | K20: 21.09.25 | L20: Swimming New Zealand Short Course Records by Age - user-supplied PDF | N20: NO | O20: YES | P20: Mitchell Donaldson | Q20: 1:01.46 | R20: =IF(Q20="","",IF(ISNUMBER(SEARCH(":",Q20)),VALUE(LEFT(Q20,SEARCH(":",Q20)-1))*60+VALUE(MID(Q20,SEARCH(":",Q20)+1,99)),VALUE(Q20))) | S20: =IF(OR(J20="",R20=""),"",(R20-J20)/R20) | T20: =IF(OR(P20<>"",N20="YES"),"YES","NO") | U20: =IF(AND(O20="YES",T20="YES",S20<>""),COUNTIFS($C$5:$C$424,C20,$S$5:$S$424,">"&S20)+COUNTIFS($C$5:C20,C20,$S$5:S20,S20),"") | V20: =IF(U20="","",C20&"|"&U20) | X20: Next-fastest time supplied in user workbook; swimmer name not yet supplied.
A21: NZ|SCM|M|13|200 IM | B21: SCM | C21: Male | D21: 13 | E21: 200 IM | F21: Grayson Coulter | G21: Grayson Coulter | I21: 2:05.15 | J21: =IF(I21="","",IF(ISNUMBER(SEARCH(":",I21)),VALUE(LEFT(I21,SEARCH(":",I21)-1))*60+VALUE(MID(I21,SEARCH(":",I21)+1,99)),VALUE(I21))) | K21: 25.09.25 | L21: Swimming New Zealand Short Course Records by Age - user-supplied PDF | N21: NO | O21: YES | P21: Ariel Muchirahondo | Q21: 2:12.85 | R21: =IF(Q21="","",IF(ISNUMBER(SEARCH(":",Q21)),VALUE(LEFT(Q21,SEARCH(":",Q21)-1))*60+VALUE(MID(Q21,SEARCH(":",Q21)+1,99)),VALUE(Q21))) | S21: =IF(OR(J21="",R21=""),"",(R21-J21)/R21) | T21: =IF(OR(P21<>"",N21="YES"),"YES","NO") | U21: =IF(AND(O21="YES",T21="YES",S21<>""),COUNTIFS($C$5:$C$424,C21,$S$5:$S$424,">"&S21)+COUNTIFS($C$5:C21,C21,$S$5:S21,S21),"") | V21: =IF(U21="","",C21&"|"&U21) | X21: Next-fastest time supplied in user workbook; swimmer name not yet supplied.
A22: NZ|SCM|M|13|400 IM | B22: SCM | C22: Male | D22: 13 | E22: 400 IM | F22: Mitchell Donaldson | G22: Mitchell Donaldson | I22: 4:35.84 | J22: =IF(I22="","",IF(ISNUMBER(SEARCH(":",I22)),VALUE(LEFT(I22,SEARCH(":",I22)-1))*60+VALUE(MID(I22,SEARCH(":",I22)+1,99)),VALUE(I22))) | K22: 25.09.06 | L22: Swimming New Zealand Short Course Records by Age - user-supplied PDF | N22: NO | O22: YES | Q22: 4:40.81 | R22: =IF(Q22="","",IF(ISNUMBER(SEARCH(":",Q22)),VALUE(LEFT(Q22,SEARCH(":",Q22)-1))*60+VALUE(MID(Q22,SEARCH(":",Q22)+1,99)),VALUE(Q22))) | S22: =IF(OR(J22="",R22=""),"",(R22-J22)/R22) | T22: =IF(OR(P22<>"",N22="YES"),"YES","NO") | U22: =IF(AND(O22="YES",T22="YES",S22<>""),COUNTIFS($C$5:$C$424,C22,$S$5:$S$424,">"&S22)+COUNTIFS($C$5:C22,C22,$S$5:S22,S22),"") | V22: =IF(U22="","",C22&"|"&U22) | X22: Next-fastest time supplied in user workbook; swimmer name not yet supplied.
A23: NZ|SCM|M|14|50 Free | B23: SCM | C23: Male | D23: 14 | E23: 50 Free | F23: Grayson Coulter | G23: Grayson Coulter | I23: 23.11 | J23: =IF(I23="","",IF(ISNUMBER(SEARCH(":",I23)),VALUE(LEFT(I23,SEARCH(":",I23)-1))*60+VALUE(MID(I23,SEARCH(":",I23)+1,99)),VALUE(I23))) | K23: 01.10.26 | L23: Updated through 2026 NZ Short Course Championships | M23: https://swimdadnz.github.io/NZSC_2026/NZSC_2026_meet_editorial_summary_final.html | N23: NO | O23: YES | Q23: 23.55 | R23: =IF(Q23="","",IF(ISNUMBER(SEARCH(":",Q23)),VALUE(LEFT(Q23,SEARCH(":",Q23)-1))*60+VALUE(MID(Q23,SEARCH(":",Q23)+1,99)),VALUE(Q23))) | S23: =IF(OR(J23="",R23=""),"",(R23-J23)/R23) | T23: =IF(OR(P23<>"",N23="YES"),"YES","NO") | U23: =IF(AND(O23="YES",T23="YES",S23<>""),COUNTIFS($C$5:$C$424,C23,$S$5:$S$424,">"&S23)+COUNTIFS($C$5:C23,C23,$S$5:S23,S23),"") | V23: =IF(U23="","",C23&"|"&U23) | W23: NZSC 2026: same swimmer improved own record; next-fastest different-swimmer time retained from supplied dataset. | X23: Next-fastest time supplied in user workbook; swimmer name not yet supplied.
A24: NZ|SCM|M|14|100 Free | B24: SCM | C24: Male | D24: 14 | E24: 100 Free | F24: Grayson Coulter | G24: Grayson Coulter | I24: 50.06 | J24: =IF(I24="","",IF(ISNUMBER(SEARCH(":",I24)),VALUE(LEFT(I24,SEARCH(":",I24)-1))*60+VALUE(MID(I24,SEARCH(":",I24)+1,99)),VALUE(I24))) | K24: 01.10.26 | L24: Updated through 2026 NZ Short Course Championships | M24: https://swimdadnz.github.io/NZSC_2026/NZSC_2026_meet_editorial_summary_final.html | N24: NO | O24: YES | Q24: 51.42 | R24: =IF(Q24="","",IF(ISNUMBER(SEARCH(":",Q24)),VALUE(LEFT(Q24,SEARCH(":",Q24)-1))*60+VALUE(MID(Q24,SEARCH(":",Q24)+1,99)),VALUE(Q24))) | S24: =IF(OR(J24="",R24=""),"",(R24-J24)/R24) | T24: =IF(OR(P24<>"",N24="YES"),"YES","NO") | U24: =IF(AND(O24="YES",T24="YES",S24<>""),COUNTIFS($C$5:$C$424,C24,$S$5:$S$424,">"&S24)+COUNTIFS($C$5:C24,C24,$S$5:S24,S24),"") | V24: =IF(U24="","",C24&"|"&U24) | W24: NZSC 2026: same swimmer improved own record; next-fastest different-swimmer time retained from supplied dataset. | X24: Next-fastest time supplied in user workbook; swimmer name not yet supplied.
A25: NZ|SCM|M|14|200 Free | B25: SCM | C25: Male | D25: 14 | E25: 200 Free | F25: Grayson Coulter | G25: Grayson Coulter | I25: 1:48.13 | J25: =IF(I25="","",IF(ISNUMBER(SEARCH(":",I25)),VALUE(LEFT(I25,SEARCH(":",I25)-1))*60+VALUE(MID(I25,SEARCH(":",I25)+1,99)),VALUE(I25))) | K25: 30.09.26 | L25: Updated through 2026 NZ Short Course Championships | M25: https://swimdadnz.github.io/NZSC_2026/NZSC_2026_meet_editorial_summary_final.html | N25: NO | O25: YES | P25: Leo English | Q25: 1:52.58 | R25: =IF(Q25="","",IF(ISNUMBER(SEARCH(":",Q25)),VALUE(LEFT(Q25,SEARCH(":",Q25)-1))*60+VALUE(MID(Q25,SEARCH(":",Q25)+1,99)),VALUE(Q25))) | S25: =IF(OR(J25="",R25=""),"",(R25-J25)/R25) | T25: =IF(OR(P25<>"",N25="YES"),"YES","NO") | U25: =IF(AND(O25="YES",T25="YES",S25<>""),COUNTIFS($C$5:$C$424,C25,$S$5:$S$424,">"&S25)+COUNTIFS($C$5:C25,C25,$S$5:S25,S25),"") | V25: =IF(U25="","",C25&"|"&U25) | W25: NZSC 2026: same swimmer improved own record; next-fastest different-swimmer time retained from supplied dataset. | X25: Next-fastest time supplied in user workbook; swimmer name not yet supplied.
A26: NZ|SCM|M|14|400 Free | B26: SCM | C26: Male | D26: 14 | E26: 400 Free | F26: Leo English | G26: Leo English | I26: 3:57.62 | J26: =IF(I26="","",IF(ISNUMBER(SEARCH(":",I26)),VALUE(LEFT(I26,SEARCH(":",I26)-1))*60+VALUE(MID(I26,SEARCH(":",I26)+1,99)),VALUE(I26))) | K26: 25.02.24 | L26: Swimming New Zealand Short Course Records by Age - user-supplied PDF | N26: NO | O26: YES | Q26: 3:59.92 | R26: =IF(Q26="","",IF(ISNUMBER(SEARCH(":",Q26)),VALUE(LEFT(Q26,SEARCH(":",Q26)-1))*60+VALUE(MID(Q26,SEARCH(":",Q26)+1,99)),VALUE(Q26))) | S26: =IF(OR(J26="",R26=""),"",(R26-J26)/R26) | T26: =IF(OR(P26<>"",N26="YES"),"YES","NO") | U26: =IF(AND(O26="YES",T26="YES",S26<>""),COUNTIFS($C$5:$C$424,C26,$S$5:$S$424,">"&S26)+COUNTIFS($C$5:C26,C26,$S$5:S26,S26),"") | V26: =IF(U26="","",C26&"|"&U26) | X26: Next-fastest time supplied in user workbook; swimmer name not yet supplied.
A27: NZ|SCM|M|14|800 Free | B27: SCM | C27: Male | D27: 14 | E27: 800 Free | F27: Cameron Burrows | G27: Cameron Burrows | I27: 8:19.31 | J27: =IF(I27="","",IF(ISNUMBER(SEARCH(":",I27)),VALUE(LEFT(I27,SEARCH(":",I27)-1))*60+VALUE(MID(I27,SEARCH(":",I27)+1,99)),VALUE(I27))) | K27: 10.06.06 | L27: Swimming New Zealand Short Course Records by Age - user-supplied PDF | N27: NO | O27: YES | Q27: 8:21.35 | R27: =IF(Q27="","",IF(ISNUMBER(SEARCH(":",Q27)),VALUE(LEFT(Q27,SEARCH(":",Q27)-1))*60+VALUE(MID(Q27,SEARCH(":",Q27)+1,99)),VALUE(Q27))) | S27: =IF(OR(J27="",R27=""),"",(R27-J27)/R27) | T27: =IF(OR(P27<>"",N27="YES"),"YES","NO") | U27: =IF(AND(O27="YES",T27="YES",S27<>""),COUNTIFS($C$5:$C$424,C27,$S$5:$S$424,">"&S27)+COUNTIFS($C$5:C27,C27,$S$5:S27,S27),"") | V27: =IF(U27="","",C27&"|"&U27) | X27: Next-fastest time supplied in user workbook; swimmer name not yet supplied.
A28: NZ|SCM|M|14|1500 Free | B28: SCM | C28: Male | D28: 14 | E28: 1500 Free | F28: Michael Mincham | G28: Michael Mincham | I28: 15:38.51 | J28: =IF(I28="","",IF(ISNUMBER(SEARCH(":",I28)),VALUE(LEFT(I28,SEARCH(":",I28)-1))*60+VALUE(MID(I28,SEARCH(":",I28)+1,99)),VALUE(I28))) | K28: 13.11.10 | L28: Swimming New Zealand Short Course Records by Age - user-supplied PDF | N28: NO | O28: YES | Q28: 15:47.26 | R28: =IF(Q28="","",IF(ISNUMBER(SEARCH(":",Q28)),VALUE(LEFT(Q28,SEARCH(":",Q28)-1))*60+VALUE(MID(Q28,SEARCH(":",Q28)+1,99)),VALUE(Q28))) | S28: =IF(OR(J28="",R28=""),"",(R28-J28)/R28) | T28: =IF(OR(P28<>"",N28="YES"),"YES","NO") | U28: =IF(AND(O28="YES",T28="YES",S28<>""),COUNTIFS($C$5:$C$424,C28,$S$5:$S$424,">"&S28)+COUNTIFS($C$5:C28,C28,$S$5:S28,S28),"") | V28: =IF(U28="","",C28&"|"&U28) | X28: Next-fastest time supplied in user workbook; swimmer name not yet supplied.
A29: NZ|SCM|M|14|50 Back | B29: SCM | C29: Male | D29: 14 | E29: 50 Back | F29: Donald Tian | G29: Donald Tian | I29: 26.20 | J29: =IF(I29="","",IF(ISNUMBER(SEARCH(":",I29)),VALUE(LEFT(I29,SEARCH(":",I29)-1))*60+VALUE(MID(I29,SEARCH(":",I29)+1,99)),VALUE(I29))) | K29: 23.08.24 | L29: Swimming New Zealand Short Course Records by Age - user-supplied PDF | N29: NO | O29: YES | Q29: 26.44 | R29: =IF(Q29="","",IF(ISNUMBER(SEARCH(":",Q29)),VALUE(LEFT(Q29,SEARCH(":",Q29)-1))*60+VALUE(MID(Q29,SEARCH(":",Q29)+1,99)),VALUE(Q29))) | S29: =IF(OR(J29="",R29=""),"",(R29-J29)/R29) | T29: =IF(OR(P29<>"",N29="YES"),"YES","NO") | U29: =IF(AND(O29="YES",T29="YES",S29<>""),COUNTIFS($C$5:$C$424,C29,$S$5:$S$424,">"&S29)+COUNTIFS($C$5:C29,C29,$S$5:S29,S29),"") | V29: =IF(U29="","",C29&"|"&U29) | X29: Next-fastest time supplied in user workbook; swimmer name not yet supplied.
A30: NZ|SCM|M|14|100 Back | B30: SCM | C30: Male | D30: 14 | E30: 100 Back | F30: Corey Main | G30: Corey Main | I30: 56.48 | J30: =IF(I30="","",IF(ISNUMBER(SEARCH(":",I30)),VALUE(LEFT(I30,SEARCH(":",I30)-1))*60+VALUE(MID(I30,SEARCH(":",I30)+1,99)),VALUE(I30))) | K30: 27.09.09 | L30: Swimming New Zealand Short Course Records by Age - user-supplied PDF | N30: NO | O30: YES | Q30: 56.57 | R30: =IF(Q30="","",IF(ISNUMBER(SEARCH(":",Q30)),VALUE(LEFT(Q30,SEARCH(":",Q30)-1))*60+VALUE(MID(Q30,SEARCH(":",Q30)+1,99)),VALUE(Q30))) | S30: =IF(OR(J30="",R30=""),"",(R30-J30)/R30) | T30: =IF(OR(P30<>"",N30="YES"),"YES","NO") | U30: =IF(AND(O30="YES",T30="YES",S30<>""),COUNTIFS($C$5:$C$424,C30,$S$5:$S$424,">"&S30)+COUNTIFS($C$5:C30,C30,$S$5:S30,S30),"") | V30: =IF(U30="","",C30&"|"&U30) | X30: Next-fastest time supplied in user workbook; swimmer name not yet supplied.
A31: NZ|SCM|M|14|200 Back | B31: SCM | C31: Male | D31: 14 | E31: 200 Back | F31: Corey Main | G31: Corey Main | I31: 2:00.71 | J31: =IF(I31="","",IF(ISNUMBER(SEARCH(":",I31)),VALUE(LEFT(I31,SEARCH(":",I31)-1))*60+VALUE(MID(I31,SEARCH(":",I31)+1,99)),VALUE(I31))) | K31: 28.09.09 | L31: Swimming New Zealand Short Course Records by Age - user-supplied PDF | N31: NO | O31: YES | Q31: 2:03.18 | R31: =IF(Q31="","",IF(ISNUMBER(SEARCH(":",Q31)),VALUE(LEFT(Q31,SEARCH(":",Q31)-1))*60+VALUE(MID(Q31,SEARCH(":",Q31)+1,99)),VALUE(Q31))) | S31: =IF(OR(J31="",R31=""),"",(R31-J31)/R31) | T31: =IF(OR(P31<>"",N31="YES"),"YES","NO") | U31: =IF(AND(O31="YES",T31="YES",S31<>""),COUNTIFS($C$5:$C$424,C31,$S$5:$S$424,">"&S31)+COUNTIFS($C$5:C31,C31,$S$5:S31,S31),"") | V31: =IF(U31="","",C31&"|"&U31) | X31: Next-fastest time supplied in user workbook; swimmer name not yet supplied.
A32: NZ|SCM|M|14|50 Breast | B32: SCM | C32: Male | D32: 14 | E32: 50 Breast | F32: Jeffrey Arona-Tuifana'e | G32: Jeffrey Arona-Tuifana'e | I32: 29.54 | J32: =IF(I32="","",IF(ISNUMBER(SEARCH(":",I32)),VALUE(LEFT(I32,SEARCH(":",I32)-1))*60+VALUE(MID(I32,SEARCH(":",I32)+1,99)),VALUE(I32))) | K32: 06.07.09 | L32: Swimming New Zealand Short Course Records by Age - user-supplied PDF | N32: NO | O32: YES | Q32: 29.60 | R32: =IF(Q32="","",IF(ISNUMBER(SEARCH(":",Q32)),VALUE(LEFT(Q32,SEARCH(":",Q32)-1))*60+VALUE(MID(Q32,SEARCH(":",Q32)+1,99)),VALUE(Q32))) | S32: =IF(OR(J32="",R32=""),"",(R32-J32)/R32) | T32: =IF(OR(P32<>"",N32="YES"),"YES","NO") | U32: =IF(AND(O32="YES",T32="YES",S32<>""),COUNTIFS($C$5:$C$424,C32,$S$5:$S$424,">"&S32)+COUNTIFS($C$5:C32,C32,$S$5:S32,S32),"") | V32: =IF(U32="","",C32&"|"&U32) | X32: Next-fastest time supplied in user workbook; swimmer name not yet supplied.
A33: NZ|SCM|M|14|100 Breast | B33: SCM | C33: Male | D33: 14 | E33: 100 Breast | F33: Cameron Karpik | G33: Cameron Karpik | I33: 1:04.11 | J33: =IF(I33="","",IF(ISNUMBER(SEARCH(":",I33)),VALUE(LEFT(I33,SEARCH(":",I33)-1))*60+VALUE(MID(I33,SEARCH(":",I33)+1,99)),VALUE(I33))) | K33: 11.08.23 | L33: Swimming New Zealand Short Course Records by Age - user-supplied PDF | N33: NO | O33: YES | Q33: 1:04.92 | R33: =IF(Q33="","",IF(ISNUMBER(SEARCH(":",Q33)),VALUE(LEFT(Q33,SEARCH(":",Q33)-1))*60+VALUE(MID(Q33,SEARCH(":",Q33)+1,99)),VALUE(Q33))) | S33: =IF(OR(J33="",R33=""),"",(R33-J33)/R33) | T33: =IF(OR(P33<>"",N33="YES"),"YES","NO") | U33: =IF(AND(O33="YES",T33="YES",S33<>""),COUNTIFS($C$5:$C$424,C33,$S$5:$S$424,">"&S33)+COUNTIFS($C$5:C33,C33,$S$5:S33,S33),"") | V33: =IF(U33="","",C33&"|"&U33) | X33: Next-fastest time supplied in user workbook; swimmer name not yet supplied.
A34: NZ|SCM|M|14|200 Breast | B34: SCM | C34: Male | D34: 14 | E34: 200 Breast | F34: Cameron Karpik | G34: Cameron Karpik | I34: 2:20.58 | J34: =IF(I34="","",IF(ISNUMBER(SEARCH(":",I34)),VALUE(LEFT(I34,SEARCH(":",I34)-1))*60+VALUE(MID(I34,SEARCH(":",I34)+1,99)),VALUE(I34))) | K34: 08.08.23 | L34: Swimming New Zealand Short Course Records by Age - user-supplied PDF | N34: NO | O34: YES | Q34: 2:20.67 | R34: =IF(Q34="","",IF(ISNUMBER(SEARCH(":",Q34)),VALUE(LEFT(Q34,SEARCH(":",Q34)-1))*60+VALUE(MID(Q34,SEARCH(":",Q34)+1,99)),VALUE(Q34))) | S34: =IF(OR(J34="",R34=""),"",(R34-J34)/R34) | T34: =IF(OR(P34<>"",N34="YES"),"YES","NO") | U34: =IF(AND(O34="YES",T34="YES",S34<>""),COUNTIFS($C$5:$C$424,C34,$S$5:$S$424,">"&S34)+COUNTIFS($C$5:C34,C34,$S$5:S34,S34),"") | V34: =IF(U34="","",C34&"|"&U34) | X34: Next-fastest time supplied in user workbook; swimmer name not yet supplied.
A35: NZ|SCM|M|14|50 Fly | B35: SCM | C35: Male | D35: 14 | E35: 50 Fly | F35: Grayson Coulter | G35: Grayson Coulter | I35: 25.06 | J35: =IF(I35="","",IF(ISNUMBER(SEARCH(":",I35)),VALUE(LEFT(I35,SEARCH(":",I35)-1))*60+VALUE(MID(I35,SEARCH(":",I35)+1,99)),VALUE(I35))) | K35: 28.09.26 | L35: Updated through 2026 NZ Short Course Championships | M35: https://swimdadnz.github.io/NZSC_2026/NZSC_2026_meet_editorial_summary_final.html | N35: NO | O35: YES | P35: Kento Wangford | Q35: 25.60 | R35: =IF(Q35="","",IF(ISNUMBER(SEARCH(":",Q35)),VALUE(LEFT(Q35,SEARCH(":",Q35)-1))*60+VALUE(MID(Q35,SEARCH(":",Q35)+1,99)),VALUE(Q35))) | S35: =IF(OR(J35="",R35=""),"",(R35-J35)/R35) | T35: =IF(OR(P35<>"",N35="YES"),"YES","NO") | U35: =IF(AND(O35="YES",T35="YES",S35<>""),COUNTIFS($C$5:$C$424,C35,$S$5:$S$424,">"&S35)+COUNTIFS($C$5:C35,C35,$S$5:S35,S35),"") | V35: =IF(U35="","",C35&"|"&U35) | W35: NZSC 2026 update: Kento Wangford 25.60 became next-fastest. | X35: Auto-set from displaced NZ record after NZSC 2026.
A36: NZ|SCM|M|14|100 Fly | B36: SCM | C36: Male | D36: 14 | E36: 100 Fly | F36: Grayson Coulter | G36: Grayson Coulter | I36: 54.92 | J36: =IF(I36="","",IF(ISNUMBER(SEARCH(":",I36)),VALUE(LEFT(I36,SEARCH(":",I36)-1))*60+VALUE(MID(I36,SEARCH(":",I36)+1,99)),VALUE(I36))) | K36: 29.09.26 | L36: Updated through 2026 NZ Short Course Championships | M36: https://swimdadnz.github.io/NZSC_2026/NZSC_2026_meet_editorial_summary_final.html | N36: NO | O36: YES | P36: Jacob Humphries | Q36: 57.22 | R36: =IF(Q36="","",IF(ISNUMBER(SEARCH(":",Q36)),VALUE(LEFT(Q36,SEARCH(":",Q36)-1))*60+VALUE(MID(Q36,SEARCH(":",Q36)+1,99)),VALUE(Q36))) | S36: =IF(OR(J36="",R36=""),"",(R36-J36)/R36) | T36: =IF(OR(P36<>"",N36="YES"),"YES","NO") | U36: =IF(AND(O36="YES",T36="YES",S36<>""),COUNTIFS($C$5:$C$424,C36,$S$5:$S$424,">"&S36)+COUNTIFS($C$5:C36,C36,$S$5:S36,S36),"") | V36: =IF(U36="","",C36&"|"&U36) | W36: NZSC 2026 update: Jacob Humphries 57.22 became next-fastest. | X36: Auto-set from displaced NZ record after NZSC 2026.
A37: NZ|SCM|M|14|200 Fly | B37: SCM | C37: Male | D37: 14 | E37: 200 Fly | F37: Kento Wangford | G37: Kento Wangford | I37: 2:03.00 | J37: =IF(I37="","",IF(ISNUMBER(SEARCH(":",I37)),VALUE(LEFT(I37,SEARCH(":",I37)-1))*60+VALUE(MID(I37,SEARCH(":",I37)+1,99)),VALUE(I37))) | K37: 31.07.26 | L37: Swimming New Zealand Short Course Records by Age - user-supplied PDF | N37: NO | O37: YES | Q37: 2:05.29 | R37: =IF(Q37="","",IF(ISNUMBER(SEARCH(":",Q37)),VALUE(LEFT(Q37,SEARCH(":",Q37)-1))*60+VALUE(MID(Q37,SEARCH(":",Q37)+1,99)),VALUE(Q37))) | S37: =IF(OR(J37="",R37=""),"",(R37-J37)/R37) | T37: =IF(OR(P37<>"",N37="YES"),"YES","NO") | U37: =IF(AND(O37="YES",T37="YES",S37<>""),COUNTIFS($C$5:$C$424,C37,$S$5:$S$424,">"&S37)+COUNTIFS($C$5:C37,C37,$S$5:S37,S37),"") | V37: =IF(U37="","",C37&"|"&U37) | X37: Next-fastest time supplied in user workbook; swimmer name not yet supplied.
A38: NZ|SCM|M|14|100 IM | B38: SCM | C38: Male | D38: 14 | E38: 100 IM | F38: Grayson Coulter | G38: Grayson Coulter | I38: 57.72 | J38: =IF(I38="","",IF(ISNUMBER(SEARCH(":",I38)),VALUE(LEFT(I38,SEARCH(":",I38)-1))*60+VALUE(MID(I38,SEARCH(":",I38)+1,99)),VALUE(I38))) | K38: 27.09.26 | L38: Updated through 2026 NZ Short Course Championships | M38: https://swimdadnz.github.io/NZSC_2026/NZSC_2026_meet_editorial_summary_final.html | N38: NO | O38: YES | P38: Kevin Zhang | Q38: 58.70 | R38: =IF(Q38="","",IF(ISNUMBER(SEARCH(":",Q38)),VALUE(LEFT(Q38,SEARCH(":",Q38)-1))*60+VALUE(MID(Q38,SEARCH(":",Q38)+1,99)),VALUE(Q38))) | S38: =IF(OR(J38="",R38=""),"",(R38-J38)/R38) | T38: =IF(OR(P38<>"",N38="YES"),"YES","NO") | U38: =IF(AND(O38="YES",T38="YES",S38<>""),COUNTIFS($C$5:$C$424,C38,$S$5:$S$424,">"&S38)+COUNTIFS($C$5:C38,C38,$S$5:S38,S38),"") | V38: =IF(U38="","",C38&"|"&U38) | W38: NZSC 2026 update: Kevin Zhang 58.70 became next-fastest. | X38: Auto-set from displaced NZ record after NZSC 2026.
A39: NZ|SCM|M|14|200 IM | B39: SCM | C39: Male | D39: 14 | E39: 200 IM | F39: Ariel Muchirahondo | G39: Ariel Muchirahondo | I39: 2:07.42 | J39: =IF(I39="","",IF(ISNUMBER(SEARCH(":",I39)),VALUE(LEFT(I39,SEARCH(":",I39)-1))*60+VALUE(MID(I39,SEARCH(":",I39)+1,99)),VALUE(I39))) | K39: 12.08.23 | L39: Swimming New Zealand Short Course Records by Age - user-supplied PDF | N39: NO | O39: YES | Q39: 2:08.37 | R39: =IF(Q39="","",IF(ISNUMBER(SEARCH(":",Q39)),VALUE(LEFT(Q39,SEARCH(":",Q39)-1))*60+VALUE(MID(Q39,SEARCH(":",Q39)+1,99)),VALUE(Q39))) | S39: =IF(OR(J39="",R39=""),"",(R39-J39)/R39) | T39: =IF(OR(P39<>"",N39="YES"),"YES","NO") | U39: =IF(AND(O39="YES",T39="YES",S39<>""),COUNTIFS($C$5:$C$424,C39,$S$5:$S$424,">"&S39)+COUNTIFS($C$5:C39,C39,$S$5:S39,S39),"") | V39: =IF(U39="","",C39&"|"&U39) | X39: Next-fastest time supplied in user workbook; swimmer name not yet supplied.
A40: NZ|SCM|M|14|400 IM | B40: SCM | C40: Male | D40: 14 | E40: 400 IM | F40: Ariel Muchirahondo | G40: Ariel Muchirahondo | I40: 4:28.23 | J40: =IF(I40="","",IF(ISNUMBER(SEARCH(":",I40)),VALUE(LEFT(I40,SEARCH(":",I40)-1))*60+VALUE(MID(I40,SEARCH(":",I40)+1,99)),VALUE(I40))) | K40: 10.08.23 | L40: Swimming New Zealand Short Course Records by Age - user-supplied PDF | N40: NO | O40: YES | Q40: 4:30.48 | R40: =IF(Q40="","",IF(ISNUMBER(SEARCH(":",Q40)),VALUE(LEFT(Q40,SEARCH(":",Q40)-1))*60+VALUE(MID(Q40,SEARCH(":",Q40)+1,99)),VALUE(Q40))) | S40: =IF(OR(J40="",R40=""),"",(R40-J40)/R40) | T40: =IF(OR(P40<>"",N40="YES"),"YES","NO") | U40: =IF(AND(O40="YES",T40="YES",S40<>""),COUNTIFS($C$5:$C$424,C40,$S$5:$S$424,">"&S40)+COUNTIFS($C$5:C40,C40,$S$5:S40,S40),"") | V40: =IF(U40="","",C40&"|"&U40) | X40: Next-fastest time supplied in user workbook; swimmer name not yet supplied.
A41: NZ|SCM|M|15|50 Free | B41: SCM | C41: Male | D41: 15 | E41: 50 Free | F41: Charlie Dickison | G41: Charlie Dickison | I41: 22.77 | J41: =IF(I41="","",IF(ISNUMBER(SEARCH(":",I41)),VALUE(LEFT(I41,SEARCH(":",I41)-1))*60+VALUE(MID(I41,SEARCH(":",I41)+1,99)),VALUE(I41))) | K41: 31.07.26 | L41: Swimming New Zealand Short Course Records by Age - user-supplied PDF | N41: NO | O41: YES | Q41: 23.15 | R41: =IF(Q41="","",IF(ISNUMBER(SEARCH(":",Q41)),VALUE(LEFT(Q41,SEARCH(":",Q41)-1))*60+VALUE(MID(Q41,SEARCH(":",Q41)+1,99)),VALUE(Q41))) | S41: =IF(OR(J41="",R41=""),"",(R41-J41)/R41) | T41: =IF(OR(P41<>"",N41="YES"),"YES","NO") | U41: =IF(AND(O41="YES",T41="YES",S41<>""),COUNTIFS($C$5:$C$424,C41,$S$5:$S$424,">"&S41)+COUNTIFS($C$5:C41,C41,$S$5:S41,S41),"") | V41: =IF(U41="","",C41&"|"&U41) | X41: Next-fastest time supplied in user workbook; swimmer name not yet supplied.
A42: NZ|SCM|M|15|100 Free | B42: SCM | C42: Male | D42: 15 | E42: 100 Free | F42: Charlie Dickison | G42: Charlie Dickison | I42: 49.98 | J42: =IF(I42="","",IF(ISNUMBER(SEARCH(":",I42)),VALUE(LEFT(I42,SEARCH(":",I42)-1))*60+VALUE(MID(I42,SEARCH(":",I42)+1,99)),VALUE(I42))) | K42: 31.07.26 | L42: Swimming New Zealand Short Course Records by Age - user-supplied PDF | N42: NO | O42: YES | Q42: 50.29 | R42: =IF(Q42="","",IF(ISNUMBER(SEARCH(":",Q42)),VALUE(LEFT(Q42,SEARCH(":",Q42)-1))*60+VALUE(MID(Q42,SEARCH(":",Q42)+1,99)),VALUE(Q42))) | S42: =IF(OR(J42="",R42=""),"",(R42-J42)/R42) | T42: =IF(OR(P42<>"",N42="YES"),"YES","NO") | U42: =IF(AND(O42="YES",T42="YES",S42<>""),COUNTIFS($C$5:$C$424,C42,$S$5:$S$424,">"&S42)+COUNTIFS($C$5:C42,C42,$S$5:S42,S42),"") | V42: =IF(U42="","",C42&"|"&U42) | X42: Next-fastest time supplied in user workbook; swimmer name not yet supplied.
A43: NZ|SCM|M|15|200 Free | B43: SCM | C43: Male | D43: 15 | E43: 200 Free | F43: Charlie Dickison | G43: Charlie Dickison | I43: 1:50.08 | J43: =IF(I43="","",IF(ISNUMBER(SEARCH(":",I43)),VALUE(LEFT(I43,SEARCH(":",I43)-1))*60+VALUE(MID(I43,SEARCH(":",I43)+1,99)),VALUE(I43))) | K43: 01.08.26 | L43: Swimming New Zealand Short Course Records by Age - user-supplied PDF | N43: NO | O43: YES | Q43: 1:50.39 | R43: =IF(Q43="","",IF(ISNUMBER(SEARCH(":",Q43)),VALUE(LEFT(Q43,SEARCH(":",Q43)-1))*60+VALUE(MID(Q43,SEARCH(":",Q43)+1,99)),VALUE(Q43))) | S43: =IF(OR(J43="",R43=""),"",(R43-J43)/R43) | T43: =IF(OR(P43<>"",N43="YES"),"YES","NO") | U43: =IF(AND(O43="YES",T43="YES",S43<>""),COUNTIFS($C$5:$C$424,C43,$S$5:$S$424,">"&S43)+COUNTIFS($C$5:C43,C43,$S$5:S43,S43),"") | V43: =IF(U43="","",C43&"|"&U43) | X43: Next-fastest time supplied in user workbook; swimmer name not yet supplied.
A44: NZ|SCM|M|15|400 Free | B44: SCM | C44: Male | D44: 15 | E44: 400 Free | F44: Matthew Hutchins | G44: Matthew Hutchins | I44: 3:54.19 | J44: =IF(I44="","",IF(ISNUMBER(SEARCH(":",I44)),VALUE(LEFT(I44,SEARCH(":",I44)-1))*60+VALUE(MID(I44,SEARCH(":",I44)+1,99)),VALUE(I44))) | K44: 05.07.10 | L44: Swimming New Zealand Short Course Records by Age - user-supplied PDF | N44: NO | O44: YES | Q44: 3:55.42 | R44: =IF(Q44="","",IF(ISNUMBER(SEARCH(":",Q44)),VALUE(LEFT(Q44,SEARCH(":",Q44)-1))*60+VALUE(MID(Q44,SEARCH(":",Q44)+1,99)),VALUE(Q44))) | S44: =IF(OR(J44="",R44=""),"",(R44-J44)/R44) | T44: =IF(OR(P44<>"",N44="YES"),"YES","NO") | U44: =IF(AND(O44="YES",T44="YES",S44<>""),COUNTIFS($C$5:$C$424,C44,$S$5:$S$424,">"&S44)+COUNTIFS($C$5:C44,C44,$S$5:S44,S44),"") | V44: =IF(U44="","",C44&"|"&U44) | X44: Next-fastest time supplied in user workbook; swimmer name not yet supplied.
A45: NZ|SCM|M|15|800 Free | B45: SCM | C45: Male | D45: 15 | E45: 800 Free | F45: William Tye | G45: William Tye | I45: 8:07.90 | J45: =IF(I45="","",IF(ISNUMBER(SEARCH(":",I45)),VALUE(LEFT(I45,SEARCH(":",I45)-1))*60+VALUE(MID(I45,SEARCH(":",I45)+1,99)),VALUE(I45))) | K45: 01.10.26 | L45: Updated through 2026 NZ Short Course Championships | M45: https://swimdadnz.github.io/NZSC_2026/NZSC_2026_meet_editorial_summary_final.html | N45: NO | O45: YES | P45: Cameron Burrows | Q45: 8:10.40 | R45: =IF(Q45="","",IF(ISNUMBER(SEARCH(":",Q45)),VALUE(LEFT(Q45,SEARCH(":",Q45)-1))*60+VALUE(MID(Q45,SEARCH(":",Q45)+1,99)),VALUE(Q45))) | S45: =IF(OR(J45="",R45=""),"",(R45-J45)/R45) | T45: =IF(OR(P45<>"",N45="YES"),"YES","NO") | U45: =IF(AND(O45="YES",T45="YES",S45<>""),COUNTIFS($C$5:$C$424,C45,$S$5:$S$424,">"&S45)+COUNTIFS($C$5:C45,C45,$S$5:S45,S45),"") | V45: =IF(U45="","",C45&"|"&U45) | W45: NZSC 2026 update: Cameron Burrows 8:10.40 became next-fastest. | X45: Auto-set from displaced NZ record after NZSC 2026.
A46: NZ|SCM|M|15|1500 Free | B46: SCM | C46: Male | D46: 15 | E46: 1500 Free | F46: William Tye | G46: William Tye | I46: 15:26.42 | J46: =IF(I46="","",IF(ISNUMBER(SEARCH(":",I46)),VALUE(LEFT(I46,SEARCH(":",I46)-1))*60+VALUE(MID(I46,SEARCH(":",I46)+1,99)),VALUE(I46))) | K46: 27.09.26 | L46: Updated through 2026 NZ Short Course Championships | M46: https://swimdadnz.github.io/NZSC_2026/NZSC_2026_meet_editorial_summary_final.html | N46: NO | O46: YES | P46: Michael Mincham | Q46: 15:34.56 | R46: =IF(Q46="","",IF(ISNUMBER(SEARCH(":",Q46)),VALUE(LEFT(Q46,SEARCH(":",Q46)-1))*60+VALUE(MID(Q46,SEARCH(":",Q46)+1,99)),VALUE(Q46))) | S46: =IF(OR(J46="",R46=""),"",(R46-J46)/R46) | T46: =IF(OR(P46<>"",N46="YES"),"YES","NO") | U46: =IF(AND(O46="YES",T46="YES",S46<>""),COUNTIFS($C$5:$C$424,C46,$S$5:$S$424,">"&S46)+COUNTIFS($C$5:C46,C46,$S$5:S46,S46),"") | V46: =IF(U46="","",C46&"|"&U46) | W46: NZSC 2026 update: Michael Mincham 15:34.56 became next-fastest. | X46: Auto-set from displaced NZ record after NZSC 2026.
A47: NZ|SCM|M|15|50 Back | B47: SCM | C47: Male | D47: 15 | E47: 50 Back | F47: Cameron Gray | G47: Cameron Gray | I47: 25.33 | J47: =IF(I47="","",IF(ISNUMBER(SEARCH(":",I47)),VALUE(LEFT(I47,SEARCH(":",I47)-1))*60+VALUE(MID(I47,SEARCH(":",I47)+1,99)),VALUE(I47))) | K47: 28.07.19 | L47: Swimming New Zealand Short Course Records by Age - user-supplied PDF | N47: NO | O47: YES | Q47: 25.67 | R47: =IF(Q47="","",IF(ISNUMBER(SEARCH(":",Q47)),VALUE(LEFT(Q47,SEARCH(":",Q47)-1))*60+VALUE(MID(Q47,SEARCH(":",Q47)+1,99)),VALUE(Q47))) | S47: =IF(OR(J47="",R47=""),"",(R47-J47)/R47) | T47: =IF(OR(P47<>"",N47="YES"),"YES","NO") | U47: =IF(AND(O47="YES",T47="YES",S47<>""),COUNTIFS($C$5:$C$424,C47,$S$5:$S$424,">"&S47)+COUNTIFS($C$5:C47,C47,$S$5:S47,S47),"") | V47: =IF(U47="","",C47&"|"&U47) | X47: Next-fastest time supplied in user workbook; swimmer name not yet supplied.
A48: NZ|SCM|M|15|100 Back | B48: SCM | C48: Male | D48: 15 | E48: 100 Back | F48: Te Rauroha Paki | G48: Te Rauroha Paki | I48: 54.74 | J48: =IF(I48="","",IF(ISNUMBER(SEARCH(":",I48)),VALUE(LEFT(I48,SEARCH(":",I48)-1))*60+VALUE(MID(I48,SEARCH(":",I48)+1,99)),VALUE(I48))) | K48: 21.09.25 | L48: Swimming New Zealand Short Course Records by Age - user-supplied PDF | N48: NO | O48: YES | Q48: 54.91 | R48: =IF(Q48="","",IF(ISNUMBER(SEARCH(":",Q48)),VALUE(LEFT(Q48,SEARCH(":",Q48)-1))*60+VALUE(MID(Q48,SEARCH(":",Q48)+1,99)),VALUE(Q48))) | S48: =IF(OR(J48="",R48=""),"",(R48-J48)/R48) | T48: =IF(OR(P48<>"",N48="YES"),"YES","NO") | U48: =IF(AND(O48="YES",T48="YES",S48<>""),COUNTIFS($C$5:$C$424,C48,$S$5:$S$424,">"&S48)+COUNTIFS($C$5:C48,C48,$S$5:S48,S48),"") | V48: =IF(U48="","",C48&"|"&U48) | X48: Next-fastest time supplied in user workbook; swimmer name not yet supplied.
A49: NZ|SCM|M|15|200 Back | B49: SCM | C49: Male | D49: 15 | E49: 200 Back | F49: Ariel Muchirahondo | G49: Ariel Muchirahondo | I49: 1:57.69 | J49: =IF(I49="","",IF(ISNUMBER(SEARCH(":",I49)),VALUE(LEFT(I49,SEARCH(":",I49)-1))*60+VALUE(MID(I49,SEARCH(":",I49)+1,99)),VALUE(I49))) | K49: 23.08.24 | L49: Swimming New Zealand Short Course Records by Age - user-supplied PDF | N49: NO | O49: YES | Q49: 1:58.58 | R49: =IF(Q49="","",IF(ISNUMBER(SEARCH(":",Q49)),VALUE(LEFT(Q49,SEARCH(":",Q49)-1))*60+VALUE(MID(Q49,SEARCH(":",Q49)+1,99)),VALUE(Q49))) | S49: =IF(OR(J49="",R49=""),"",(R49-J49)/R49) | T49: =IF(OR(P49<>"",N49="YES"),"YES","NO") | U49: =IF(AND(O49="YES",T49="YES",S49<>""),COUNTIFS($C$5:$C$424,C49,$S$5:$S$424,">"&S49)+COUNTIFS($C$5:C49,C49,$S$5:S49,S49),"") | V49: =IF(U49="","",C49&"|"&U49) | X49: Next-fastest time supplied in user workbook; swimmer name not yet supplied.
A50: NZ|SCM|M|15|50 Breast | B50: SCM | C50: Male | D50: 15 | E50: 50 Breast | F50: Jeffrey Arona-Tuifana'e | G50: Jeffrey Arona-Tuifana'e | I50: 28.72 | J50: =IF(I50="","",IF(ISNUMBER(SEARCH(":",I50)),VALUE(LEFT(I50,SEARCH(":",I50)-1))*60+VALUE(MID(I50,SEARCH(":",I50)+1,99)),VALUE(I50))) | K50: 06.07.10 | L50: Swimming New Zealand Short Course Records by Age - user-supplied PDF | N50: NO | O50: YES | Q50: 28.94 | R50: =IF(Q50="","",IF(ISNUMBER(SEARCH(":",Q50)),VALUE(LEFT(Q50,SEARCH(":",Q50)-1))*60+VALUE(MID(Q50,SEARCH(":",Q50)+1,99)),VALUE(Q50))) | S50: =IF(OR(J50="",R50=""),"",(R50-J50)/R50) | T50: =IF(OR(P50<>"",N50="YES"),"YES","NO") | U50: =IF(AND(O50="YES",T50="YES",S50<>""),COUNTIFS($C$5:$C$424,C50,$S$5:$S$424,">"&S50)+COUNTIFS($C$5:C50,C50,$S$5:S50,S50),"") | V50: =IF(U50="","",C50&"|"&U50) | X50: Next-fastest time supplied in user workbook; swimmer name not yet supplied.
A51: NZ|SCM|M|15|100 Breast | B51: SCM | C51: Male | D51: 15 | E51: 100 Breast | F51: Erik Kahr | G51: Erik Kahr | I51: 1:01.86 | J51: =IF(I51="","",IF(ISNUMBER(SEARCH(":",I51)),VALUE(LEFT(I51,SEARCH(":",I51)-1))*60+VALUE(MID(I51,SEARCH(":",I51)+1,99)),VALUE(I51))) | K51: 07.08.11 | L51: Swimming New Zealand Short Course Records by Age - user-supplied PDF | N51: NO | O51: YES | Q51: 1:02.23 | R51: =IF(Q51="","",IF(ISNUMBER(SEARCH(":",Q51)),VALUE(LEFT(Q51,SEARCH(":",Q51)-1))*60+VALUE(MID(Q51,SEARCH(":",Q51)+1,99)),VALUE(Q51))) | S51: =IF(OR(J51="",R51=""),"",(R51-J51)/R51) | T51: =IF(OR(P51<>"",N51="YES"),"YES","NO") | U51: =IF(AND(O51="YES",T51="YES",S51<>""),COUNTIFS($C$5:$C$424,C51,$S$5:$S$424,">"&S51)+COUNTIFS($C$5:C51,C51,$S$5:S51,S51),"") | V51: =IF(U51="","",C51&"|"&U51) | X51: Next-fastest time supplied in user workbook; swimmer name not yet supplied.
A52: NZ|SCM|M|15|200 Breast | B52: SCM | C52: Male | D52: 15 | E52: 200 Breast | F52: Jacob Story | G52: Jacob Story | I52: 2:14.31 | J52: =IF(I52="","",IF(ISNUMBER(SEARCH(":",I52)),VALUE(LEFT(I52,SEARCH(":",I52)-1))*60+VALUE(MID(I52,SEARCH(":",I52)+1,99)),VALUE(I52))) | K52: 08.08.23 | L52: Swimming New Zealand Short Course Records by Age - user-supplied PDF | N52: NO | O52: YES | Q52: 2:14.60 | R52: =IF(Q52="","",IF(ISNUMBER(SEARCH(":",Q52)),VALUE(LEFT(Q52,SEARCH(":",Q52)-1))*60+VALUE(MID(Q52,SEARCH(":",Q52)+1,99)),VALUE(Q52))) | S52: =IF(OR(J52="",R52=""),"",(R52-J52)/R52) | T52: =IF(OR(P52<>"",N52="YES"),"YES","NO") | U52: =IF(AND(O52="YES",T52="YES",S52<>""),COUNTIFS($C$5:$C$424,C52,$S$5:$S$424,">"&S52)+COUNTIFS($C$5:C52,C52,$S$5:S52,S52),"") | V52: =IF(U52="","",C52&"|"&U52) | X52: Next-fastest time supplied in user workbook; swimmer name not yet supplied.
A53: NZ|SCM|M|15|50 Fly | B53: SCM | C53: Male | D53: 15 | E53: 50 Fly | F53: Jacob Story | G53: Jacob Story | I53: 24.84 | J53: =IF(I53="","",IF(ISNUMBER(SEARCH(":",I53)),VALUE(LEFT(I53,SEARCH(":",I53)-1))*60+VALUE(MID(I53,SEARCH(":",I53)+1,99)),VALUE(I53))) | K53: 09.08.23 | L53: Swimming New Zealand Short Course Records by Age - user-supplied PDF | N53: NO | O53: YES | Q53: 25.10 | R53: =IF(Q53="","",IF(ISNUMBER(SEARCH(":",Q53)),VALUE(LEFT(Q53,SEARCH(":",Q53)-1))*60+VALUE(MID(Q53,SEARCH(":",Q53)+1,99)),VALUE(Q53))) | S53: =IF(OR(J53="",R53=""),"",(R53-J53)/R53) | T53: =IF(OR(P53<>"",N53="YES"),"YES","NO") | U53: =IF(AND(O53="YES",T53="YES",S53<>""),COUNTIFS($C$5:$C$424,C53,$S$5:$S$424,">"&S53)+COUNTIFS($C$5:C53,C53,$S$5:S53,S53),"") | V53: =IF(U53="","",C53&"|"&U53) | X53: Next-fastest time supplied in user workbook; swimmer name not yet supplied.
A54: NZ|SCM|M|15|100 Fly | B54: SCM | C54: Male | D54: 15 | E54: 100 Fly | F54: Michael Chen | G54: Michael Chen | I54: 54.70 | J54: =IF(I54="","",IF(ISNUMBER(SEARCH(":",I54)),VALUE(LEFT(I54,SEARCH(":",I54)-1))*60+VALUE(MID(I54,SEARCH(":",I54)+1,99)),VALUE(I54))) | K54: 01.08.26 | L54: Swimming New Zealand Short Course Records by Age - user-supplied PDF | N54: NO | O54: YES | Q54: 55.75 | R54: =IF(Q54="","",IF(ISNUMBER(SEARCH(":",Q54)),VALUE(LEFT(Q54,SEARCH(":",Q54)-1))*60+VALUE(MID(Q54,SEARCH(":",Q54)+1,99)),VALUE(Q54))) | S54: =IF(OR(J54="",R54=""),"",(R54-J54)/R54) | T54: =IF(OR(P54<>"",N54="YES"),"YES","NO") | U54: =IF(AND(O54="YES",T54="YES",S54<>""),COUNTIFS($C$5:$C$424,C54,$S$5:$S$424,">"&S54)+COUNTIFS($C$5:C54,C54,$S$5:S54,S54),"") | V54: =IF(U54="","",C54&"|"&U54) | X54: Next-fastest time supplied in user workbook; swimmer name not yet supplied.
A55: NZ|SCM|M|15|200 Fly | B55: SCM | C55: Male | D55: 15 | E55: 200 Fly | F55: Ariel Muchirahondo | G55: Ariel Muchirahondo | I55: 1:58.61 | J55: =IF(I55="","",IF(ISNUMBER(SEARCH(":",I55)),VALUE(LEFT(I55,SEARCH(":",I55)-1))*60+VALUE(MID(I55,SEARCH(":",I55)+1,99)),VALUE(I55))) | K55: 23.08.24 | L55: Swimming New Zealand Short Course Records by Age - user-supplied PDF | N55: NO | O55: YES | P55: Cameron Burrows | Q55: 2:03.08 | R55: =IF(Q55="","",IF(ISNUMBER(SEARCH(":",Q55)),VALUE(LEFT(Q55,SEARCH(":",Q55)-1))*60+VALUE(MID(Q55,SEARCH(":",Q55)+1,99)),VALUE(Q55))) | S55: =IF(OR(J55="",R55=""),"",(R55-J55)/R55) | T55: =IF(OR(P55<>"",N55="YES"),"YES","NO") | U55: =IF(AND(O55="YES",T55="YES",S55<>""),COUNTIFS($C$5:$C$424,C55,$S$5:$S$424,">"&S55)+COUNTIFS($C$5:C55,C55,$S$5:S55,S55),"") | V55: =IF(U55="","",C55&"|"&U55) | X55: Next-fastest time supplied in user workbook; swimmer name not yet supplied.
A56: NZ|SCM|M|15|100 IM | B56: SCM | C56: Male | D56: 15 | E56: 100 IM | F56: Jacob Story | G56: Jacob Story | I56: 56.33 | J56: =IF(I56="","",IF(ISNUMBER(SEARCH(":",I56)),VALUE(LEFT(I56,SEARCH(":",I56)-1))*60+VALUE(MID(I56,SEARCH(":",I56)+1,99)),VALUE(I56))) | K56: 08.08.23 | L56: Swimming New Zealand Short Course Records by Age - user-supplied PDF | N56: NO | O56: YES | Q56: 57.34 | R56: =IF(Q56="","",IF(ISNUMBER(SEARCH(":",Q56)),VALUE(LEFT(Q56,SEARCH(":",Q56)-1))*60+VALUE(MID(Q56,SEARCH(":",Q56)+1,99)),VALUE(Q56))) | S56: =IF(OR(J56="",R56=""),"",(R56-J56)/R56) | T56: =IF(OR(P56<>"",N56="YES"),"YES","NO") | U56: =IF(AND(O56="YES",T56="YES",S56<>""),COUNTIFS($C$5:$C$424,C56,$S$5:$S$424,">"&S56)+COUNTIFS($C$5:C56,C56,$S$5:S56,S56),"") | V56: =IF(U56="","",C56&"|"&U56) | X56: Next-fastest time supplied in user workbook; swimmer name not yet supplied.
A57: NZ|SCM|M|15|200 IM | B57: SCM | C57: Male | D57: 15 | E57: 200 IM | F57: Kevin Zhang | G57: Kevin Zhang | I57: 2:02.86 | J57: =IF(I57="","",IF(ISNUMBER(SEARCH(":",I57)),VALUE(LEFT(I57,SEARCH(":",I57)-1))*60+VALUE(MID(I57,SEARCH(":",I57)+1,99)),VALUE(I57))) | K57: 26.08.22 | L57: Swimming New Zealand Short Course Records by Age - user-supplied PDF | N57: NO | O57: YES | Q57: 2:03.83 | R57: =IF(Q57="","",IF(ISNUMBER(SEARCH(":",Q57)),VALUE(LEFT(Q57,SEARCH(":",Q57)-1))*60+VALUE(MID(Q57,SEARCH(":",Q57)+1,99)),VALUE(Q57))) | S57: =IF(OR(J57="",R57=""),"",(R57-J57)/R57) | T57: =IF(OR(P57<>"",N57="YES"),"YES","NO") | U57: =IF(AND(O57="YES",T57="YES",S57<>""),COUNTIFS($C$5:$C$424,C57,$S$5:$S$424,">"&S57)+COUNTIFS($C$5:C57,C57,$S$5:S57,S57),"") | V57: =IF(U57="","",C57&"|"&U57) | X57: Next-fastest time supplied in user workbook; swimmer name not yet supplied.
A58: NZ|SCM|M|15|400 IM | B58: SCM | C58: Male | D58: 15 | E58: 400 IM | F58: Anthony van der Kraay | G58: Anthony van der Kraay | I58: 4:19.83 | J58: =IF(I58="","",IF(ISNUMBER(SEARCH(":",I58)),VALUE(LEFT(I58,SEARCH(":",I58)-1))*60+VALUE(MID(I58,SEARCH(":",I58)+1,99)),VALUE(I58))) | K58: 19.09.96 | L58: Swimming New Zealand Short Course Records by Age - user-supplied PDF | N58: NO | O58: YES | Q58: 4:20.24 | R58: =IF(Q58="","",IF(ISNUMBER(SEARCH(":",Q58)),VALUE(LEFT(Q58,SEARCH(":",Q58)-1))*60+VALUE(MID(Q58,SEARCH(":",Q58)+1,99)),VALUE(Q58))) | S58: =IF(OR(J58="",R58=""),"",(R58-J58)/R58) | T58: =IF(OR(P58<>"",N58="YES"),"YES","NO") | U58: =IF(AND(O58="YES",T58="YES",S58<>""),COUNTIFS($C$5:$C$424,C58,$S$5:$S$424,">"&S58)+COUNTIFS($C$5:C58,C58,$S$5:S58,S58),"") | V58: =IF(U58="","",C58&"|"&U58) | X58: Next-fastest time supplied in user workbook; swimmer name not yet supplied.
A59: NZ|SCM|M|16|50 Free | B59: SCM | C59: Male | D59: 16 | E59: 50 Free | F59: Michael Pickett | G59: Michael Pickett | I59: 22.31 | J59: =IF(I59="","",IF(ISNUMBER(SEARCH(":",I59)),VALUE(LEFT(I59,SEARCH(":",I59)-1))*60+VALUE(MID(I59,SEARCH(":",I59)+1,99)),VALUE(I59))) | K59: 17.08.18 | L59: Swimming New Zealand Short Course Records by Age - user-supplied PDF | N59: NO | O59: YES | Q59: 22.53 | R59: =IF(Q59="","",IF(ISNUMBER(SEARCH(":",Q59)),VALUE(LEFT(Q59,SEARCH(":",Q59)-1))*60+VALUE(MID(Q59,SEARCH(":",Q59)+1,99)),VALUE(Q59))) | S59: =IF(OR(J59="",R59=""),"",(R59-J59)/R59) | T59: =IF(OR(P59<>"",N59="YES"),"YES","NO") | U59: =IF(AND(O59="YES",T59="YES",S59<>""),COUNTIFS($C$5:$C$424,C59,$S$5:$S$424,">"&S59)+COUNTIFS($C$5:C59,C59,$S$5:S59,S59),"") | V59: =IF(U59="","",C59&"|"&U59) | X59: Next-fastest time supplied in user workbook; swimmer name not yet supplied.
A60: NZ|SCM|M|16|100 Free | B60: SCM | C60: Male | D60: 16 | E60: 100 Free | F60: Sam McKenzie | G60: Sam McKenzie | I60: 49.70 | J60: =IF(I60="","",IF(ISNUMBER(SEARCH(":",I60)),VALUE(LEFT(I60,SEARCH(":",I60)-1))*60+VALUE(MID(I60,SEARCH(":",I60)+1,99)),VALUE(I60))) | K60: 26.09.15 | L60: Swimming New Zealand Short Course Records by Age - user-supplied PDF | N60: NO | O60: YES | Q60: 49.71 | R60: =IF(Q60="","",IF(ISNUMBER(SEARCH(":",Q60)),VALUE(LEFT(Q60,SEARCH(":",Q60)-1))*60+VALUE(MID(Q60,SEARCH(":",Q60)+1,99)),VALUE(Q60))) | S60: =IF(OR(J60="",R60=""),"",(R60-J60)/R60) | T60: =IF(OR(P60<>"",N60="YES"),"YES","NO") | U60: =IF(AND(O60="YES",T60="YES",S60<>""),COUNTIFS($C$5:$C$424,C60,$S$5:$S$424,">"&S60)+COUNTIFS($C$5:C60,C60,$S$5:S60,S60),"") | V60: =IF(U60="","",C60&"|"&U60) | X60: Next-fastest time supplied in user workbook; swimmer name not yet supplied.
A61: NZ|SCM|M|16|200 Free | B61: SCM | C61: Male | D61: 16 | E61: 200 Free | F61: Ariel Muchirahondo | G61: Ariel Muchirahondo | I61: 1:47.09 | J61: =IF(I61="","",IF(ISNUMBER(SEARCH(":",I61)),VALUE(LEFT(I61,SEARCH(":",I61)-1))*60+VALUE(MID(I61,SEARCH(":",I61)+1,99)),VALUE(I61))) | K61: 30.01.26 | L61: Swimming New Zealand Short Course Records by Age - user-supplied PDF | N61: NO | O61: YES | Q61: 1:48.53 | R61: =IF(Q61="","",IF(ISNUMBER(SEARCH(":",Q61)),VALUE(LEFT(Q61,SEARCH(":",Q61)-1))*60+VALUE(MID(Q61,SEARCH(":",Q61)+1,99)),VALUE(Q61))) | S61: =IF(OR(J61="",R61=""),"",(R61-J61)/R61) | T61: =IF(OR(P61<>"",N61="YES"),"YES","NO") | U61: =IF(AND(O61="YES",T61="YES",S61<>""),COUNTIFS($C$5:$C$424,C61,$S$5:$S$424,">"&S61)+COUNTIFS($C$5:C61,C61,$S$5:S61,S61),"") | V61: =IF(U61="","",C61&"|"&U61) | X61: Next-fastest time supplied in user workbook; swimmer name not yet supplied.
A62: NZ|SCM|M|16|400 Free | B62: SCM | C62: Male | D62: 16 | E62: 400 Free | F62: Danyon Loader | G62: Danyon Loader | I62: 3:43.64 | J62: =IF(I62="","",IF(ISNUMBER(SEARCH(":",I62)),VALUE(LEFT(I62,SEARCH(":",I62)-1))*60+VALUE(MID(I62,SEARCH(":",I62)+1,99)),VALUE(I62))) | K62: 01.02.92 | L62: Swimming New Zealand Short Course Records by Age - user-supplied PDF | N62: NO | O62: YES | Q62: 3:48.92 | R62: =IF(Q62="","",IF(ISNUMBER(SEARCH(":",Q62)),VALUE(LEFT(Q62,SEARCH(":",Q62)-1))*60+VALUE(MID(Q62,SEARCH(":",Q62)+1,99)),VALUE(Q62))) | S62: =IF(OR(J62="",R62=""),"",(R62-J62)/R62) | T62: =IF(OR(P62<>"",N62="YES"),"YES","NO") | U62: =IF(AND(O62="YES",T62="YES",S62<>""),COUNTIFS($C$5:$C$424,C62,$S$5:$S$424,">"&S62)+COUNTIFS($C$5:C62,C62,$S$5:S62,S62),"") | V62: =IF(U62="","",C62&"|"&U62) | X62: Next-fastest time supplied in user workbook; swimmer name not yet supplied.
A63: NZ|SCM|M|16|800 Free | B63: SCM | C63: Male | D63: 16 | E63: 800 Free | F63: Danyon Loader | G63: Danyon Loader | I63: 7:57.08 | J63: =IF(I63="","",IF(ISNUMBER(SEARCH(":",I63)),VALUE(LEFT(I63,SEARCH(":",I63)-1))*60+VALUE(MID(I63,SEARCH(":",I63)+1,99)),VALUE(I63))) | K63: 02.02.92 | L63: Swimming New Zealand Short Course Records by Age - user-supplied PDF | N63: NO | O63: YES | Q63: 8:06.80 | R63: =IF(Q63="","",IF(ISNUMBER(SEARCH(":",Q63)),VALUE(LEFT(Q63,SEARCH(":",Q63)-1))*60+VALUE(MID(Q63,SEARCH(":",Q63)+1,99)),VALUE(Q63))) | S63: =IF(OR(J63="",R63=""),"",(R63-J63)/R63) | T63: =IF(OR(P63<>"",N63="YES"),"YES","NO") | U63: =IF(AND(O63="YES",T63="YES",S63<>""),COUNTIFS($C$5:$C$424,C63,$S$5:$S$424,">"&S63)+COUNTIFS($C$5:C63,C63,$S$5:S63,S63),"") | V63: =IF(U63="","",C63&"|"&U63) | X63: Next-fastest time supplied in user workbook; swimmer name not yet supplied.
A64: NZ|SCM|M|16|1500 Free | B64: SCM | C64: Male | D64: 16 | E64: 1500 Free | F64: Danyon Loader | G64: Danyon Loader | I64: 14:54.38 | J64: =IF(I64="","",IF(ISNUMBER(SEARCH(":",I64)),VALUE(LEFT(I64,SEARCH(":",I64)-1))*60+VALUE(MID(I64,SEARCH(":",I64)+1,99)),VALUE(I64))) | K64: 02.02.92 | L64: Swimming New Zealand Short Course Records by Age - user-supplied PDF | N64: NO | O64: YES | Q64: 15:17.91 | R64: =IF(Q64="","",IF(ISNUMBER(SEARCH(":",Q64)),VALUE(LEFT(Q64,SEARCH(":",Q64)-1))*60+VALUE(MID(Q64,SEARCH(":",Q64)+1,99)),VALUE(Q64))) | S64: =IF(OR(J64="",R64=""),"",(R64-J64)/R64) | T64: =IF(OR(P64<>"",N64="YES"),"YES","NO") | U64: =IF(AND(O64="YES",T64="YES",S64<>""),COUNTIFS($C$5:$C$424,C64,$S$5:$S$424,">"&S64)+COUNTIFS($C$5:C64,C64,$S$5:S64,S64),"") | V64: =IF(U64="","",C64&"|"&U64) | X64: Next-fastest time supplied in user workbook; swimmer name not yet supplied.
A65: NZ|SCM|M|16|50 Back | B65: SCM | C65: Male | D65: 16 | E65: 50 Back | F65: Bruce Shen | G65: Bruce Shen | I65: 24.47 | J65: =IF(I65="","",IF(ISNUMBER(SEARCH(":",I65)),VALUE(LEFT(I65,SEARCH(":",I65)-1))*60+VALUE(MID(I65,SEARCH(":",I65)+1,99)),VALUE(I65))) | K65: 24.09.25 | L65: Swimming New Zealand Short Course Records by Age - user-supplied PDF | N65: NO | O65: YES | Q65: 25.05 | R65: =IF(Q65="","",IF(ISNUMBER(SEARCH(":",Q65)),VALUE(LEFT(Q65,SEARCH(":",Q65)-1))*60+VALUE(MID(Q65,SEARCH(":",Q65)+1,99)),VALUE(Q65))) | S65: =IF(OR(J65="",R65=""),"",(R65-J65)/R65) | T65: =IF(OR(P65<>"",N65="YES"),"YES","NO") | U65: =IF(AND(O65="YES",T65="YES",S65<>""),COUNTIFS($C$5:$C$424,C65,$S$5:$S$424,">"&S65)+COUNTIFS($C$5:C65,C65,$S$5:S65,S65),"") | V65: =IF(U65="","",C65&"|"&U65) | X65: Next-fastest time supplied in user workbook; swimmer name not yet supplied.
A66: NZ|SCM|M|16|100 Back | B66: SCM | C66: Male | D66: 16 | E66: 100 Back | F66: Corey Main | G66: Corey Main | I66: 53.53 | J66: =IF(I66="","",IF(ISNUMBER(SEARCH(":",I66)),VALUE(LEFT(I66,SEARCH(":",I66)-1))*60+VALUE(MID(I66,SEARCH(":",I66)+1,99)),VALUE(I66))) | K66: 11.09.11 | L66: Swimming New Zealand Short Course Records by Age - user-supplied PDF | N66: NO | O66: YES | Q66: 53.93 | R66: =IF(Q66="","",IF(ISNUMBER(SEARCH(":",Q66)),VALUE(LEFT(Q66,SEARCH(":",Q66)-1))*60+VALUE(MID(Q66,SEARCH(":",Q66)+1,99)),VALUE(Q66))) | S66: =IF(OR(J66="",R66=""),"",(R66-J66)/R66) | T66: =IF(OR(P66<>"",N66="YES"),"YES","NO") | U66: =IF(AND(O66="YES",T66="YES",S66<>""),COUNTIFS($C$5:$C$424,C66,$S$5:$S$424,">"&S66)+COUNTIFS($C$5:C66,C66,$S$5:S66,S66),"") | V66: =IF(U66="","",C66&"|"&U66) | X66: Next-fastest time supplied in user workbook; swimmer name not yet supplied.
A67: NZ|SCM|M|16|200 Back | B67: SCM | C67: Male | D67: 16 | E67: 200 Back | F67: Ariel Muchirahondo | G67: Ariel Muchirahondo | I67: 1:55.38 | J67: =IF(I67="","",IF(ISNUMBER(SEARCH(":",I67)),VALUE(LEFT(I67,SEARCH(":",I67)-1))*60+VALUE(MID(I67,SEARCH(":",I67)+1,99)),VALUE(I67))) | K67: 26.07.25 | L67: Swimming New Zealand Short Course Records by Age - user-supplied PDF | N67: NO | O67: YES | Q67: 1:55.44 | R67: =IF(Q67="","",IF(ISNUMBER(SEARCH(":",Q67)),VALUE(LEFT(Q67,SEARCH(":",Q67)-1))*60+VALUE(MID(Q67,SEARCH(":",Q67)+1,99)),VALUE(Q67))) | S67: =IF(OR(J67="",R67=""),"",(R67-J67)/R67) | T67: =IF(OR(P67<>"",N67="YES"),"YES","NO") | U67: =IF(AND(O67="YES",T67="YES",S67<>""),COUNTIFS($C$5:$C$424,C67,$S$5:$S$424,">"&S67)+COUNTIFS($C$5:C67,C67,$S$5:S67,S67),"") | V67: =IF(U67="","",C67&"|"&U67) | X67: Next-fastest time supplied in user workbook; swimmer name not yet supplied.
... A85: NZ|SCM|M|17|200 Back | B85: SCM | C85: Male | D85: 17 | E85: 200 Back | F85: Corey Main | G85: Corey Main | I85: 1:54.39 | J85: =IF(I85="","",IF(ISNUMBER(SEARCH(":",I85)),VALUE(LEFT(I85,SEARCH(":",I85)-1))*60+VALUE(MID(I85,SEARCH(":",I85)+1,99)),VALUE(I85))) | K85: 04.10.12 | L85: Swimming New Zealand Short Course Records by Age - user-supplied PDF | N85: NO | O85: YES | Q85: 1:55.95 | R85: =IF(Q85="","",IF(ISNUMBER(SEARCH(":",Q85)),VALUE(LEFT(Q85,SEARCH(":",Q85)-1))*60+VALUE(MID(Q85,SEARCH(":",Q85)+1,99)),VALUE(Q85))) | S85: =IF(OR(J85="",R85=""),"",(R85-J85)/R85) | T85: =IF(OR(P85<>"",N85="YES"),"YES","NO") | U85: =IF(AND(O85="YES",T85="YES",S85<>""),COUNTIFS($C$5:$C$424,C85,$S$5:$S$424,">"&S85)+COUNTIFS($C$5:C85,C85,$S$5:S85,S85),"") | V85: =IF(U85="","",C85&"|"&U85) | X85: Next-fastest time supplied in user workbook; swimmer name not yet supplied.
A86: NZ|SCM|M|17|50 Breast | B86: SCM | C86: Male | D86: 17 | E86: 50 Breast | F86: Roman Anderson | G86: Roman Anderson | I86: 27.14 | J86: =IF(I86="","",IF(ISNUMBER(SEARCH(":",I86)),VALUE(LEFT(I86,SEARCH(":",I86)-1))*60+VALUE(MID(I86,SEARCH(":",I86)+1,99)),VALUE(I86))) | K86: 29.09.26 | L86: Updated through 2026 NZ Short Course Championships | M86: https://swimdadnz.github.io/NZSC_2026/NZSC_2026_meet_editorial_summary_final.html | N86: NO | O86: YES | Q86: 27.90 | R86: =IF(Q86="","",IF(ISNUMBER(SEARCH(":",Q86)),VALUE(LEFT(Q86,SEARCH(":",Q86)-1))*60+VALUE(MID(Q86,SEARCH(":",Q86)+1,99)),VALUE(Q86))) | S86: =IF(OR(J86="",R86=""),"",(R86-J86)/R86) | T86: =IF(OR(P86<>"",N86="YES"),"YES","NO") | U86: =IF(AND(O86="YES",T86="YES",S86<>""),COUNTIFS($C$5:$C$424,C86,$S$5:$S$424,">"&S86)+COUNTIFS($C$5:C86,C86,$S$5:S86,S86),"") | V86: =IF(U86="","",C86&"|"&U86) | W86: NZSC 2026: same swimmer improved own record; next-fastest different-swimmer time retained from supplied dataset. | X86: Next-fastest time supplied in user workbook; swimmer name not yet supplied.
A87: NZ|SCM|M|17|100 Breast | B87: SCM | C87: Male | D87: 17 | E87: 100 Breast | F87: Roman Anderson | G87: Roman Anderson | I87: 1:00.01 | J87: =IF(I87="","",IF(ISNUMBER(SEARCH(":",I87)),VALUE(LEFT(I87,SEARCH(":",I87)-1))*60+VALUE(MID(I87,SEARCH(":",I87)+1,99)),VALUE(I87))) | K87: 30.09.26 | L87: Updated through 2026 NZ Short Course Championships | M87: https://swimdadnz.github.io/NZSC_2026/NZSC_2026_meet_editorial_summary_final.html | N87: NO | O87: YES | P87: Erik Kahr | Q87: 1:00.77 | R87: =IF(Q87="","",IF(ISNUMBER(SEARCH(":",Q87)),VALUE(LEFT(Q87,SEARCH(":",Q87)-1))*60+VALUE(MID(Q87,SEARCH(":",Q87)+1,99)),VALUE(Q87))) | S87: =IF(OR(J87="",R87=""),"",(R87-J87)/R87) | T87: =IF(OR(P87<>"",N87="YES"),"YES","NO") | U87: =IF(AND(O87="YES",T87="YES",S87<>""),COUNTIFS($C$5:$C$424,C87,$S$5:$S$424,">"&S87)+COUNTIFS($C$5:C87,C87,$S$5:S87,S87),"") | V87: =IF(U87="","",C87&"|"&U87) | W87: NZSC 2026 update: Erik Kahr 1:00.77 became next-fastest. | X87: Auto-set from displaced NZ record after NZSC 2026.
A88: NZ|SCM|M|17|200 Breast | B88: SCM | C88: Male | D88: 17 | E88: 200 Breast | F88: Jackson Kennard | G88: Jackson Kennard | I88: 2:11.88 | J88: =IF(I88="","",IF(ISNUMBER(SEARCH(":",I88)),VALUE(LEFT(I88,SEARCH(":",I88)-1))*60+VALUE(MID(I88,SEARCH(":",I88)+1,99)),VALUE(I88))) | K88: 08.08.23 | L88: Swimming New Zealand Short Course Records by Age - user-supplied PDF | N88: NO | O88: YES | Q88: 2:13.09 | R88: =IF(Q88="","",IF(ISNUMBER(SEARCH(":",Q88)),VALUE(LEFT(Q88,SEARCH(":",Q88)-1))*60+VALUE(MID(Q88,SEARCH(":",Q88)+1,99)),VALUE(Q88))) | S88: =IF(OR(J88="",R88=""),"",(R88-J88)/R88) | T88: =IF(OR(P88<>"",N88="YES"),"YES","NO") | U88: =IF(AND(O88="YES",T88="YES",S88<>""),COUNTIFS($C$5:$C$424,C88,$S$5:$S$424,">"&S88)+COUNTIFS($C$5:C88,C88,$S$5:S88,S88),"") | V88: =IF(U88="","",C88&"|"&U88) | X88: Next-fastest time supplied in user workbook; swimmer name not yet supplied.
